Workbook

Sheet AGRICORP
C1: 2022 | D1: 2021 | E1: 2020 | F1: 2019 | I1: Comptes de gestion
A2: 10100000 | B2: Capital | C2: =IF(A2=A1,0,SUMIFS(BLG1222!$I:$I,BLG1222!$A:$A,"agricorp",BLG1222!$D:$D,A:A)) -> 0 | D2: -10000000 | E2: -2000000 | F2: -2000000 | I2: 10100000 | J2: Capital
A3: 11900000 | B3: RAN débiteur | C3: =IF(A3=A2,0,SUMIFS(BLG1222!$I:$I,BLG1222!$A:$A,"agricorp",BLG1222!$D:$D,A:A)) -> 0 | D3: 2419584.2 | E3: 2419584.2 | F3: 2106451.2 | I3: 11900000 | J3: RAN débiteur
A4: 12000000 | B4: Resultat net de l'exercice benefice | C4: =IF(A4=A3,0,SUMIFS(BLG1222!$I:$I,BLG1222!$A:$A,"agricorp",BLG1222!$D:$D,A:A)) -> 0 | D4: 280428.55 | I4: 12000000 | J4: Resultat net de l'exercice benefice
A5: 12900000 | B5: Resultat net de exercice perte | C5: =IF(A5=A4,0,SUMIFS(BLG1222!$I:$I,BLG1222!$A:$A,"agricorp",BLG1222!$D:$D,A:A)) -> 0 | I5: 12900000 | J5: Resultat net de exercice perte
A6: 20400000 | B6: Logiciels informatiques & assimilés | C6: =IF(A6=A5,0,SUMIFS(BLG1222!$I:$I,BLG1222!$A:$A,"agricorp",BLG1222!$D:$D,A:A)) -> 0 | I6: 20400000 | J6: Logiciels informatiques & assimilés
A7: 21500000 | B7: AAI batiments | C7: =IF(A7=A6,0,SUMIFS(BLG1222!$I:$I,BLG1222!$A:$A,"agricorp",BLG1222!$D:$D,A:A)) -> 0 | D7: 3128790 | I7: 21500000 | J7: AAI batiments
A8: 21510000 | B8: AAI-Autres que bâtiments | C8: =IF(A8=A7,0,SUMIFS(BLG1222!$I:$I,BLG1222!$A:$A,"agricorp",BLG1222!$D:$D,A:A)) -> 0 | D8: 2808000 | I8: 21510000 | J8: AAI-Autres que bâtiments
A9: 21800000 | B9: Matériels et mob de logement | C9: =IF(A9=A8,0,SUMIFS(BLG1222!$I:$I,BLG1222!$A:$A,"agricorp",BLG1222!$D:$D,A:A)) -> 0 | D9: 10847965 | I9: 21800000 | J9: Matériels et mob de logement
A10: 21810000 | B10: Matériels & outillages | C10: =IF(A10=A9,0,SUMIFS(BLG1222!$I:$I,BLG1222!$A:$A,"agricorp",BLG1222!$D:$D,A:A)) -> 0 | I10: 21811000 | J10: Matériels & outillages
A11: 21820000 | B11: MMB | C11: =IF(A11=A10,0,SUMIFS(BLG1222!$I:$I,BLG1222!$A:$A,"agricorp",BLG1222!$D:$D,A:A)) -> 0 | D11: 25009519 | I11: 21820000 | J11: MMB
A12: 21830000 | B12: Materiel de transport | C12: =IF(A12=A11,0,SUMIFS(BLG1222!$I:$I,BLG1222!$A:$A,"agricorp",BLG1222!$D:$D,A:A)) -> 0 | D12: 22154000 | I12: 21830000 | J12: Materiel de transport
A13: 21840000 | B13: Matériel informatiques | C13: =IF(A13=A12,0,SUMIFS(BLG1222!$I:$I,BLG1222!$A:$A,"agricorp",BLG1222!$D:$D,A:A)) -> 0 | D13: 1.5531039e+08 | I13: 21840000 | J13: Matériel informatiques
A14: 26100000 | B14: Titres de participations | C14: =IF(A14=A13,0,SUMIFS(BLG1222!$I:$I,BLG1222!$A:$A,"agricorp",BLG1222!$D:$D,A:A)) -> 0 | D14: 3980000 | E14: 3980000 | F14: 3980000 | I14: 26100000 | J14: Titres de participations
A15: 27500000 | B15: Depot & cautionnements verses | C15: =IF(A15=A14,0,SUMIFS(BLG1222!$I:$I,BLG1222!$A:$A,"agricorp",BLG1222!$D:$D,A:A)) -> 0 | I15: 27500000 | J15: Depot & cautionnements verses
A16: 28150000 | B16: Amts Amenagement batiments | C16: =IF(A16=A15,0,SUMIFS(BLG1222!$I:$I,BLG1222!$A:$A,"agricorp",BLG1222!$D:$D,A:A)) -> 0 | D16: -13036.63 | I16: 28150000 | J16: Amts Amenagement batiments
A17: 28151000 | B17: Amortt agenc-amengt- autres que bât | C17: =IF(A17=A16,0,SUMIFS(BLG1222!$I:$I,BLG1222!$A:$A,"agricorp",BLG1222!$D:$D,A:A)) -> 0 | D17: -23400 | I17: 28151000 | J17: Amortt agenc-amengt- autres que bât
A18: 28182000 | B18: Amts MMB | C18: =IF(A18=A17,0,SUMIFS(BLG1222!$I:$I,BLG1222!$A:$A,"agricorp",BLG1222!$D:$D,A:A)) -> 0 | D18: -899873.34 | I18: 28182000 | J18: Amts MMB
A19: 28183000 | B19: AMT matériel de transport | C19: =IF(A19=A18,0,SUMIFS(BLG1222!$I:$I,BLG1222!$A:$A,"agricorp",BLG1222!$D:$D,A:A)) -> 0 | D19: -778590.28 | I19: 28183000 | J19: AMT matériel de transport
A20: 28184000 | B20: Amts materiel informatique | C20: =IF(A20=A19,0,SUMIFS(BLG1222!$I:$I,BLG1222!$A:$A,"agricorp",BLG1222!$D:$D,A:A)) -> 0 | D20: -16381200 | I20: 28184000 | J20: Amts materiel informatique
A21: 28185000 | B21: Amts mat & mob de logt | C21: =IF(A21=A20,0,SUMIFS(BLG1222!$I:$I,BLG1222!$A:$A,"agricorp",BLG1222!$D:$D,A:A)) -> 0 | D21: -146986.45 | I21: 28185000 | J21: Amts mat & mob de logt
A22: 40100000 | B22: Fournisseurs locaux | C22: =IF(A22=A21,0,SUMIFS(BLG1222!$I:$I,BLG1222!$A:$A,"agricorp",BLG1222!$D:$D,A:A)) -> 0 | D22: -2.2166698e+08 | I22: 40100000 | J22: Fournisseurs locaux
A23: 40120000 | B23: Fournisseurs étrangers | C23: =IF(A23=A22,0,SUMIFS(BLG1222!$I:$I,BLG1222!$A:$A,"agricorp",BLG1222!$D:$D,A:A)) -> 0 | I23: 40120000 | J23: FRNS ETRANGERS
A24: 40340000 | B24: F/sseurs effets à payer BNI | C24: =IF(A24=A23,0,SUMIFS(BLG1222!$I:$I,BLG1222!$A:$A,"agricorp",BLG1222!$D:$D,A:A)) -> 0 | I24: 40340000 | J24: F/SSEURS EFFETS À PAYER BNI
A25: 40800000 | B25: F/sseurs fact à recevoir | C25: =IF(A25=A24,0,SUMIFS(BLG1222!$I:$I,BLG1222!$A:$A,"agricorp",BLG1222!$D:$D,A:A)) -> 0 | D25: -17262815 | I25: 40800000 | J25: F/sseurs fact à recevoir
A26: 40900000 | B26: Frns: avance et acomptes | C26: =IF(A26=A25,0,SUMIFS(BLG1222!$I:$I,BLG1222!$A:$A,"agricorp",BLG1222!$D:$D,A:A)) -> 0 | D26: 4073000.2 | I26: 40900000 | J26: Frns: avance et acomptes
A27: 41100000 | B27: Collectifs clients | C27: =IF(A27=A26,0,SUMIFS(BLG1222!$I:$I,BLG1222!$A:$A,"agricorp",BLG1222!$D:$D,A:A)) -> 0 | I27: 41100000 | J27: Collectifs clients
A28: 41810000 | B28: Clients: factures à établir | C28: =IF(A28=A27,0,SUMIFS(BLG1222!$I:$I,BLG1222!$A:$A,"agricorp",BLG1222!$D:$D,A:A)) -> 0 | D28: 2.5037272e+08 | I28: 41810000 | J28: Clients: factures à établir
A29: 42100000 | B29: Rémunérations dues au personnel | C29: =IF(A29=A28,0,SUMIFS(BLG1222!$I:$I,BLG1222!$A:$A,"agricorp",BLG1222!$D:$D,A:A)) -> 0 | D29: 1109807.8 | I29: 42100000 | J29: Rémunérations dues au personnel
A30: 42500000 | B30: Avances & acomptes au personnel | C30: =IF(A30=A29,0,SUMIFS(BLG1222!$I:$I,BLG1222!$A:$A,"agricorp",BLG1222!$D:$D,A:A)) -> 0 | I30: 42500000 | J30: AVANCES & ACOMPTESAU PERSONNEL
A31: 42520000 | B31: Avances spéciales | C31: =IF(A31=A30,0,SUMIFS(BLG1222!$I:$I,BLG1222!$A:$A,"agricorp",BLG1222!$D:$D,A:A)) -> 0 | D31: 380983.63 | I31: 42520000 | J31: Avances spéciales
A32: 42540000 | B32: Tsinjo FAMENO | C32: =IF(A32=A31,0,SUMIFS(BLG1222!$I:$I,BLG1222!$A:$A,"agricorp",BLG1222!$D:$D,A:A)) -> 0 | D32: -7095999.9 | I32: 42540000 | J32: Tsinjo FAMENO
A33: 43100000 | B33: CNaPS | C33: =IF(A33=A32,0,SUMIFS(BLG1222!$I:$I,BLG1222!$A:$A,"agricorp",BLG1222!$D:$D,A:A)) -> 0 | D33: -84746315 | I33: 43100000 | J33: CNaPS
A34: 43110000 | B34: Allocation familiale CNAPS | C34: =IF(A34=A33,0,SUMIFS(BLG1222!$I:$I,BLG1222!$A:$A,"agricorp",BLG1222!$D:$D,A:A)) -> 0 | D34: -348000 | I34: 43110000 | J34: Allocation familiale CNAPS
A35: 43200000 | B35: OSTIE | C35: =IF(A35=A34,0,SUMIFS(BLG1222!$I:$I,BLG1222!$A:$A,"agricorp",BLG1222!$D:$D,A:A)) -> 0 | D35: -36319849 | I35: 43200000 | J35: OSTIE
A36: 43300000 | B36: FMFP | C36: =IF(A36=A35,0,SUMIFS(BLG1222!$I:$I,BLG1222!$A:$A,"agricorp",BLG1222!$D:$D,A:A)) -> 0 | D36: -6053308.2 | I36: 43300000 | J36: FMFP
A37: 43400000 | B37: ASCOMA | C37: =IF(A37=A36,0,SUMIFS(BLG1222!$I:$I,BLG1222!$A:$A,"agricorp",BLG1222!$D:$D,A:A)) -> 0 | D37: -700000 | I37: 43400000 | J37: ASCOMA
A38: 44100000 | B38: Etat: IRSA à payer | C38: =IF(A38=A37,0,SUMIFS(BLG1222!$I:$I,BLG1222!$A:$A,"agricorp",BLG1222!$D:$D,A:A)) -> 0 | D38: -75838460 | I38: 44100000 | J38: Etat: IRSA à payer
A39: 44300000 | B39: Etat: acomptes IR | C39: =IF(A39=A38,0,SUMIFS(BLG1222!$I:$I,BLG1222!$A:$A,"agricorp",BLG1222!$D:$D,A:A)) -> 0 | D39: 300000 | E39: 150000 | F39: 150000 | I39: 44300000 | J39: Etat: acomptes IR
A40: 44310000 | B40: IR Intermittent Locaux | C40: =IF(A40=A39,0,SUMIFS(BLG1222!$I:$I,BLG1222!$A:$A,"agricorp",BLG1222!$D:$D,A:A)) -> 0 | D40: -200000 | I40: 44310000 | J40: IR Intermittent Locaux
A41: 44320000 | B41: IR Intermittent étranger | C41: =IF(A41=A40,0,SUMIFS(BLG1222!$I:$I,BLG1222!$A:$A,"agricorp",BLG1222!$D:$D,A:A)) -> 0 | I41: 44320000 | J41: IR Intermittent étranger
A42: 44400000 | B42: Impôts synthetiques (IS) | C42: =IF(A42=A41,0,SUMIFS(BLG1222!$I:$I,BLG1222!$A:$A,"agricorp",BLG1222!$D:$D,A:A)) -> 0 | D42: -7511181.7 | I42: 44400000 | J42: Impôts synthetiques (IS)
A43: 44410000 | B43: Impôts synthetiques (IS) | C43: =IF(A43=A42,0,SUMIFS(BLG1222!$I:$I,BLG1222!$A:$A,"agricorp",BLG1222!$D:$D,A:A)) -> 0 | D43: 0 | E43: 0 | F43: -150000 | I43: 44410000 | J43: Impôts synthetiques (IS)
A44: 44550000 | B44: Credit de TVA | C44: =IF(A44=A43,0,SUMIFS(BLG1222!$I:$I,BLG1222!$A:$A,"agricorp",BLG1222!$D:$D,A:A)) -> 0 | I44: 44550000 | J44: Credit de taxe
A45: 44562000 | B45: TVA pour les Biens | C45: =IF(A45=A44,0,SUMIFS(BLG1222!$I:$I,BLG1222!$A:$A,"agricorp",BLG1222!$D:$D,A:A)) -> 0 | I45: 44562000 | J45: TVA pour les Biens
A46: 44563000 | B46: TVA Intermittente Déductible | C46: =IF(A46=A45,0,SUMIFS(BLG1222!$I:$I,BLG1222!$A:$A,"agricorp",BLG1222!$D:$D,A:A)) -> 0 | I46: 44563000 | J46: TVA Intermittente Déductible
A47: 44564000 | B47: TVA pour les Services | C47: =IF(A47=A46,0,SUMIFS(BLG1222!$I:$I,BLG1222!$A:$A,"agricorp",BLG1222!$D:$D,A:A)) -> 0 | I47: 44564000 | J47: TVA pour les Services
A48: 44565000 | B48: TVA pour l'Immobilisation | C48: =IF(A48=A47,0,SUMIFS(BLG1222!$I:$I,BLG1222!$A:$A,"agricorp",BLG1222!$D:$D,A:A)) -> 0 | I48: 44565000 | J48: TVA pour l'Immobilisation
A49: 44571000 | B49: TVA Intermittente collectéé | C49: =IF(A49=A48,0,SUMIFS(BLG1222!$I:$I,BLG1222!$A:$A,"agricorp",BLG1222!$D:$D,A:A)) -> 0 | I49: 44571000 | J49: TVA collectées
A50: 45510000 | B50: CCT ISMAEL DANIL | C50: =IF(A50=A49,0,SUMIFS(BLG1222!$I:$I,BLG1222!$A:$A,"agricorp",BLG1222!$D:$D,A:A)) -> 0 | D50: -1420000 | I50: 45510000 | J50: CCT ISMAEL DANIL
A51: 45511000 | B51: CCT ISMAEL DANIL | C51: =IF(A51=A50,0,SUMIFS(BLG1222!$I:$I,BLG1222!$A:$A,"agricorp",BLG1222!$D:$D,A:A)) -> 0 | D51: 0 | E51: -6480000 | F51: -6480000 | I51: 45511000 | J51: CCT ISMAEL DANIL
A52: 45520000 | B52: CCT SHERALY MINAZE | C52: =IF(A52=A51,0,SUMIFS(BLG1222!$I:$I,BLG1222!$A:$A,"agricorp",BLG1222!$D:$D,A:A)) -> 0 | D52: 75000 | I52: 45520000 | J52: CCT SHERALY MINAZE
A53: 45530000 | B53: CCT ISMAEL SHAHIM | C53: =IF(A53=A52,0,SUMIFS(BLG1222!$I:$I,BLG1222!$A:$A,"agricorp",BLG1222!$D:$D,A:A)) -> 0 | D53: 1140000 | I53: 45530000 | J53: CCT ISMAEL SHAHIM
A54: 45540000 | B54: CCT ISAMEL YANISH | C54: =IF(A54=A53,0,SUMIFS(BLG1222!$I:$I,BLG1222!$A:$A,"agricorp",BLG1222!$D:$D,A:A)) -> 0 | D54: 1725000 | I54: 45540000 | J54: CCT ISAMEL YANISH
A55: 46600000 | B55: STI | C55: =IF(A55=A54,0,SUMIFS(BLG1222!$I:$I,BLG1222!$A:$A,"agricorp",BLG1222!$D:$D,A:A)) -> 0 | D55: 897490 | I55: 46600000 | J55: STI
A56: 46600000 | B56: SEM | C56: =IF(A56=A55,0,SUMIFS(BLG1222!$I:$I,BLG1222!$A:$A,"agricorp",BLG1222!$D:$D,A:A)) -> 0 | D56: 1346234.9 | I56: 46600000 | J56: SEM
A57: 46610000 | B57: NUTRIFOOD REFACTURATION | C57: =IF(A57=A56,0,SUMIFS(BLG1222!$I:$I,BLG1222!$A:$A,"agricorp",BLG1222!$D:$D,A:A)) -> 0 | D57: 270000 | I57: 46610000 | J57: NUTRIFOOD REFACTURATION
A58: 46610000 | B58: INTERKEM REFACTURATION | C58: =IF(A58=A57,0,SUMIFS(BLG1222!$I:$I,BLG1222!$A:$A,"agricorp",BLG1222!$D:$D,A:A)) -> 0 | D58: 342000 | I58: 46610000 | J58: INTERKEM REFACTURATION
A59: 46610000 | B59: DITE REFACTURATION | C59: =IF(A59=A58,0,SUMIFS(BLG1222!$I:$I,BLG1222!$A:$A,"agricorp",BLG1222!$D:$D,A:A)) -> 0 | D59: 418800 | I59: 46610000 | J59: DITE REFACTURATION
A60: 46610000 | B60: AGRIVET ANTSIRABE REFACTURATION | C60: =IF(A60=A59,0,SUMIFS(BLG1222!$I:$I,BLG1222!$A:$A,"agricorp",BLG1222!$D:$D,A:A)) -> 0 | D60: 448745.02 | I60: 46610000 | J60: AGRIVET ANTSIRABE REFACTURATION
A61: 46610000 | B61: AGRIVET FIANARNTSOA REFACT | C61: =IF(A61=A60,0,SUMIFS(BLG1222!$I:$I,BLG1222!$A:$A,"agricorp",BLG1222!$D:$D,A:A)) -> 0 | D61: 448745.02 | I61: 46610000 | J61: AGRIVET FIANARNTSOA REFACT
A62: 46610000 | B62: AGRIVET TAMATAVE REFACTURATION | C62: =IF(A62=A61,0,SUMIFS(BLG1222!$I:$I,BLG1222!$A:$A,"agricorp",BLG1222!$D:$D,A:A)) -> 0 | D62: 448745.02 | I62: 46610000 | J62: AGRIVET TAMATAVE REFACTURATION
A63: 46610000 | B63: FERRIS ENGINEERING REFACTURATION | C63: =IF(A63=A62,0,SUMIFS(BLG1222!$I:$I,BLG1222!$A:$A,"agricorp",BLG1222!$D:$D,A:A)) -> 0 | D63: 448745.02 | I63: 46610000 | J63: FERRIS ENGINEERING REFACTURATION
... A129: 46800000 | B129: IRS IMMO | C129: =IF(A129=A128,0,SUMIFS(BLG1222!$I:$I,BLG1222!$A:$A,"agricorp",BLG1222!$D:$D,A:A)) -> 0 | D129: 17876450 | I129: 46800000 | J129: IRS IMMO
A130: 47100000 | B130: Compte d'attente | C130: =IF(A130=A129,0,SUMIFS(BLG1222!$I:$I,BLG1222!$A:$A,"agricorp",BLG1222!$D:$D,A:A)) -> 0 | I130: 47100000 | J130: Compte d'attente
A131: 48600000 | B131: Charges constatées d'avance | C131: =IF(A131=A130,0,SUMIFS(BLG1222!$I:$I,BLG1222!$A:$A,"agricorp",BLG1222!$D:$D,A:A)) -> 0 | D131: 59389369 | I131: 48600000 | J131: Charges constatées d'avance
A132: 51241000 | B132: BNI Ariary | C132: =IF(A132=A131,0,SUMIFS(BLG1222!$I:$I,BLG1222!$A:$A,"agricorp",BLG1222!$D:$D,A:A)) -> 0 | D132: 2.4676563e+08 | E132: 430387.24 | F132: 708815.79 | I132: 51241000 | J132: BNI Ariary
A133: 53100000 | B133: Caisse Ambohibao | C133: =IF(A133=A132,0,SUMIFS(BLG1222!$I:$I,BLG1222!$A:$A,"agricorp",BLG1222!$D:$D,A:A)) -> 0 | D133: 1792350.4 | E133: 1369600 | F133: 1371600 | I133: 53100000 | J133: Caisse Ambohibao
A134: 53200000 | B134: Caisse Recette | C134: =IF(A134=A133,0,SUMIFS(BLG1222!$I:$I,BLG1222!$A:$A,"agricorp",BLG1222!$D:$D,A:A)) -> 0 | I134: 53200000 | J134: Caisse 3
A135: 58000000 | B135: Virements internes | C135: =IF(A135=A134,0,SUMIFS(BLG1222!$I:$I,BLG1222!$A:$A,"agricorp",BLG1222!$D:$D,A:A)) -> 0 | I135: 58000000 | J135: Virements internes
A136: 60601000 | B136: Eau & électricité | C136: =IF(A136=A135,0,SUMIFS(BLG1222!$I:$I,BLG1222!$A:$A,"agricorp",BLG1222!$D:$D,A:A)) -> 0 | D136: 2430309.2 | I136: 60601000 | J136: Eau & électricité
A137: 60602000 | B137: Carburants pour vehicules | C137: =IF(A137=A136,0,SUMIFS(BLG1222!$I:$I,BLG1222!$A:$A,"agricorp",BLG1222!$D:$D,A:A)) -> 0 | D137: 1687400 | I137: 60602000 | J137: Carburants pour vehicules
A138: 60604000 | B138: Produits d'hygiene et ménages | C138: =IF(A138=A137,0,SUMIFS(BLG1222!$I:$I,BLG1222!$A:$A,"agricorp",BLG1222!$D:$D,A:A)) -> 0 | D138: 39968033 | I138: 60604000 | J138: Produits d'hygiene et ménages
A139: 60605000 | B139: Petit outillage | C139: =IF(A139=A138,0,SUMIFS(BLG1222!$I:$I,BLG1222!$A:$A,"agricorp",BLG1222!$D:$D,A:A)) -> 0 | D139: 91552974 | I139: 60605000 | J139: Petit outillage
A140: 60607000 | B140: Fournitures informatiques | C140: =IF(A140=A139,0,SUMIFS(BLG1222!$I:$I,BLG1222!$A:$A,"agricorp",BLG1222!$D:$D,A:A)) -> 0 | D140: 40952139 | I140: 60607000 | J140: Fournitures informatiques
A141: 60608000 | B141: Fournitures de bureau | C141: =IF(A141=A140,0,SUMIFS(BLG1222!$I:$I,BLG1222!$A:$A,"agricorp",BLG1222!$D:$D,A:A)) -> 0 | D141: 96476345 | I141: 60608000 | J141: Fournitures de bureau
A142: 60609000 | B142: Autres charges | C142: =IF(A142=A141,0,SUMIFS(BLG1222!$I:$I,BLG1222!$A:$A,"agricorp",BLG1222!$D:$D,A:A)) -> 0 | I142: 60609000 | J142: Achats matières et fournitures
A143: 61100000 | B143: Sous traitance Groupe | C143: =IF(A143=A142,0,SUMIFS(BLG1222!$I:$I,BLG1222!$A:$A,"agricorp",BLG1222!$D:$D,A:A)) -> 0 | I143: 61100000 | J143: sous traitances
A144: 61301000 | B144: Location mat et mobil de bureau | C144: =IF(A144=A143,0,SUMIFS(BLG1222!$I:$I,BLG1222!$A:$A,"agricorp",BLG1222!$D:$D,A:A)) -> 0 | D144: 26894105 | I144: 61301000 | J144: Location mat et mobil de bureau
A145: 61302000 | B145: Locations véhicules | C145: =IF(A145=A144,0,SUMIFS(BLG1222!$I:$I,BLG1222!$A:$A,"agricorp",BLG1222!$D:$D,A:A)) -> 0 | D145: 1.195067e+08 | I145: 61302000 | J145: Locations véhicules
A146: 61303000 | B146: Autres locations | C146: =IF(A146=A145,0,SUMIFS(BLG1222!$I:$I,BLG1222!$A:$A,"agricorp",BLG1222!$D:$D,A:A)) -> 0 | D146: 1.2686371e+08 | I146: 61303000 | J146: Autres locations
A147: 61500000 | B147: Autres entretiens | C147: =IF(A147=A146,0,SUMIFS(BLG1222!$I:$I,BLG1222!$A:$A,"agricorp",BLG1222!$D:$D,A:A)) -> 0 | D147: 11243056 | I147: 61500000 | J147: Autres entretiens
A148: 61501000 | B148: ERM Immobilieres | C148: =IF(A148=A147,0,SUMIFS(BLG1222!$I:$I,BLG1222!$A:$A,"agricorp",BLG1222!$D:$D,A:A)) -> 0 | D148: 335480 | I148: 61501000 | J148: ERM Immobilieres
A149: 61501400 | B149: ERM ABAO | C149: =IF(A149=A148,0,SUMIFS(BLG1222!$I:$I,BLG1222!$A:$A,"agricorp",BLG1222!$D:$D,A:A)) -> 0 | D149: 1644359.3 | I149: 61501400 | J149: ERM ABAO
A150: 61502000 | B150: ERM bureautique & informatique | C150: =IF(A150=A149,0,SUMIFS(BLG1222!$I:$I,BLG1222!$A:$A,"agricorp",BLG1222!$D:$D,A:A)) -> 0 | D150: 923150.73 | I150: 61502000 | J150: ERM bureautique & informatique
A151: 61503000 | B151: ERM vehicules | C151: =IF(A151=A150,0,SUMIFS(BLG1222!$I:$I,BLG1222!$A:$A,"agricorp",BLG1222!$D:$D,A:A)) -> 0 | D151: 76244609 | I151: 61503000 | J151: ERM vehicules
A152: 61601000 | B152: Assurances flottes auto | C152: =IF(A152=A151,0,SUMIFS(BLG1222!$I:$I,BLG1222!$A:$A,"agricorp",BLG1222!$D:$D,A:A)) -> 0 | D152: 2029.44 | I152: 61601000 | J152: Assurances flottes auto
A153: 61604000 | B153: Autres polices d'assurances | C153: =IF(A153=A152,0,SUMIFS(BLG1222!$I:$I,BLG1222!$A:$A,"agricorp",BLG1222!$D:$D,A:A)) -> 0 | D153: 2156413.8 | I153: 61604000 | J153: Autres polices d'assurances
A154: 61801000 | B154: Journaux | C154: =IF(A154=A153,0,SUMIFS(BLG1222!$I:$I,BLG1222!$A:$A,"agricorp",BLG1222!$D:$D,A:A)) -> 0 | D154: 1352000 | I154: 61801000 | J154: Journaux
A155: 61802000 | B155: Autres divers & documentation | C155: =IF(A155=A154,0,SUMIFS(BLG1222!$I:$I,BLG1222!$A:$A,"agricorp",BLG1222!$D:$D,A:A)) -> 0 | D155: 1904000 | I155: 61802000 | J155: Autres divers & documentation
... A165: 62501000 | B165: Billets d'avion | C165: =IF(A165=A164,0,SUMIFS(BLG1222!$I:$I,BLG1222!$A:$A,"agricorp",BLG1222!$D:$D,A:A)) -> 0 | D165: 1.8505057e+08 | I165: 62501000 | J165: Billets d'avion
A166: 62502000 | B166: Achat de devises | C166: =IF(A166=A165,0,SUMIFS(BLG1222!$I:$I,BLG1222!$A:$A,"agricorp",BLG1222!$D:$D,A:A)) -> 0 | I166: 62502000 | J166: Achat de devises
A167: 62503000 | B167: Per Diem tournées | C167: =IF(A167=A166,0,SUMIFS(BLG1222!$I:$I,BLG1222!$A:$A,"agricorp",BLG1222!$D:$D,A:A)) -> 0 | D167: 9203800 | I167: 62503000 | J167: Per Diem tournées
A168: 62504000 | B168: Réceptions | C168: =IF(A168=A167,0,SUMIFS(BLG1222!$I:$I,BLG1222!$A:$A,"agricorp",BLG1222!$D:$D,A:A)) -> 0 | D168: 46013368 | I168: 62504000 | J168: Réceptions
A169: 62505000 | B169: Mission: Hergement , hotel | C169: =IF(A169=A168,0,SUMIFS(BLG1222!$I:$I,BLG1222!$A:$A,"agricorp",BLG1222!$D:$D,A:A)) -> 0 | D169: 3482000 | I169: 62505000 | J169: Mission: Hergement , hotel
A170: 62506000 | B170: Frais de deplacement en ville | C170: =IF(A170=A169,0,SUMIFS(BLG1222!$I:$I,BLG1222!$A:$A,"agricorp",BLG1222!$D:$D,A:A)) -> 0 | D170: 516080 | I170: 62506000 | J170: Frais de deplacement en ville
A171: 62507000 | B171: Collation du personnel | C171: =IF(A171=A170,0,SUMIFS(BLG1222!$I:$I,BLG1222!$A:$A,"agricorp",BLG1222!$D:$D,A:A)) -> 0 | D171: 42565888 | I171: 62507000 | J171: Collation du personnel
A172: 62602000 | B172: Telephone mobile | C172: =IF(A172=A171,0,SUMIFS(BLG1222!$I:$I,BLG1222!$A:$A,"agricorp",BLG1222!$D:$D,A:A)) -> 0 | D172: 7075084.5 | I172: 62602000 | J172: Telephone mobile
A173: 62603000 | B173: Internet | C173: =IF(A173=A172,0,SUMIFS(BLG1222!$I:$I,BLG1222!$A:$A,"agricorp",BLG1222!$D:$D,A:A)) -> 0 | D173: 6117579.8 | I173: 62603000 | J173: Internet
A174: 62604000 | B174: Envoi colis | C174: =IF(A174=A173,0,SUMIFS(BLG1222!$I:$I,BLG1222!$A:$A,"agricorp",BLG1222!$D:$D,A:A)) -> 0 | D174: 6000 | I174: 62604000 | J174: Envoi colis
...

Sheet AGRIFARM
J1: 2022 | K1: 2021 | L1: 2020 | M1: 2019
A2: 10100000 | B2: Capital | C2: -3540000000 | E2: -3540000000 | G2: =+VLOOKUP(H2,#REF!,1,FALSE()) -> #VALUE! | H2: 10100000 | I2: Capital | K2: -3540000000 | L2: -3540000000 | M2: -3540000000
A3: 10610000 | B3: Reserves légales | C3: -354000000 | E3: -354000000 | G3: =+VLOOKUP(H3,#REF!,1,FALSE()) -> #VALUE! | H3: 10610000 | I3: Reserves légales | K3: -354000000 | L3: -354000000 | M3: -354000000
A4: 11000000 | B4: RAN Créditeur | C4: -8.509871e+09 | E4: -6.3446446e+09 | G4: =+VLOOKUP(H4,#REF!,1,FALSE()) -> #VALUE! | H4: 11000000 | I4: RAN Créditeur | K4: -9.40908e+09 | L4: -8.509871e+09 | M4: -6.3446446e+09 | N4: -2.1652263e+09
A5: 16100000 | B5: Emprunts BNI | C5: -2000000000 | E5: 0 | G5: =+VLOOKUP(H5,#REF!,1,FALSE()) -> #VALUE! | H5: 16100000 | I5: Emprunts BNI | K5: -3.600927e+09 | L5: -2000000000 | M5: 0
A6: 16120000 | B6: Emprunts BFV | C6: -1.8946752e+09 | E6: -4.0799357e+08 | G6: =+VLOOKUP(H6,#REF!,1,FALSE()) -> #VALUE! | H6: 16120000 | I6: Emprunts BFV | K6: 0 | L6: -1.8946752e+09 | M6: 0
A7: 16130000 | B7: Emprunts BMOI | C7: -2000000000 | G7: =+VLOOKUP(H7,#REF!,1,FALSE()) -> #VALUE! | H7: 16130000 | I7: Emprunts BMOI | K7: 0 | L7: -4000000000 | M7: -4.0799357e+08
A8: 16130000 | B8: Emprunts BMOI MGA | C8: -2000000000 | G8: =+VLOOKUP(H8,#REF!,1,FALSE()) -> #VALUE! | H8: 16200000 | I8: EMPRUNTS BFV | K8: -5.7823688e+08 | M8: -2.2978343e+09
A9: 16884000 | B9: Intérêts couru sur emprunts | C9: -30840097 | E9: 4832320.4 | G9: =+VLOOKUP(H9,#REF!,1,FALSE()) -> #VALUE! | H9: 16400000 | I9: EMPRUNTS BNI | K9: -913586398
A10: 20400000 | B10: Logiciels informatiques & assimilés | C10: 4832320.4 | E10: 617015295 | G10: =+VLOOKUP(H10,#REF!,1,FALSE()) -> #VALUE! | H10: 16430000 | I10: BOA PRET COLLECTIF | K10: -2.3479427e+08
A11: 21100000 | B11: Terrains | C11: 7.3484863e+08 | E11: 4.7259753e+08 | G11: =+VLOOKUP(H11,#REF!,1,FALSE()) -> #VALUE! | H11: 16884000 | I11: Intérêts couru sur emprunts | K11: 0 | L11: -30840097 | M11: -8881771
A12: 21200000 | B12: Agencement amenagement terrain | C12: 1.1032187e+09 | E12: 6.9909811e+09 | G12: =+VLOOKUP(H12,#REF!,1,FALSE()) -> #VALUE! | H12: 20400000 | I12: Logiciels informatiques & assimilés | K12: 4832320.4 | L12: 4832320.4 | M12: 4832320.4
A13: 21300000 | B13: Batiments - Constructions | C13: 8.68729e+09 | E13: 5.397081e+08 | G13: =+VLOOKUP(H13,#REF!,1,FALSE()) -> #VALUE! | H13: 21100000 | I13: Terrains | K13: 1.3115778e+09 | L13: 7.3484863e+08 | M13: 617015295
A14: 21500000 | B14: Agencement aménagement installation | C14: 2.9003776e+08 | E14: 29445569 | G14: =+VLOOKUP(H14,#REF!,1,FALSE()) -> #VALUE! | H14: 21200000 | I14: Agencement amenagement terrain | K14: 1.741202e+09 | L14: 1.1032187e+09 | M14: 4.7259753e+08
A15: 21520000 | B15: INSTALLATION CAMERA | C15: 33571788 | E15: 0 | G15: =+VLOOKUP(H15,#REF!,1,FALSE()) -> #VALUE! | H15: 21300000 | I15: Batiments - Constructions | K15: 9.3963741e+09 | L15: 8.68729e+09 | M15: 6.9909811e+09
A16: 21540000 | B16: MATERIEL ET OUT INDUSTRIEL | C16: 4.169547e+08 | E16: 4.0232754e+09 | G16: =+VLOOKUP(H16,#REF!,1,FALSE()) -> #VALUE! | H16: 21500000 | I16: Agencement aménagement installation | K16: 4.474744e+08 | L16: 2.9003776e+08 | M16: 5.397081e+08
A17: 21540000 | B17: Matériels & outillages | C17: 2.336805e+09 | G17: =+VLOOKUP(H17,#REF!,1,FALSE()) -> #VALUE! | H17: 21520000 | I17: Installations | K17: 33571788 | L17: 33571788 | M17: 29445569
A18: 21540000 | B18: Matériels & outillages TALATA | C18: 1.8188668e+09 | E18: 32942199 | G18: =+VLOOKUP(H18,#REF!,1,FALSE()) -> #VALUE! | H18: 21530000 | I18: Agenc Amenag Batiment | K18: 12600000
A19: 21540000 | B19: MATERIEL DE LABORATOIRE | C19: 2.2047552e+08 | E19: 1.6839917e+09 | G19: =+VLOOKUP(H19,#REF!,1,FALSE()) -> #VALUE! | H19: 21540000 | I19: Matériels & outillages | K19: 8.2536993e+08 | L19: 4.793102e+09 | M19: 4.243751e+09
A20: 21820000 | B20: MMB | C20: 42123956 | E20: 9.6264369e+08 | G20: =+VLOOKUP(H20,#REF!,1,FALSE()) -> #VALUE! | H20: 21810000 | I20: MATÉRIELS & OUTILLAGES | K20: 2.427449e+09
A21: 21820000 | B21: Materiel & mobilier de logement | C21: 14315435 | E21: 2.2047552e+08 | G21: =+VLOOKUP(H21,#REF!,1,FALSE()) -> #VALUE! | H21: 21811000 | I21: Matériels & outillages TALATA | K21: 1.8622359e+09
A22: 21830000 | B22: Materiel de transport | C22: 9.0107832e+08 | E22: 88221560 | G22: =+VLOOKUP(H22,#REF!,1,FALSE()) -> #VALUE! | H22: 21820000 | I22: MMB | K22: 49337398 | L22: 56439391 | M22: 47257634
A23: 21840000 | B23: Matériel informatiques | C23: 95049060 | E23: 0 | G23: =+VLOOKUP(H23,#REF!,1,FALSE()) -> #VALUE! | H23: 21830000 | I23: Materiel de transport | K23: 9.9473781e+08 | L23: 9.0107832e+08 | M23: 9.6264369e+08
A24: 23200000 | B24: Autres immo en cours | C24: 6.7889432e+08 | E24: 0 | G24: =+VLOOKUP(H24,#REF!,1,FALSE()) -> #VALUE! | H24: 21840000 | I24: Matériel informatiques | K24: 1.2353253e+08 | L24: 95049060 | M24: 88221560
A25: 23200000 | B25: Immo en cours dépot | C25: 1.0727673e+09 | E25: 1200000 | G25: =+VLOOKUP(H25,#REF!,1,FALSE()) -> #VALUE! | H25: 21850000 | I25: MATERIEL &MOBILIER DE LOGEMENT | K25: 14315435
A26: 27500000 | B26: Depot & cautionnements verses | C26: 1200000 | E26: -2902076.8 | G26: =+VLOOKUP(H26,#REF!,1,FALSE()) -> #VALUE! | H26: 21860000 | I26: MATERIEL DE LABORATOIRE | K26: 2.3180962e+08
A27: 28040000 | B27: Amts logiciel informatique | C27: -3868540.9 | E27: -1.7227006e+08 | G27: =+VLOOKUP(H27,#REF!,1,FALSE()) -> #VALUE! | H27: 23000000 | I27: IMMO EN COURS | K27: 1.1430707e+09
A28: 28120000 | B28: Amts Agens Amenag Terrain | C28: -2.3839724e+08 | E28: -1.7433025e+09 | G28: =+VLOOKUP(H28,#REF!,1,FALSE()) -> #VALUE! | H28: 23200000 | I28: Autres immo en cours | K28: 1.2284763e+09 | L28: 1.7516616e+09 | M28: 1.6839917e+09
A29: 28130000 | B29: Amts batiments et constructions | C29: -2.1040979e+09 | E29: -2.8957175e+08 | G29: =+VLOOKUP(H29,#REF!,1,FALSE()) -> #VALUE! | H29: 27500000 | I29: Depot & cautionnements verses | K29: 0 | L29: 1200000 | M29: 1200000
A30: 28150000 | B30: Amts agen. amen.instal. | C30: -1.7634706e+08 | E30: -893419.85 | G30: =+VLOOKUP(H30,#REF!,1,FALSE()) -> #VALUE! | H30: 28040000 | I30: Amts logiciel informatique | K30: -4832320.4 | L30: -3868540.9 | M30: -2902076.8
A31: 28152000 | B31: AMORT INSTALLATION CAMERA | C31: -4126812 | E31: 0 | G31: =+VLOOKUP(H31,#REF!,1,FALSE()) -> #VALUE! | H31: 28120000 | I31: Amts Agens Amenag Terrain | K31: -3.6104054e+08 | L31: -2.3839724e+08 | M31: -1.7227006e+08
A32: 28154000 | B32: Amts matériels & outillage | C32: -1.392022e+09 | G32: =+VLOOKUP(H32,#REF!,1,FALSE()) -> #VALUE! | H32: 28130000 | I32: Amts batiments et constructions | K32: -2.5585134e+09 | L32: -2.1040979e+09 | M32: -1.7433025e+09
A33: 28154000 | B33: Amts matériel & outillage TALA | C33: -7.6336681e+08 | E33: -17324137 | G33: =+VLOOKUP(H33,#REF!,1,FALSE()) -> #VALUE! | H33: 28150000 | I33: Amts agen. amen.instal. | K33: -2.1213962e+08 | L33: -1.7634706e+08 | M33: -2.8957175e+08
A34: 28154000 | B34: AMORT MAT LABORATOIRE | C34: -1.1972664e+08 | E34: 1.0228732e+09 | G34: =+VLOOKUP(H34,#REF!,1,FALSE()) -> #VALUE! | H34: 28152000 | I34: AMORT INSTALLATION CAMERA | K34: -7483991 | L34: -4126812 | M34: -893419.85
A35: 28154000 | B35: AMORT SUR MAT ET OUT INDUSTRIEL | C35: -1.7493873e+08 | E35: -1.7496416e+09 | G35: =+VLOOKUP(H35,#REF!,1,FALSE()) -> #VALUE! | H35: 28153000 | I35: Amts Agenc Amenag Batiment | K35: -630000
A36: 28182000 | B36: Amts MMB | C36: -21006458 | E36: -7.6004316e+08 | G36: =+VLOOKUP(H36,#REF!,1,FALSE()) -> #VALUE! | H36: 28154000 | I36: Amts matériels & outillage | K36: -2.3577521e+08 | L36: -2.4500542e+09 | M36: -1.8473207e+09
A37: 28182000 | B37: Amts mat & mob de logt | C37: -11666574 | E37: -97679090 | G37: =+VLOOKUP(H37,#REF!,1,FALSE()) -> #VALUE! | H37: 28181000 | I37: AMTS MATERIELS & OUTILLAGE | K37: -1.6158093e+09
A38: 28183000 | B38: AMT matériel de transport | C38: -7.5423769e+08 | E38: -71476538 | G38: =+VLOOKUP(H38,#REF!,1,FALSE()) -> #VALUE! | H38: 28181100 | I38: Amts matériel & outillage TALA | K38: -9.4692702e+08
A39: 28184000 | B39: Amts materiel informatique | C39: -80279548 | E39: -10324724 | G39: =+VLOOKUP(H39,#REF!,1,FALSE()) -> #VALUE! | H39: 28182000 | I39: Amts MMB | K39: -25650896 | L39: -32673032 | M39: -27648861
A40: 31000000 | B40: Stocks de mat.1ères & fournitures | C40: 1.3578887e+09 | E40: 2.5656028e+09 | G40: =+VLOOKUP(H40,#REF!,1,FALSE()) -> #VALUE! | H40: 28183000 | I40: AMT matériel de transport | K40: -8.2073672e+08 | L40: -7.5423769e+08 | M40: -7.6004316e+08
A41: 35100000 | B41: Stock cheptel | C41: 2.1704279e+09 | E41: -1.3261839e+09 | G41: =+VLOOKUP(H41,#REF!,1,FALSE()) -> #VALUE! | H41: 28184000 | I41: Amts materiel informatique | K41: -89765908 | L41: -80279548 | M41: -71476538
A42: 40110000 | B42: Fournisseurs locaux | C42: -1.6338791e+09 | E42: -28058553 | G42: =+VLOOKUP(H42,#REF!,1,FALSE()) -> #VALUE! | H42: 28185000 | I42: AMTS MAT & MOB DE LOGT | K42: -12533214
A43: 40120000 | B43: FRNS ETRANGERS | C43: -1.1873601e+09 | E43: -3.4279093e+08 | G43: =+VLOOKUP(H43,#REF!,1,FALSE()) -> #VALUE! | H43: 28186000 | I43: AMORT MAT LABORATOIRE | K43: -1.423493e+08
A44: 40310000 | B44: F/sseurs effets à payer | C44: -14819979 | E44: -23760682 | G44: =+VLOOKUP(H44,#REF!,1,FALSE()) -> #VALUE! | H44: 31000000 | I44: Stocks de matières & fournitures | K44: 1.5269987e+09 | L44: 1.3578887e+09 | M44: 1.0228732e+09
A45: 40310000 | B45: F/sseurs effets à payer | C45: -23584725 | E45: -2.694895e+08 | G45: =+VLOOKUP(H45,#REF!,1,FALSE()) -> #VALUE! | H45: 35100000 | I45: Stocks de produits | K45: 2.9058756e+09 | L45: 2.1704279e+09 | M45: 2.5656028e+09
A46: 40400000 | B46: F/sseurs d'immobilisations | C46: -1616760 | E46: -5.8559274e+08 | G46: =+VLOOKUP(H46,#REF!,1,FALSE()) -> #VALUE! | H46: 40110000 | I46: Fournisseurs locaux | K46: -1.3165383e+09 | L46: -1.6338791e+09 | M46: -1.3261839e+09
A47: 40810000 | B47: FRNS FACT NON PARVENUES | C47: -3.443545e+08 | G47: =+VLOOKUP(H47,#REF!,1,FALSE()) -> #VALUE! | H47: 40120000 | I47: FRNS ETRANGERS | K47: -1.2821648e+08 | L47: -1.1873601e+09 | M47: -28058553
A48: 40910000 | B48: FRNS LOCAUX DEBITEURS:AVANCE | C48: 3.3973324e+08 | G48: =+VLOOKUP(H48,#REF!,1,FALSE()) -> #VALUE! | H48: 40310000 | I48: Fournisseurs, effets à payer | K48: -2.4173721e+08 | L48: -38404704 | M48: -3.816726e+08
A49: 40910000 | B49: FRNS ETRANGER DEBITEUR:AVANCE | C49: 96437754 | E49: 0 | G49: =+VLOOKUP(H49,#REF!,1,FALSE()) -> #VALUE! | H49: 40320000 | I49: F/SSEURS EFFETS À PAYER BFV | K49: -100078700
A50: 41100000 | B50: Collectifs clients | C50: 1.4854705e+09 | G50: =+VLOOKUP(H50,#REF!,1,FALSE()) -> #VALUE! | H50: 40330000 | I50: F/SSEURS EFFETS À PAYER BOA | K50: -2.6712014e+08
A51: 41310000 | B51: CLIENTS EFFETS À RECEVOIR | C51: 71450000 | E51: 6.5783347e+08 | G51: =+VLOOKUP(H51,#REF!,1,FALSE()) -> #VALUE! | H51: 40340000 | I51: F/SSEURS EFFETS À PAYER BNI | K51: -1.7834292e+08
A52: 41600000 | B52: CLTS DOUTEUX OU LITIGIEUX | C52: 7.9496448e+08 | E52: 0 | G52: =+VLOOKUP(H52,#REF!,1,FALSE()) -> #VALUE! | H52: 40400000 | I52: F/sseurs d'immobilisations | K52: -1616760 | L52: -1616760 | M52: -2.694895e+08
A53: 41810000 | B53: Clients fact a etablir | C53: 1500000 | G53: =+VLOOKUP(H53,#REF!,1,FALSE()) -> #VALUE! | H53: 40810000 | I53: FRNS FACT NON PARVENUES | K53: -9.783877e+08 | L53: -3.443545e+08 | M53: -5.8559274e+08
A54: 41910000 | B54: Clients: avances et acomptes | C54: 1240000 | G54: =+VLOOKUP(H54,#REF!,1,FALSE()) -> #VALUE! | H54: 40910000 | I54: FRNS DEBITEURS:AVANCE | K54: 6.261939e+08 | L54: 4.36171e+08 | M54: 6.4257629e+08
A55: 41980000 | B55: Avoir à établir | C55: -30000 | E55: 0 | G55: =+VLOOKUP(H55,#REF!,1,FALSE()) -> #VALUE! | H55: 40920000 | I55: FRNS ETRANGER DEBITEUR:AVANCE | K55: 33766757
A56: 42110000 | B56: Rémunérations dues au personnel | C56: 725894.09 | E56: 4000 | G56: =+VLOOKUP(H56,#REF!,1,FALSE()) -> #VALUE! | H56: 41100000 | I56: Collectifs clients | K56: 0 | L56: 1.4854705e+09 | M56: 1.4523555e+09
A57: 42110000 | B57: Salaires Temporaires | C57: 1893800 | G57: =+VLOOKUP(H57,#REF!,1,FALSE()) -> #VALUE! | H57: 41110000 | I57: CLIENTS LOCAUX | K57: 1.5813687e+09
A58: 42520000 | B58: Avances speciales | C58: -2179998 | E58: 60000 | G58: =+VLOOKUP(H58,#REF!,1,FALSE()) -> #VALUE! | H58: 41300000 | I58: CLIENTS EFFETS À RECEVOIR | K58: 4.7038609e+08
A59: 42520000 | B59: Avances prêt scolaire | C59: 59999.97 | E59: -1.0843296e+08 | G59: =+VLOOKUP(H59,#REF!,1,FALSE()) -> #VALUE! | H59: 41310000 | I59: CLIENTS EFFETS À RECEVOIR | K59: 0 | L59: 71450000 | M59: 86322656
A60: 42800000 | B60: Congés payés provision | C60: -1.2036252e+08 | E60: -26888118 | G60: =+VLOOKUP(H60,#REF!,1,FALSE()) -> #VALUE! | H60: 41600000 | I60: CLTS DOUTEUX OU LITIGIEUX | K60: 8.3543969e+08 | L60: 7.9496448e+08 | M60: 6.5783347e+08
A61: 43100000 | B61: CNaPS | C61: -27917350 | E61: -278100 | G61: =+VLOOKUP(H61,#REF!,1,FALSE()) -> #VALUE! | H61: 41810000 | I61: Clients fact a etablir | K61: 184846992 | L61: 1500000 | M61: 167260000
A62: 43110000 | B62: Allocation familiale CNAPS | C62: -1904100 | E62: -17925412 | G62: =+VLOOKUP(H62,#REF!,1,FALSE()) -> #VALUE! | H62: 41900000 | I62: Clients: avances et acomptes | K62: 1240000
A63: 43200000 | B63: OSTIE | C63: -18611567 | E63: -2987568.6 | G63: =+VLOOKUP(H63,#REF!,1,FALSE()) -> #VALUE! | H63: 41910000 | I63: Clients: avances et acomptes | K63: 0 | L63: 1240000 | M63: -70547130
A64: 43300000 | B64: FMFP | C64: -3101927.8 | E64: -32351713 | G64: =+VLOOKUP(H64,#REF!,1,FALSE()) -> #VALUE! | H64: 41980000 | I64: Avoir à établir | K64: -30000 | L64: -30000 | M64: 0
A65: 43860000 | B65: Organismes autres charges à payer | C65: -34629801 | G65: =+VLOOKUP(H65,#REF!,1,FALSE()) -> #VALUE! | H65: 42100000 | I65: RÉMUNÉRATION DUES AU PERSONNEL | K65: 7385000
A66: 44100000 | B66: Etat: IRSA à payer | C66: -15129483 | E66: 0 | G66: =+VLOOKUP(H66,#REF!,1,FALSE()) -> #VALUE! | H66: 42110000 | I66: Rémunérations dues au personnel | K66: 0 | L66: 2619694.1 | M66: 4000
A67: 44200000 | B67: Etat : IFPB | C67: -4488218 | E67: 5.8958572e+08 | G67: =+VLOOKUP(H67,#REF!,1,FALSE()) -> #VALUE! | H67: 42500000 | I67: AVANCES & ACOMPTESAU PERSONNEL | K67: 1435000
A68: 44300000 | B68: Etat : acomptes IR | C68: 2.8879756e+08 | G68: =+VLOOKUP(H68,#REF!,1,FALSE()) -> #VALUE! | H68: 42510000 | I68: Avances quinzaines | K68: 400000
A69: 44400000 | B69: Etat à payer | C69: -1.0141028e+08 | E69: -16841462 | G69: =+VLOOKUP(H69,#REF!,1,FALSE()) -> #VALUE! | H69: 42520000 | I69: Avances speciales | K69: -14072000 | L69: -2119998 | M69: 60000
A70: 44410000 | B70: Crédit IR | C70: 2.3404748e+08 | G70: =+VLOOKUP(H70,#REF!,1,FALSE()) -> #VALUE! | H70: 42530000 | I70: Avances prêt scolaire | K70: 59999.97
A71: 44411000 | B71: IR Intermittent Locaux | C71: -1049017.6 | E71: 1.5976688e+08 | G71: =+VLOOKUP(H71,#REF!,1,FALSE()) -> #VALUE! | H71: 42540000 | I71: Tsinjo Fameno | K71: 449333.3
A72: 44412000 | B72: IR INTERMITENT ETRANGER | C72: 5301932.1 | E72: -3.8869024e+08 | G72: =+VLOOKUP(H72,#REF!,1,FALSE()) -> #VALUE! | H72: 42800000 | I72: Congés payés provision | K72: -286291175 | L72: -1.2036252e+08 | M72: -1.0843296e+08
A73: 44550000 | B73: Credit de taxe | C73: 1.2645259e+08 | E73: 0 | G73: =+VLOOKUP(H73,#REF!,1,FALSE()) -> #VALUE! | H73: 43100000 | I73: CNaPS | K73: -31479639 | L73: -27917350 | M73: -26888118
A74: 44561000 | B74: TVA pour les Biens | C74: 34183823 | E74: 7872143.3 | G74: =+VLOOKUP(H74,#REF!,1,FALSE()) -> #VALUE! | H74: 43110000 | I74: Allocation familiale CNAPS | K74: -440100 | L74: -1904100 | M74: -278100
A75: 44561000 | B75: TVA pour les Services | C75: 18957863 | E75: 10644361 | G75: =+VLOOKUP(H75,#REF!,1,FALSE()) -> #VALUE! | H75: 43200000 | I75: OSTIE | K75: -20986426 | L75: -18611567 | M75: -17925412
A76: 44561000 | B76: TVA pour l'Immobilisation | C76: 4426515.8 | E76: -47898200 | G76: =+VLOOKUP(H76,#REF!,1,FALSE()) -> #VALUE! | H76: 43300000 | I76: FMFP | K76: -3497737.7 | L76: -3101927.8 | M76: -2987568.6
A77: 44571000 | B77: TVA relatifs aux opéra° locales | C77: -21086970 | E77: 7740333.9 | G77: =+VLOOKUP(H77,#REF!,1,FALSE()) -> #VALUE! | H77: 43860000 | I77: Organismes autres charges à payer | K77: -18928935 | L77: -34629801 | M77: -32351713
A78: 44581000 | B78: TVA sur factures non parvenues | C78: 1761134.1 | E78: -4.7272873e+08 | G78: =+VLOOKUP(H78,#REF!,1,FALSE()) -> #VALUE! | H78: 44100000 | I78: Etat: IRSA à payer | K78: -14256380 | L78: -15129483 | M78: -16841462
A79: 45500001 | B79: C/C ISMAEL DANILHOUSSEN | C79: -4.7272873e+08 | E79: 0 | G79: =+VLOOKUP(H79,#REF!,1,FALSE()) -> #VALUE! | H79: 44200000 | I79: Etat : IFPB | K79: 0 | L79: -4488218 | M79: 0
A80: 45500002 | B80: C/C ISMAEL SHAHIM | C80: -13346443 | E80: 21850000 | G80: =+VLOOKUP(H80,#REF!,1,FALSE()) -> #VALUE! | H80: 44300000 | I80: Etat : acomptes IR | K80: 2.9293025e+08 | L80: 2.8879756e+08 | M80: 5.8958572e+08
A81: 46200000 | B81: Creances / cessions d'immo | C81: 51183811 | E81: 78733409 | G81: =+VLOOKUP(H81,#REF!,1,FALSE()) -> #VALUE! | H81: 44400000 | I81: Etat à payer | K81: 4362444.6 | L81: -1.0141028e+08 | M81: -3.8869024e+08
A82: 46600000 | B82: DIVERS TIERS | C82: 518446.2 | E82: 636050 | G82: =+VLOOKUP(H82,#REF!,1,FALSE()) -> #VALUE! | H82: 44410000 | I82: Crédit IR | K82: 4.2143476e+08 | L82: 2.3404748e+08 | M82: 0
A83: 46600000 | B83: Debiteurs & crediteurs divers | C83: 15084423 | G83: =+VLOOKUP(H83,#REF!,1,FALSE()) -> #VALUE! | H83: 44411000 | I83: IR Intermittent Locaux | K83: 0 | L83: -1049017.6 | M83: -2421270.9
A84: 46615000 | B84: EUROPAINTS REFACTURATION | C84: 16320 | E84: 26913065 | G84: =+VLOOKUP(H84,#REF!,1,FALSE()) -> #VALUE! | H84: 44412000 | I84: IR INTERMITENT ETRANGER | K84: 0 | L84: 5301932.1 | M84: 4327303.7
A85: 46617000 | B85: FIRST ENERGY REFACTURATION | C85: 27280265 | E85: 211500 | G85: =+VLOOKUP(H85,#REF!,1,FALSE()) -> #VALUE! | H85: 44420000 | I85: IR INTERMITENT LOCAUX | K85: -1688826.4
A86: 46621000 | B86: IDF REFACTURATION | C86: 187680 | E86: 432000 | G86: =+VLOOKUP(H86,#REF!,1,FALSE()) -> #VALUE! | H86: 44430000 | I86: IMPOT SUR LES RESULTATS (IR) | K86: -58908880
A87: 46622000 | B87: ID MOTORS REFACTURATION | C87: 509520 | E87: 126000 | G87: =+VLOOKUP(H87,#REF!,1,FALSE()) -> #VALUE! | H87: 44550000 | I87: Credit de taxe | K87: 1.5624579e+08 | L87: 1.2645259e+08 | M87: 1.5976688e+08
A88: 46623000 | B88: ID RENTAL REFACTURATION | C88: 550320 | E88: 63000 | G88: =+VLOOKUP(H88,#REF!,1,FALSE()) -> #VALUE! | H88: 44561000 | I88: TVA déductibles | K88: 0 | L88: 57568202 | M88: 38002768
A89: 46624000 | B89: MABEL REFACTURATION | C89: 48960 | E89: 166500 | G89: =+VLOOKUP(H89,#REF!,1,FALSE()) -> #VALUE! | H89: 44562000 | I89: TVA pour les Biens | K89: 16041712
A90: 46625000 | B90: MCM REFACTURATION | C90: 223620 | E90: 256500 | G90: =+VLOOKUP(H90,#REF!,1,FALSE()) -> #VALUE! | H90: 44563000 | I90: TVA Intermittente Déductible | K90: 3757950
A91: 46626000 | B91: MPL REFACTURATION | C91: 126480 | E91: 9000 | G91: =+VLOOKUP(H91,#REF!,1,FALSE()) -> #VALUE! | H91: 44564000 | I91: TVA pour les Services | K91: 9801247
A92: 46627000 | B92: NMP REFACTURATION | C92: 4080 | E92: 0 | G92: =+VLOOKUP(H92,#REF!,1,FALSE()) -> #VALUE! | H92: 44571000 | I92: TVA collectée | K92: -3757950 | L92: -21086970 | M92: -49847457
A93: 46628000 | B93: NOAH REFACTURATION | C93: 28560 | E93: 0 | G93: =+VLOOKUP(H93,#REF!,1,FALSE()) -> #VALUE! | H93: 44572000 | I93: TVA relatifs aux opéra° locale | K93: -6338500
A94: 46629000 | B94: RYA REFACTURATION | C94: 32640 | E94: 27000 | G94: =+VLOOKUP(H94,#REF!,1,FALSE()) -> #VALUE! | H94: 44581000 | I94: TVA sur factures non parvenues | K94: 0 | L94: 1761134.1 | M94: 7740333.9
A95: 46630000 | B95: AGRIKOBA REFACTURATION | C95: 138720 | E95: 63000 | G95: =+VLOOKUP(H95,#REF!,1,FALSE()) -> #VALUE! | H95: 44583000 | I95: TVA DED/ FACTURE NON PARVENUE | K95: 1928228.1
A96: 46632000 | B96: SIM REFACTURATION | C96: 20400 | E96: -2.683263e+08 | G96: =+VLOOKUP(H96,#REF!,1,FALSE()) -> #VALUE! | H96: 45500001 | I96: C/C ISMAEL DANILHOUSSEN | K96: 0 | L96: -4.7272873e+08 | M96: -4.7272873e+08
A97: 46634000 | B97: SMTP REFACTURATION | C97: -87205765 | E97: 144000 | G97: =+VLOOKUP(H97,#REF!,1,FALSE()) -> #VALUE! | H97: 45500002 | I97: C/C ISMAEL SHAHIM | K97: 0 | L97: -13346443 | M97: -13346443
A98: 46639000 | B98: UNITED MALAGASY REFACTURATION | C98: 144000 | E98: -2295000 | G98: =+VLOOKUP(H98,#REF!,1,FALSE()) -> #VALUE! | H98: 45511000 | I98: C/C ISMAEL DANIL HOUSSEN | K98: -4.2272873e+08
A99: 46640000 | B99: AGRIMOTORS REFACTURATION | C99: 20400 | E99: 1.3012122e+08 | G99: =+VLOOKUP(H99,#REF!,1,FALSE()) -> #VALUE! | H99: 45514000 | I99: C/C ISMAEL Shahim | K99: -13346443
A100: 46642000 | B100: AGRIVET ANTSIRABE | C100: 16320 | G100: =+VLOOKUP(H100,#REF!,1,FALSE()) -> #VALUE! | H100: 46200000 | I100: Creances / cessions d'immo | K100: 51183811 | L100: 51183811 | M100: 21850000
...

Sheet AGRIVET
D1: 2021 | E1: 2020 | F1: 2019
A2: Compte | B2: Société | C2: Libellé | G2: Compte de gestion | H2: Libellés - groupe
A3: 1010000 | B3: 10100000 | C3: CAPITAL | D3: -4000000000 | E3: -4000000000 | F3: -4000000000 | G3: 10100000 | H3: Capital
A4: 1061000 | B4: 10610000 | C4: RESERVES LÉGALES | D4: -400000000 | E4: -400000000 | F4: -400000000 | G4: 10610000 | H4: Reserves légales
A5: 1062000 | B5: 10620000 | C5: RESERVES FACULTATIVES | D5: -4.5342185e+08 | E5: -4.5342185e+08 | F5: -4.5342185e+08 | G5: 10620000 | H5: RESERVES FACULTATIVES
A6: 1100000 | B6: 11000000 | C6: RAN CREDITEUR | D6: -2.0417021e+10 | E6: -2.0264125e+10 | F6: -9.6521783e+09 | G6: 11000000 | H6: RAN Créditeur
A7: 1200000 | B7: 12000000 | C7: RESULTAT NET BENEFICE | D7: 0 | E7: 0 | F7: 0 | G7: 12000000 | H7: RESULTAT NET BENEFICE
A8: 1280000 | B8: 12800000 | C8: RESULTAT INSTANCE DAFFECTATION | D8: 0 | E8: 0 | F8: -3.7633088e+09 | G8: 12800000 | H8: Résultat en instance d'affectation
A9: 1640000 | B9: 16400000 | C9: EMPRUNTS BNI | D9: -9.135864e+08 | E9: -2000000000 | F9: 0 | G9: 16100000 | H9: Emprunts BNI
A10: 1642000 | B10: 16420000 | C10: Emprunts BMOI MGA | D10: -3.6228689e+09 | E10: -6000000000 | F10: 0 | G10: 16130000 | H10: Emprunts BMOI MGA
A11: 1643000 | B11: 16430000 | C11: BOA PRET COLLECTIF | D11: -3.9734415e+08 | G11: 16430000
A12: 1688500 | B12: 16885000 | C12: Intérêts couru sur emprunts | D12: 0 | E12: -66824742 | F12: 0 | G12: 16884000 | H12: Intérêts couru sur emprunts
A13: 2040000 | B13: 20400000 | C13: LOGICIEL INFO & ASSIMILÉ | D13: 89779560 | E13: 89779560 | F13: 2.6393684e+08 | G13: 20400000 | H13: Logiciels informatiques & assimilés
A14: 2080000 | B14: 20800000 | C14: AUTRES IMMO INCORPORELLES | D14: 11536530 | G14: 20800000
A15: 2120000 | B15: 21200000 | C15: AGENCEMENT AMENAGEMENT TERRAIN | D15: 9054500 | E15: 4654500 | F15: 4654500 | G15: 21200000 | H15: Agencement amenagement terrain
A16: 2130000 | B16: 21300000 | C16: CONSTRUCTIONS | D16: 92084865 | E16: 59268359 | F16: 53086164 | G16: 21300000 | H16: Batiments - Constructions
A17: 2150000 | B17: 21500000 | C17: AGENCEMENT AMENAGEMENT INSTAL | D17: 7.0941593e+08 | E17: 6.8180496e+08 | F17: 6.7257296e+08 | G17: 21500000 | H17: Agencement aménagement
A18: 2153000 | B18: 21530000 | C18: Agenc Amenag Batiment | D18: 0 | E18: 0 | F18: 0 | G18: 21500000 | H18: Agencement aménagement
A19: 2151000 | B19: 21510000 | C19: INSTALLATIONS TELEPHONIQUES | D19: 6314534 | E19: 6314534 | F19: 6314534 | G19: 21520000 | H19: Installations
A20: 2152000 | B20: 21520000 | C20: INSTALLATION CAMERA | D20: 54908530 | E20: 54908530 | F20: 54908530 | G20: 21520000 | H20: Installations
A21: 2181000 | B21: 21810000 | C21: MATÉRIELS & OUTILLAGES | D21: 1.096365e+09 | E21: 1.056192e+09 | F21: 1.0167907e+09 | G21: 21540000 | H21: Matériels & outillages
A22: 2182000 | B22: 21820000 | C22: MMB | D22: 89776925 | E22: 83474134 | F22: 74048092 | G22: 21820000 | H22: MMB
A23: 2185000 | B23: 21850000 | C23: MATERIEL &MOBILIER DE LOGEMENT | D23: 8621314.5 | E23: 8621314.5 | F23: 8621314.5 | G23: 21820000 | H23: MMB
A24: 2186000 | B24: 21860000 | C24: MATERIEL DE LABORATOIRE | D24: 2810305 | E24: 2810305 | F24: 2810305 | G24: 21820000 | H24: MMB
A25: 2187000 | B25: 21870000 | C25: MATERIEL & MOBILIER DE MAGASIN | D25: 10263847 | E25: 10263847 | F25: 10263847 | G25: 21820000 | H25: MMB
A26: 2183000 | B26: 21830000 | C26: MATERIEL DE TRANSPORT | D26: 9.8383174e+08 | E26: 1.0592942e+09 | F26: 9.649424e+08 | G26: 21830000 | H26: Materiel de transport
... A32: 2804000 | B32: 28040000 | C32: AMTS LOGICIEL INFORMATIQUE | D32: -66952203 | E32: -45715393 | F32: -65642767 | G32: 28040000 | H32: Amts logiciel informatique
A33: 2808000 | B33: 28080000 | C33: AMTS AMO INCORPO | D33: -913308.63 | G33: 28080000 | H33: =+C:C -> AMTS AMO INCORPO
A34: 2812000 | B34: 28120000 | C34: AMORT AGENC AMENAG TERRAIN | D34: -2385289.9 | E34: -1917395.4 | F34: -1451945.4 | G34: 28120000 | H34: Amts Agens Amenag Terrain
A35: 2813000 | B35: 28130000 | C35: AMTS CONSTRUCTIONS | D35: -60485037 | E35: -54774933 | F35: -53086164 | G35: 28130000 | H35: Amts batiments et constructions
A36: 2815000 | B36: 28150000 | C36: AMTS AGEN.AMEN.INSTAL. | D36: -4.4697739e+08 | E36: -3.7732355e+08 | F36: -3.0988051e+08 | G36: 28150000 | H36: Amts agen. amen.instal.
A37: 2815100 | B37: 28151000 | C37: AMORT INSTALLATION TELEPHONIQU | D37: -5175941.5 | E37: -4717888.1 | F37: -4259834.7 | G37: 28152000 | H37: AMORT INSTALLATION TELEPHONIQUE & ELECTRIQUE
A38: 2815200 | B38: 28152000 | C38: AMORT INSTALLATION CAMERA | D38: -54908530 | E38: -54908530 | F38: -54908530 | G38: 28152000 | H38: AMORT INSTALLATION TELEPHONIQUE & ELECTRIQUE
A39: 2818100 | B39: 28181000 | C39: AMTS MATERIELS & OUTILLAGE | D39: -5.8247933e+08 | E39: -4.8527236e+08 | F39: -3.8967224e+08 | G39: 28154000 | H39: AMORT SUR MAT ET OUT INDUSTRIEL
A40: 2818200 | B40: 28182000 | C40: AMTS MMB | D40: -46940804 | E40: -40018542 | F40: -33974959 | G40: 28182000 | H40: Amts MMB
A41: 2818400 | B41: 28184000 | C41: AMTS MATERIEL INFORMATIQUE | D41: -1.9541498e+08 | E41: -1.4159418e+08 | F41: -92594943 | G41: 28182000 | H41: Amts MMB
A42: 2818500 | B42: 28185000 | C42: AMTS MAT & MOB DE LOGT | D42: -5691644.9 | E42: -4829513.5 | F42: -3967382 | G42: 28182000 | H42: Amts MMB
A43: 2818700 | B43: 28187000 | C43: AMORT MAT & MOB DE MAGASIN | D43: -10235222 | E43: -10063472 | F43: -9891721.7 | G43: 28182000 | H43: Amts MMB
A44: 2818300 | B44: 28183000 | C44: AMTS MATERIEL DE TRANSPORT | D44: -7.7868285e+08 | E44: -7.9764443e+08 | F44: -7.5399697e+08 | G44: 28183000 | H44: AMT matériel de transport
A45: 2818600 | B45: 28186000 | C45: AMORT MAT LABORATOIRE | D45: -2810305 | E45: -2599532.1 | F45: -2318501.6 | G45: 28184000 | H45: Amts materiel informatique
... A70: 4252000 | B70: 42520000 | C70: Avances speciales | D70: 15039833 | E70: 11339833 | F70: 1641500 | G70: 42520000 | H70: Avances speciales
A71: 4254000 | B71: 42540000 | C71: Tsinjo Fameno | D71: 1005666.7 | G71: 42540000 | H71: Avances speciales
A72: 4280000 | B72: 42800000 | C72: PERSONNEL CONGES PAYES | D72: -121247723 | E72: -1.2832649e+08 | F72: 0 | G72: 42800000 | H72: Congés payés provision
A73: 4310000 | B73: 43100000 | C73: CNAPS | D73: -64050124 | E73: -61652234 | F73: -59766522 | G73: 43100000 | H73: CNaPS
A74: 4311000 | B74: 43110000 | C74: CNAPS ALLOCAT° FAMILIALES | D74: -1672000 | E74: -1132600 | F74: -302000 | G74: 43110000 | H74: Allocation familiale CNAPS
A75: 4320000 | B75: 43200000 | C75: OSTIE | D75: -26600926 | E75: -26653814 | F75: -24447817 | G75: 43200000 | H75: OSTIE
A76: 4322000 | B76: 43220000 | C76: FUNHECE | D76: -295045.14 | G76: 43200000 | H76: OSTIE
A77: 4323000 | B77: 43230000 | C77: SMIA | D77: -1166406.4 | E77: -1166406.4 | F77: -1166406.4 | G77: 43200000 | H77: OSTIE
A78: 4330000 | B78: 43300000 | C78: FMFP | D78: -4644269.1 | E78: -4982302.4 | F78: -4269037.2 | G78: 43300000 | H78: FMFP
A79: 4386000 | B79: 43860000 | C79: ORGANISME-AUTRE CHARGE A PAYER | D79: 16218458 | E79: -51646849 | F79: 0 | G79: 43860000 | H79: Organismes autres charges à payer
A80: 4410000 | B80: 44100000 | C80: ETAT: IRSA À PAYER | D80: -43139610 | E80: -56910914 | F80: -37319657 | G80: 44100000 | H80: Etat: IRSA à payer
A81: 4430000 | B81: 44300000 | C81: ETAT: ACOMPTES IR | D81: 0 | E81: 1.5612082e+09 | F81: 1.3739105e+09 | G81: 44300000 | H81: Etat : acomptes IR
A82: 4400000 | B82: 44000000 | C82: ETAT A PAYER | D82: 0 | E82: 0 | F82: -2.0111432e+08 | G82: 44400000 | H82: Etat à payer
A83: 4443000 | B83: 44430000 | C83: IMPOT SUR LES RESULTATS (IR) | D83: 0 | E83: 0 | F83: 0 | G83: 44400000 | H83: Etat à payer
A84: 44400000 | B84: 44400000 | C84: ETAT à payer: IR | D84: 2.057828e+09 | G84: 44400000
A85: 4441000 | B85: 44410000 | C85: CREDIT D'IR | D85: 0 | E85: 0 | F85: -1.8104082e+09 | G85: 44410000 | H85: Crédit IR
A86: 4442000 | B86: 44420000 | C86: IR INTERMITENT LOCAUX | D86: -161116.12 | E86: -476905.59 | F86: -3683634 | G86: 44411000 | H86: IR Intermittent Locaux
A87: 4440000 | B87: 44400000 | C87: IR INTERMITENT ETRANGER | D87: -1126589.2 | E87: 4790031.1 | F87: 3860053.7 | G87: 44412000 | H87: IR INTERMITENT ETRANGER
A88: 4454000 | B88: 44540000 | C88: TVA À DÉCAISSER | D88: 0 | E88: 0 | F88: -66059083 | G88: 44540000 | H88: TVA à décaisser
A89: 4455000 | B89: 44550000 | C89: CREDIT DE TAXE | D89: 4.1618898e+08 | E89: 3.045187e+08 | F89: 0 | G89: 44550000 | H89: Credit de taxe
A90: 4456100 | B90: 44561000 | C90: TVA dédu sur revente taxable | D90: 583063.22 | E90: 98897379 | F90: -6722144 | G90: 44561000 | H90: TVA déductibles
A91: 4456110 | B91: 44561100 | C91: TVA déd sur revente non tax | D91: 0 | E91: 0 | F91: -14328778 | G91: 44561000 | H91: TVA déductibles
A92: 4456200 | B92: 44562000 | C92: TVA pour les Biens | D92: 8436706.7 | E92: 6990708 | F92: -1242697.7 | G92: 44561000 | H92: TVA déductibles
A93: 4456300 | B93: 44563000 | C93: TVA Intermittente Déductible | D93: 25242384 | E93: 13425020 | F93: 11341731 | G93: 44561000 | H93: TVA déductibles
A94: 4456400 | B94: 44564000 | C94: TVA pour les Services | D94: 11630756 | E94: 16389767 | F94: 95418766 | G94: 44561000 | H94: TVA déductibles
A95: 4456500 | B95: 44565000 | C95: TVA pour l'Immobilisation | D95: -723333.01 | E95: 1021424.4 | F95: 10629692 | G95: 44561000 | H95: TVA déductibles
A96: 4457100 | B96: 44571000 | C96: TVA Intermittente collectéé | D96: -25242384 | E96: -13425020 | F96: -11341731 | G96: 44571000 | H96: TVA collectée
... A110: 4660000 | B110: 46600000 | C110: Debiteurs & crediteurs divers | D110: 72685878 | E110: 75685878 | F110: -11241880 | G110: 46600000 | H110: Debiteurs & crediteurs divers
A111: 4661000 | B111: 46610000 | C111: DIVERS | E111: 49904966 | G111: 46600000 | H111: Debiteurs & crediteurs divers
A112: 4661000 | B112: 46610000 | C112: DEBITEURS&CREDITEURS DIV/REFAC | D112: 8.8867523e+08 | E112: 61258 | F112: 31308478 | G112: 46610000 | H112: AGRIFARM REFACTURATION
A113: 4661000 | B113: 46610000 | C113: BOVIMA | E113: 39675300 | G113: 46611000 | H113: BOVIMA REFACTURATION
A114: 4661000 | B114: 46610000 | C114: FIRST-ENERGY | E114: 483154 | G114: 46617000 | H114: FIRST ENERGY REFACTURATION
A115: 4661000 | B115: 46610000 | C115: FIRST-INVES | E115: 5981795.9 | G115: 46618000 | H115: FIRST INVESTISSEMENT REFACTURATION
A116: 4662000 | B116: 46620000 | C116: PROVISION ND / REFACTURATION | D116: -9.155254e+08 | G116: 46620000
A117: 4661000 | B117: 46610000 | C117: IDMOTO | E117: 38424715 | G117: 46622000 | H117: ID MOTORS REFACTURATION
A118: 4661000 | B118: 46610000 | C118: IDRENTAL | E118: 123500 | G118: 46623000 | H118: ID RENTAL REFACTURATION
A119: 4661000 | B119: 46610000 | C119: RCM | E119: 35482888 | G119: 46631000 | H119: RCM REFACTURATION
A120: 4661000 | B120: 46610000 | C120: SMTP | E120: 57808002 | G120: 46634000 | H120: SMTP REFACTURATION
A121: 4661000 | B121: 46610000 | C121: SMOI | E121: 6442990 | G121: 46635000 | H121: SMOI
A122: 4661000 | B122: 46610000 | C122: UNITEDMALAGASY | E122: 1628300 | G122: 46639000 | H122: UNITED MALAGASY REFACTURATION
A123: 4661000 | B123: 46610000 | C123: AGRIMOTORS | E123: 24116184 | G123: 46640000 | H123: AGRIMOTORS REFACTURATION
A124: 4661000 | B124: 46610000 | C124: AGRIVET-MAJU | E124: 12573440 | G124: 46641000 | H124: AGRIVET-MAJU REFACTURATION
A125: 4661000 | B125: 46610000 | C125: AGRIVET-AB | E125: 186201900 | G125: 46642000 | H125: AGRIVET ANTSIRABE REFACTURATION
A126: 4661000 | B126: 46610000 | C126: AGRIVET-F | E126: 63478923 | G126: 46643000 | H126: AGRIVET FIANARANTSOA REFACTURATION
A127: 4661000 | B127: 46610000 | C127: AGRIMA | E127: -13200000 | G127: 46644000 | H127: AGRIMA REFACTURATION
A128: 4661000 | B128: 46610000 | C128: AGRIVAL | E128: 159339.27 | G128: 46650000 | H128: AGRIVAL REFACTURATION
... A132: 4670000 | B132: 46700000 | C132: DIVERS TIERS | E132: 49679.1 | G132: 46700001 | H132: Créances intra groupes/ Prêt
A133: 4670000 | B133: 46700000 | C133: Créances intra groupes/ Prêt | F133: 9.1001508e+09 | G133: 46700001 | H133: Créances intra groupes/ Prêt
A134: 4670000 | B134: 46700000 | C134: BOVIMA | E134: 5598500000 | G134: 46712000 | H134: BOVIMA PRÊT
A135: 4670000 | B135: 46700000 | C135: AGRIFEED | E135: 1905500000 | G135: 46714000 | H135: AGRIFEED PRÊT
A136: 4670000 | B136: 46700000 | C136: SMTP | E136: 1.4289182e+08 | G136: 46715000 | H136: SMTP PRÊT
A137: 4670000 | B137: 46700000 | C137: AGRIVAL | E137: -500000000 | G137: 46716000 | H137: AGRIVAL PRET
A138: 4670000 | B138: 46700000 | C138: NMP | E138: 320000000 | G138: 46718000 | H138: NMP PRÊT
A139: 4670000 | B139: 46700000 | C139: PRET ET EMPRUNT- INTRA GROUPE | D139: 1.7164171e+10 | E139: -310000000 | G139: 46720000 | H139: AGRIFARM PRET
A140: 4670000 | B140: 46700000 | C140: ID MOTORS | E140: 190000000 | G140: 46721000 | H140: ID MOTORS PRÊT
A141: 4670000 | B141: 46700000 | C141: AMCHO | E141: 80459709 | G141: 46732000 | H141: AMCHO
A142: 4670000 | B142: 46700000 | C142: FLY TECHNOLOGIE | E142: 833000000 | G142: 46733000 | H142: FLY TECHNOLOGIE
A143: 4670000 | B143: 46700000 | C143: AGRIVOLA | E143: 147869800 | G143: 46734000 | H143: AGRIVOLA
A144: 4670000 | B144: 46700000 | C144: NOAH | E144: 1000000 | G144: 46736000 | H144: NOAH PRÊT
A145: 4670000 | B145: 46700000 | C145: AGRIMOTORS | E145: 650000000 | G145: 46737000 | H145: AGRIMOTORS PRÊT
...

Sheet AGRIVAL
D1: 2021 | E1: 2020 | F1: 2019
A2: Comptes | B2: Société | C2: Libellés | G2: Gestion
A3: 1010000 | B3: 10100000 | C3: CAPITAL | D3: -3980000000 | E3: -3980000000 | F3: -3980000000 | G3: 10100000
A4: 1061000 | B4: 10610000 | C4: RESERVES LÉGALES | D4: -398000000 | E4: -398000000 | F4: -398000000 | G4: 10610000
A5: 1100000 | B5: 11000000 | C5: RAN CREDITEUR | D5: -2.2975565e+10 | E5: -1.6005083e+10 | F5: -7.1772044e+09 | G5: 11000000
A6: 1200000 | B6: 12000000 | C6: RESULTAT NET BENEFICE | D6: 0 | E6: 0 | F6: 0 | G6: 12000000
A7: 1280000 | B7: 12800000 | C7: RESULTAT INSTANCE DAFFECTATION | D7: 0 | E7: 0 | F7: -3.0943388e+09 | G7: 12800000
A8: 1620000 | B8: 16200000 | C8: EMPRUNTS BFV | D8: 0 | E8: 0 | F8: 0 | G8: 16200000
A9: 1642000 | B9: 16420000 | C9: Emprunts BMOI MGA | D9: -5.1787519e+09 | E9: -7.8144285e+09 | F9: -9.4738335e+09 | G9: 16420000
B10: 16500000 | C10: PMT - 1an | D10: -1.6510591e+09 | G10: 16500000
A11: 1688500 | B11: 16885000 | C11: Intérêts couru sur emprunts | D11: 0 | E11: -26496378 | F11: -48392389 | G11: 16885000
A12: 2040000 | B12: 20400000 | C12: LOGICIEL INFO & ASSIMILÉ | D12: 21223664 | E12: 21223664 | F12: 21223664 | G12: 20400000
A13: 2050000 | B13: 20500000 | C13: CONCESSION & DROIT SIMILAIRE | D13: 6174624.8 | E13: 6174624.8 | F13: 6174624.8 | G13: 20500000
A14: 2110000 | B14: 21100000 | C14: TERRAINS | D14: 256800000 | E14: 214200000 | F14: 79000000 | G14: 21100000
A15: 2120000 | B15: 21200000 | C15: AGENCEMENT AMENAGEMENT TERRAIN | D15: 3.3584859e+08 | E15: 3.3584859e+08 | F15: 1.7826659e+08 | G15: 21200000
A16: 2130000 | B16: 21300000 | C16: CONSTRUCTIONS | D16: 1.0186381e+10 | E16: 9.8090212e+09 | F16: 1.0777035e+10 | G16: 21300000
A17: 2150000 | B17: 21500000 | C17: AGENCEMENT AMENAGEMENT INSTAL | D17: 94238265 | E17: 80159882 | F17: 73654882 | G17: 21500000
A18: 2152000 | B18: 21520000 | C18: INSTALLATION CAMERA | D18: 17308000 | E18: 17308000 | F18: 17308000 | G18: 21520000
A19: 2153000 | B19: 21530000 | C19: Agenc Amenag Batiment | D19: 6.0497491e+08 | E19: 4.1427275e+08 | F19: 3.4707275e+08 | G19: 21530000
A20: 2181000 | B20: 21810000 | C20: MATÉRIELS & OUTILLAGES | D20: 1.2516839e+10 | E20: 1.2378615e+10 | F20: 1.125158e+10 | G20: 21810000
A21: 2182000 | B21: 21820000 | C21: MMB | D21: 1.012011e+08 | E21: 84742607 | F21: 66463180 | G21: 21820000
A22: 2183000 | B22: 21830000 | C22: MATERIEL DE TRANSPORT | D22: 4.2199605e+08 | E22: 4.0969674e+08 | F22: 4.4700586e+08 | G22: 21830000
... A63: 4250000 | B63: 42500000 | C63: AVANCES & ACOMPTESAU PERSONNEL | D63: 0 | E63: 0 | F63: 0 | G63: 42500000
B64: 42510000 | C64: Avances quinzaines | D64: 55000 | G64: 42510000
A65: 4252000 | B65: 42520000 | C65: Avances speciales | D65: -176999.85 | E65: -739999.95 | F65: -1.1920929e-09 | G65: 42520000
B66: 42540000 | C66: Tsinjo Fameno | D66: -1107164.2 | G66: 42540000
A67: 4280000 | B67: 42800000 | C67: PERSONNEL CONGES PAYES | D67: -209778785 | E67: -1.2401674e+08 | F67: -1.1148906e+08 | G67: 42800000
A68: 4310000 | B68: 43100000 | C68: CNAPS | D68: -57146780 | E68: -47515147 | F68: -43171089 | G68: 43100000
A69: 4311000 | B69: 43110000 | C69: CNAPS ALLOCAT° FAMILIALES | D69: -1231300 | E69: -1210600 | F69: -1066600 | G69: 43110000
A70: 4320000 | B70: 43200000 | C70: OSTIE | D70: -24279875 | E70: -20363634 | F70: -18501895 | G70: 43200000
B71: 43220000 | C71: FUNHECE | D71: -211602 | G71: 43220000
A72: 4330000 | B72: 43300000 | C72: FMFP | D72: -4072888.8 | E72: -3393939.1 | F72: -3083649.2 | G72: 43300000
A73: 4386000 | B73: 43860000 | C73: ORGANISME-AUTRE CHARGE A PAYER | D73: -19183516 | E73: -33175330 | F73: -32361273 | G73: 43860000
A74: 4400000 | B74: 44000000 | C74: ETAT A PAYER | D74: 0 | E74: 0 | F74: -4.3262382e+08 | G74: 44000000
A75: 4410000 | B75: 44100000 | C75: ETAT: IRSA À PAYER | D75: -31630680 | E75: -28143960 | F75: -23435012 | G75: 44100000
A76: 4430000 | B76: 44300000 | C76: ETAT: ACOMPTES IR | D76: 0 | E76: 6.1614262e+08 | F76: 5.3749559e+08 | G76: 44300000
A77: 4440000 | B77: 44400000 | C77: IR INTERMITENT ETRANGER | D77: 8843961.3 | E77: 9756010.8 | F77: -6244970.6 | G77: 44400000
A78: 4441000 | B78: 44410000 | C78: CREDIT D'IR | D78: 3.4649744e+08 | E78: -1.9073486e-08 | F78: 72648763 | G78: 44410000
A79: 4442000 | B79: 44420000 | C79: IR INTERMITENT LOCAUX | D79: -3880047.4 | E79: -2963305.3 | F79: -2005052.8 | G79: 44420000
A80: 4443000 | B80: 44430000 | C80: IMPOT SUR LES RESULTATS (IR) | D80: 0 | E80: 0 | F80: -6.9195909e+08 | G80: 44430000
A81: 4455000 | B81: 44550000 | C81: CREDIT DE TAXE | D81: 9.7031402e+08 | E81: 3.773606e+08 | F81: 1.1524003e+09 | G81: 44550000
A82: 4456100 | B82: 44561000 | C82: TVA dédu sur revente taxable | D82: 17594117 | E82: 49353 | F82: 151265.94 | G82: 44561000
A83: 4456110 | B83: 44561100 | C83: TVA déd sur revente non tax | D83: -982937.25 | E83: 0 | F83: 0 | G83: 44561100
... A91: 4458300 | B91: 44583000 | C91: TVA DED/ FACTURE NON PARVENUE | D91: 320554.06 | E91: 2036854.1 | F91: 3348663 | G91: 44583000
B92: 44584000 | C92: TVA COL/ FACTURE A ETABLIR | D92: 292600 | G92: 44584000
A93: 4551100 | B93: 45511000 | C93: C/C ISMAEL DANIL HOUSSEN | D93: -20647327 | E93: -20647327 | F93: -20647327 | G93: 45511000
A94: 4553000 | B94: 45530000 | C94: AGRIKOBA | D94: 1494000000 | E94: 2594000000 | F94: 2074000000 | G94: 45530000
A95: 4554000 | B95: 45540000 | C95: AGRIVET COMPTE COURANT | D95: -227800000 | E95: -227800000 | F95: -227800000 | G95: 45540000
A96: 4555000 | B96: 45550000 | C96: SMTP COMPTE COURANT | D96: -2500000 | E96: -2500000 | F96: -2500000 | G96: 45550000
A97: 4620000 | B97: 46200000 | C97: Créances sur cession d'immobil | D97: 0 | E97: -3.0517578e-07 | F97: 0 | G97: 46200000
A98: 4660000 | B98: 46600000 | C98: Debiteurs & crediteurs divers | D98: 2194818.6 | E98: 42174639 | F98: 22508194 | G98: 46600000
A99: 4661000 | B99: 46610000 | C99: AGRIFARM | D99: 7.1473392e+08 | E99: 1.0962446e+08 | F99: -1.2688495e+08 | G99: 46610000
A100: 4661000 | B100: 46610000 | C100: AGRIFEED | E100: 740732.84 | F100: 0 | G100: 46610000
A101: 4661000 | B101: 46610000 | C101: AGRIKOBA | E101: 50464197 | F101: 2.4445529e+08 | G101: 46610000
A102: 4661000 | B102: 46610000 | C102: AGRIVAL | E102: 0 | F102: 0 | G102: 46610000
A103: 4661000 | B103: 46610000 | C103: AGRIVET ANTSIRABE | E103: 102466.5 | F103: 0 | G103: 46610000
A104: 4661000 | B104: 46610000 | C104: AGRIVET | E104: -159339.27 | F104: -245799.84 | G104: 46610000
A105: 4661000 | B105: 46610000 | C105: AMCHO | E105: 3.9844948e+08 | F105: 2.0305619e+08 | G105: 46610000
A106: 4661000 | B106: 46610000 | C106: BOVIMA | E106: 5152428.7 | F106: 3996885.4 | G106: 46610000
A107: 4661000 | B107: 46610000 | C107: IFC | E107: 0 | F107: 0 | G107: 46610000
A108: 4661000 | B108: 46610000 | C108: FLY TECHNOLOGIE | E108: 0 | F108: 8874000 | G108: 46610000
A109: 4661000 | B109: 46610000 | C109: IDF | E109: 0 | F109: 0 | G109: 46610000
A110: 4661000 | B110: 46610000 | C110: ID MOTORS | E110: 1918681 | F110: 1918681 | G110: 46610000
A111: 4661000 | B111: 46610000 | C111: ID RENTAL | E111: 799991.47 | F111: 2200000 | G111: 46610000
... A114: 4661000 | B114: 46610000 | C114: SMTP | E114: -68765708 | F114: -3.7473218e+08 | G114: 46610000
B115: 46620000 | C115: PROVISION ND / REFACTURATION | D115: -1161419391 | G115: 46620000
A116: 4670000 | B116: 46700000 | C116: CRÉANCES INTRA GROUPE/ PRET | D116: 7.0281696e+09 | E116: -3.4863972e+09 | F116: 2295000 | G116: 46700000
A117: 4670000 | B117: 46700000 | C117: AGRIKOBA | E117: 4.1461002e+08 | F117: 0 | G117: 46700000
A118: 4670000 | B118: 46700000 | C118: AGRIVET TAMATAVE | E118: -2000000 | F118: -2000000 | G118: 46700000
A119: 4670000 | B119: 46700000 | C119: AGRIVET | E119: 500000000 | F119: 0 | G119: 46700000
A120: 4670000 | B120: 46700000 | C120: AMCHO | E120: 0 | F120: 0 | G120: 46700000
A121: 4670000 | B121: 46700000 | C121: BOVIMA | E121: 60000000 | F121: 60000000 | G121: 46700000
A122: 4670000 | B122: 46700000 | C122: FIRST INVESTISSEMENT | E122: 1185583330 | F122: 0 | G122: 46700000
A123: 4670000 | B123: 46700000 | C123: IFC /PRET MABEL | E123: -4.2280091e+09 | F123: -5.9178327e+09 | G123: 46700000
A124: 4670000 | B124: 46700000 | C124: LMOI | E124: 120000000 | F124: 120000000 | G124: 46700000
A125: 4670000 | B125: 46700000 | C125: MABEL | E125: 1.8447783e+09 | F125: 805000000 | G125: 46700000
A126: 4670000 | B126: 46700000 | C126: SMTP | E126: 0 | F126: 0 | G126: 46700000
B127: 47100000 | C127: COMPTE D'ATTENTE | D127: -1047236.5 | G127: 47100000
A128: 4860000 | B128: 48600000 | C128: CHARGES CONSTATÉES D'AVANCE | D128: 1885130 | E128: 6620349.5 | F128: 37243287 | G128: 48600000
A129: 4870000 | B129: 48700000 | C129: PRODUITS CONSTATÉS D'AVANCE | D129: -25000000 | E129: -25000000 | F129: -62318365 | G129: 48700000
A130: 4910000 | B130: 49100000 | C130: PERTES DE VALEUR/CPTES CLIENTS | D130: -1.6136468e+09 | E130: -3.2924163e+09 | F130: -2.8478692e+09 | G130: 49100000
A131: 5111000 | B131: 51110000 | C131: CHÈQUE À ENCAISSER | D131: 348872800 | E131: 469785000 | F131: 112432000 | G131: 51110000
A132: 5112211 | B132: 51122110 | C132: TRAITE RECUE ENC BMOI | D132: 0 | E132: 0 | F132: 0 | G132: 51122110
A133: 5112212 | B133: 51122120 | C133: TRAITE RECUE ESC BMOI | D133: 0 | E133: 0 | F133: 0 | G133: 51122120
A134: 5112221 | B134: 51122210 | C134: TRAITE RECUE ENC BFV | D134: 0 | E134: 8518983 | F134: 0 | G134: 51122210
A135: 5112222 | B135: 51122220 | C135: TRAITE RECUE ESC BFV | D135: 0 | E135: 0 | F135: 0 | G135: 51122220
A136: 5112231 | B136: 51122310 | C136: TRAITE RECUE ENC BOA | D136: 95744060 | E136: 0 | F136: 0 | G136: 51122310
A137: 5112241 | B137: 51122410 | C137: TRAITE RECUE ENC BNI | D137: 20000000 | E137: 0 | F137: 78610000 | G137: 51122410
A138: 5112242 | B138: 51122420 | C138: TRAITE RECUE ESC BNI | D138: 1.6375069e+09 | E138: 0 | F138: 0 | G138: 51122420
A139: 5112261 | B139: 51122610 | C139: TRAITE RECUE ENC SBM | D139: 0 | E139: 0 | F139: 226656809 | G139: 51122610
... A152: 5126300 | B152: 51263000 | C152: SBM USD | D152: 0 | E152: 26571469 | F152: 25198935 | G152: 51263000
B153: 51264000 | C153: SBM USD | D153: 33588087 | G153: 51264000
B154: 51270000 | C154: MCB | D154: -24000 | G154: 51270000
B155: 51800000 | C155: INTERETS COURUS | D155: -23637375 | G155: 51800000
A156: 5191000 | B156: 51910000 | C156: ASM BFV | D156: -6000000000 | E156: -1000000000 | F156: -3000000000 | G156: 51910000
A157: 5192000 | B157: 51920000 | C157: ASM BNI | D157: -8500000000 | E157: -1500000000 | F157: -5500000000 | G157: 51920000
A158: 5193000 | B158: 51930000 | C158: ASM BGFI | D158: 0 | E158: 0 | F158: 0 | G158: 51930000
A159: 5194000 | B159: 51940000 | C159: ASM BMOI | D159: -950000000 | E159: 0 | F159: -1500000000 | G159: 51940000
A160: 5195000 | B160: 51950000 | C160: ASM BOA | D160: -4000000000 | E160: 0 | F160: -500000000 | G160: 51950000
A161: 5196000 | B161: 51960000 | C161: ASM SBM | D161: 0 | E161: 0 | F161: -1.4797786e+08 | G161: 51960000
...

Sheet SMTP
F1: 2021 | G1: 2020 | H1: EF CONSO 2019 | I1: 2019
F2: =SUBTOTAL(9,F3:F357) -> -0.0014999106 | G2: =SUBTOTAL(9,G3:G195) -> 0.0021070696 | H2: =SUBTOTAL(9,H3:H195) -> 0.00061593644 | I2: =SUBTOTAL(9,I3:I195) -> 0.00061593644 | K2: Compte société | L2: Compte de gestion | M2: Compte société | N2: Libellé | O2: Montant
A3: 1 | B3: 10 | C3: 101 | D3: 10100000 | E3: Capital | F3: -7050000000 | G3: -7050000000 | H3: -7050000000 | I3: -7050000000 | K3: 10100000 | L3: 10100000 | M3: =+VLOOKUP(D3,AGRIVET!$B$3:$G$348,5,FALSE()) -> -4000000000 | N3: Capital | O3: -7050000000
A4: 1 | B4: 10 | C4: 106 | D4: 10610000 | E4: Reserves légales | F4: -705000000 | G4: -705000000 | H4: -705000000 | I4: -705000000 | K4: 10610000 | L4: 10610000 | M4: =+VLOOKUP(D4,AGRIVET!$B$3:$G$348,5,FALSE()) -> -400000000 | N4: Réserve légale | O4: -705000000
A5: 1 | B5: 11 | C5: 110 | D5: 11000000 | E5: RAN Créditeur | F5: -4.9782395e+09 | G5: -4.9782395e+09 | H5: -4.0392523e+09 | I5: -4.0392523e+09 | K5: 11000000 | L5: 11000000 | M5: =+VLOOKUP(D5,AGRIVET!$B$3:$G$348,5,FALSE()) -> -9.6521783e+09 | N5: RAN (solde créditeur) | O5: -4.9782395e+09
A6: 1 | B6: 12 | C6: 128 | D6: 12800000 | E6: Résultat en instance d'affectation | F6: 0 | G6: 0 | H6: -5.4257172e+08 | I6: -5.4257172e+08 | K6: 16412000 | L6: 16100000 | M6: =+VLOOKUP(D6,AGRIVET!$B$3:$G$348,5,FALSE()) -> -3.7633088e+09 | N6: Emprunt BNI | O6: -1000000000
A7: 1 | B7: 16 | C7: 161 | D7: 16100000 | E7: Emprunts BNI | F7: 0 | G7: -1000000000 | H7: 0 | I7: 0 | K7: 16880000 | L7: 16884000 | M7: =+VLOOKUP(D7,AGRIVET!$B$3:$G$348,5,FALSE()) -> #N/A | N7: Intérêts courus | O7: -5448008.9
A8: 1 | B8: 16 | C8: 168 | D8: 16884000 | E8: Intérêts couru sur emprunts | F8: 0 | G8: -19313948 | H8: 0 | I8: 0 | K8: 16884000 | L8: 16884000 | M8: =+VLOOKUP(D8,AGRIVET!$B$3:$G$348,5,FALSE()) -> #N/A | N8: Intérêts courus emprunts | O8: -13865939
A9: 2 | B9: 20 | C9: 204 | D9: 20400000 | E9: Logiciels informatiques & assimilés | F9: 1.6807905e+08 | G9: 1.6807905e+08 | H9: 1.6807905e+08 | I9: 1.6807905e+08 | K9: 20400000 | L9: 20400000 | M9: =+VLOOKUP(D9,AGRIVET!$B$3:$G$348,5,FALSE()) -> 2.6393684e+08 | N9: Logiciels informatiques & assi | O9: 1.6807905e+08
A10: 2 | B10: 21 | C10: 211 | D10: 21100000 | E10: Terrains | F10: 3.9774084e+08 | G10: 3.9774084e+08 | H10: 480198000 | I10: 480198000 | K10: 21100000 | L10: 21100000 | M10: =+VLOOKUP(D10,AGRIVET!$B$3:$G$348,5,FALSE()) -> #N/A | N10: Terrains | O10: 3.9774084e+08
A11: 2 | B11: 21 | C11: 212 | D11: 21200000 | E11: Agencement amenagement terrain | F11: 1.6707008e+08 | G11: 1.5982108e+08 | H11: 1.5982108e+08 | I11: 1.5982108e+08 | K11: 21200000 | L11: 21200000 | M11: =+VLOOKUP(D11,AGRIVET!$B$3:$G$348,5,FALSE()) -> 4654500 | N11: Agenc. et aménag. de terrains | O11: 1.5982108e+08
A12: 2 | B12: 21 | C12: 213 | D12: 21300000 | E12: Batiments - Constructions | F12: 2.4663595e+09 | G12: 2.4663595e+09 | H12: 2.4663595e+09 | I12: 2.4663595e+09 | K12: 21300000 | L12: 21300000 | M12: =+VLOOKUP(D12,AGRIVET!$B$3:$G$348,5,FALSE()) -> 53086164 | N12: Batiments - Constructions | O12: 2.4663595e+09
A13: 2 | B13: 21 | C13: 215 | D13: 21500000 | E13: Agencement aménagement | F13: 4.0890942e+08 | G13: 4.0715942e+08 | H13: 3.8263695e+08 | I13: 3.8263695e+08 | K13: 21500000 | L13: 21500000 | M13: =+VLOOKUP(D13,AGRIVET!$B$3:$G$348,5,FALSE()) -> 6.7257296e+08 | N13: Agencement aménagement install | O13: 4.0715942e+08
A14: 2 | B14: 21 | C14: 215 | D14: 21520000 | E14: Installations | F14: 0 | G14: 41336399 | H14: 41336399 | I14: 41336399 | K14: 21540000 | L14: 21540000 | M14: =+VLOOKUP(D14,AGRIVET!$B$3:$G$348,5,FALSE()) -> 54908530 | N14: Matériel industriel | O14: 5.9350947e+09
... A54: 4 | B54: 44 | C54: 441 | D54: 44100000 | E54: Etat: IRSA à payer | F54: -19337145 | G54: -42455705 | H54: -34221211 | I54: -34221211 | K54: 41300000 | L54: 41310000 | M54: =+VLOOKUP(D54,AGRIVET!$B$3:$G$348,5,FALSE()) -> -37319657 | N54: Clients - Traite reçu | O54: 1.5822673e+08
A55: 4 | B55: 44 | C55: 442 | D55: 44200000 | E55: Etat : IFPB | F55: -9569400 | G55: 0 | H55: -9569400 | I55: -9569400 | M55: =+VLOOKUP(D55,AGRIVET!$B$3:$G$348,5,FALSE()) -> #N/A
A56: 4 | B56: 44 | C56: 443 | D56: 44300000 | E56: Etat : acomptes IR | F56: 113250 | G56: 77134944 | H56: 85089615 | I56: 85089615 | K56: 41600000 | L56: 41600000 | M56: =+VLOOKUP(D56,AGRIVET!$B$3:$G$348,5,FALSE()) -> 1.3739105e+09 | N56: Clients douteux | O56: 5.5257875e+08
A57: 4 | B57: 44 | C57: 444 | D57: 44400000 | E57: Etat à payer | F57: 7425667.3 | G57: -2.6896705e+08 | H57: -62694376 | I57: -62694376 | K57: 41910000 | L57: 41910000 | M57: =+VLOOKUP(D57,AGRIVET!$B$3:$G$348,5,FALSE()) -> 0 | N57: Clients créditeurs : acomptes | O57: -1.0389338e+08
A58: 4 | B58: 44 | C58: 444 | D58: 44410000 | E58: Crédit IR | F58: -2825.2103 | G58: 1.0653845e+08 | H58: 84143209 | I58: 84143209 | K58: 41980000 | L58: 41980000 | M58: =+VLOOKUP(D58,AGRIVET!$B$3:$G$348,5,FALSE()) -> -1.8104082e+09 | N58: Avoir à établir | O58: -16061924
A59: 4 | B59: 44 | C59: 444 | D59: 44411000 | E59: IR Intermittent Locaux | F59: 0 | G59: 195563.04 | H59: -8972079.9 | I59: -8972079.9 | K59: 42110000 | L59: 42110000 | M59: =+VLOOKUP(D59,AGRIVET!$B$3:$G$348,5,FALSE()) -> #N/A | N59: Rémunérations dues personnel | O59: 223804.99
A60: 4 | B60: 44 | C60: 444 | D60: 44412000 | E60: IR INTERMITENT ETRANGER | F60: 0 | G60: 5215228.3 | H60: 110259.78 | I60: 110259.78 | K60: 42120000 | L60: 42110000 | M60: =+VLOOKUP(D60,AGRIVET!$B$3:$G$348,5,FALSE()) -> #N/A | N60: Salaires Temporaires | O60: 809000
A61: 4 | B61: 44 | C61: 445 | D61: 44540000 | E61: TVA à décaisser | F61: -0.079799995 | G61: 7.6293945e-08 | H61: -1.5863031e+08 | I61: -1.5863031e+08 | K61: 42510000 | L61: 42510000 | M61: =+VLOOKUP(D61,AGRIVET!$B$3:$G$348,5,FALSE()) -> -66059083 | N61: Avances quinzaines | O61: 1070000
A62: 4 | B62: 44 | C62: 445 | D62: 44550000 | E62: Credit de taxe | F62: 3.5260939e+08 | G62: 3.6878179e+08 | H62: 0 | I62: 0 | K62: 42520000 | L62: 42520000 | M62: =+VLOOKUP(D62,AGRIVET!$B$3:$G$348,5,FALSE()) -> 0 | N62: Avances spéciales | O62: 31752243
A63: 4 | B63: 44 | C63: 445 | D63: 44561000 | E63: TVA déductibles | F63: 0 | G63: 42039174 | H63: 95132907 | I63: 95132907 | K63: 42530000 | L63: 42520000 | M63: =+VLOOKUP(D63,AGRIVET!$B$3:$G$348,5,FALSE()) -> -6722144 | N63: Avances prêt scolaire | O63: 259999.98
A64: 4 | B64: 44 | C64: 445 | D64: 44571000 | E64: TVA collectée | F64: 60639 | G64: -6.4797105e+08 | H64: -7.3169806e+08 | I64: -7.3169806e+08 | K64: 42800000 | L64: 42800000 | M64: =+VLOOKUP(D64,AGRIVET!$B$3:$G$348,5,FALSE()) -> -11341731 | N64: Congés payés provision | O64: -1.7150059e+08
A65: 4 | B65: 44 | C65: 445 | D65: 44581000 | E65: TVA sur factures non parvenues | F65: 0 | G65: 3.7512559e+08 | H65: 4504385.2 | I65: 4504385.2 | K65: 43100000 | L65: 43100000 | M65: =+VLOOKUP(D65,AGRIVET!$B$3:$G$348,5,FALSE()) -> #N/A | N65: CNaPS | O65: -87785721
A66: 4 | B66: 45 | C66: 451 | D66: 45120000 | E66: AGRIVAL | F66: 0 | G66: 2500000 | H66: 2500000 | I66: 2500000 | K66: 43110000 | L66: 43110000 | M66: =+VLOOKUP(D66,AGRIVET!$B$3:$G$348,5,FALSE()) -> #N/A | N66: Allocation familiale CNAPS | O66: -2641600
A67: 4 | B67: 45 | C67: 455 | D67: 45500000 | E67: Associés compte courant | F67: 2500000 | G67: -4.6420028e+08 | H67: -4.5895406e+08 | I67: -4.5895406e+08 | K67: 43200000 | L67: 43200000 | M67: =+VLOOKUP(D67,AGRIVET!$B$3:$G$348,5,FALSE()) -> 0 | N67: OSTIE | O67: -37622452
... A73: 4 | B73: 46 | C73: 466 | D73: 46613000 | E73: DITE SARLU | F73: 0 | G73: 2031605 | H73: 2031605 | I73: 2031605 | K73: 44410000 | L73: 44411000 | M73: =+VLOOKUP(D73,AGRIVET!$B$3:$G$348,5,FALSE()) -> #N/A | N73: Etat : IR Intermittent | O73: 195563.04
A74: 4 | B74: 46 | C74: 466 | D74: 46614000 | E74: DANIL ISMAEL | F74: 0 | H74: 34521400 | I74: 34521400 | K74: 44420000 | L74: 44412000 | M74: =+VLOOKUP(D74,AGRIVET!$B$3:$G$348,5,FALSE()) -> #N/A | N74: IR Intermittent Etranger | O74: 5215228.3
K75: 44430000 | L75: 44400000 | M75: =+VLOOKUP(D75,AGRIVET!$B$3:$G$348,5,FALSE()) -> #N/A | N75: IR à payer | O75: -2.6896705e+08
A76: 4 | B76: 46 | C76: 466 | D76: 46615000 | E76: EUROPAINTS REFACTURATION | F76: 0 | G76: 2345200 | H76: 32278618 | I76: 32278618 | K76: 44540000 | L76: 44540000 | M76: =+VLOOKUP(D76,AGRIVET!$B$3:$G$348,5,FALSE()) -> #N/A | N76: TVA à décaisser | O76: 7.6293945e-08
A77: 4 | B77: 46 | C77: 466 | D77: 46616000 | E77: FERRIS | F77: 0 | G77: 30667378 | H77: 25197269 | I77: 25197269 | K77: 44550000 | L77: 44550000 | M77: =+VLOOKUP(D77,AGRIVET!$B$3:$G$348,5,FALSE()) -> #N/A | N77: Credit de taxe | O77: 3.6878179e+08
A78: 4 | B78: 46 | C78: 466 | D78: 46617000 | E78: FIRST ENERGY REFACTURATION | F78: 0 | G78: 1.8733868e+08 | H78: 2.4382416e+08 | I78: 2.4382416e+08 | K78: 44560000 | L78: 44561000 | M78: =+VLOOKUP(D78,AGRIVET!$B$3:$G$348,5,FALSE()) -> #N/A | N78: TVA déductibles | O78: -334000
A79: 4 | B79: 46 | C79: 466 | D79: 46618000 | E79: FIRST INVESTISSEMENT | F79: 0 | G79: 1244000 | H79: 1244000 | I79: 1244000 | K79: 44562000 | L79: 44561000 | M79: =+VLOOKUP(D79,AGRIVET!$B$3:$G$348,5,FALSE()) -> #N/A | N79: TVA sur Immobilisation | O79: 1138993.5
A80: 4 | B80: 46 | C80: 466 | D80: 46619000 | E80: FLY TECHNOLOGIE REFACTURATION | F80: 0 | G80: 1.0525247e+08 | H80: 38461774 | I80: 38461774 | K80: 44563000 | L80: 44561000 | M80: =+VLOOKUP(D80,AGRIVET!$B$3:$G$348,5,FALSE()) -> #N/A | N80: TVA Intermittente Déductible | O80: 3039959
A81: 4 | B81: 46 | C81: 466 | D81: 46620000 | E81: AGRIFEED REFACTURATION | F81: 0 | G81: 1220031.3 | H81: 487556 | I81: 487556 | K81: 44564000 | L81: 44561000 | M81: =+VLOOKUP(D81,AGRIVET!$B$3:$G$348,5,FALSE()) -> 0 | N81: TVA pour les Services | O81: 38500346
A82: 4 | B82: 46 | C82: 466 | D82: 46621000 | E82: IDF REFACTURATION | F82: 0 | G82: 96224546 | H82: 1.3425194e+08 | I82: 1.3425194e+08 | K82: 44565000 | L82: 44561000 | M82: =+VLOOKUP(D82,AGRIVET!$B$3:$G$348,5,FALSE()) -> #N/A | N82: TVA pour les Biens | O82: -306124.47
A83: 4 | B83: 46 | C83: 466 | D83: 46622000 | E83: ID MOTORS REFACTURATION | F83: 0 | G83: 2.6239274e+08 | H83: 2.0363628e+08 | I83: 2.0363628e+08 | K83: 44570000 | L83: 44571000 | M83: =+VLOOKUP(D83,AGRIVET!$B$3:$G$348,5,FALSE()) -> #N/A | N83: TVA collectées | O83: -3.5407218e+08
A84: 4 | B84: 46 | C84: 466 | D84: 46623000 | E84: ID RENTAL REFACTURATION | F84: 0 | G84: 20625566 | H84: 3903421.9 | I84: 3903421.9 | K84: 44571000 | L84: 44571000 | M84: =+VLOOKUP(D84,AGRIVET!$B$3:$G$348,5,FALSE()) -> #N/A | N84: TVA Intermitente étranger | O84: -3039959
A85: 4 | B85: 46 | C85: 466 | D85: 46624000 | E85: MABEL REFACTURATION | F85: 0 | G85: 84800 | H85: 5362900 | I85: 5362900 | K85: 44572000 | L85: 44571000 | M85: =+VLOOKUP(D85,AGRIVET!$B$3:$G$348,5,FALSE()) -> #N/A | N85: TVA relatifs aux op locales | O85: -3.0962258e+08
A86: 4 | B86: 46 | C86: 466 | D86: 46625000 | E86: MCM REFACTURATION | F86: 0 | G86: 46486823 | H86: 924500 | I86: 924500 | K86: 44574000 | L86: 44571000 | M86: =+VLOOKUP(D86,AGRIVET!$B$3:$G$348,5,FALSE()) -> #N/A | N86: TVA sur cession d'immo | O86: 18763673
A87: 4 | B87: 46 | C87: 466 | D87: 46626000 | E87: MPL REFACTURATION | F87: 0 | G87: 38766248 | H87: 16064094 | I87: 16064094 | K87: 44583000 | L87: 44581000 | M87: =+VLOOKUP(D87,AGRIVET!$B$3:$G$348,5,FALSE()) -> #N/A | N87: TVA sur factures non parvenues | O87: 15960852
... A108: 4 | B108: 46 | C108: 467 | D108: 46700001 | E108: Créances intra groupes/ Prêt | F108: 0 | G108: 200000000 | H108: -2.0901968e+08 | I108: -2.0901968e+08 | K108: 46610000 | L108: 46621000 | M108: =+VLOOKUP(D108,AGRIVET!$B$3:$G$348,5,FALSE()) -> #N/A | N108: IDF | O108: 96224546
A109: 4 | B109: 46 | C109: 467 | D109: 46710000 | E109: AGRIMA | F109: 265000000 | H109: 2340821.9 | I109: 2340821.9 | K109: 46610000 | L109: 46624000 | M109: =+VLOOKUP(D109,AGRIVET!$B$3:$G$348,5,FALSE()) -> #N/A | N109: MABEL | O109: 84800
A110: 4 | B110: 46 | C110: 467 | D110: 46712000 | E110: BOVIMA | F110: 0 | G110: 1240000000 | H110: 1240000000 | I110: 1240000000 | K110: 46610000 | L110: 46627000 | M110: =+VLOOKUP(D110,AGRIVET!$B$3:$G$348,5,FALSE()) -> #N/A | N110: NMP | O110: 114516000
A111: 4 | B111: 46 | C111: 467 | D111: 46717000 | E111: TARTINE | F111: 0 | G111: 9802303.5 | H111: 9802303.5 | I111: 9802303.5 | K111: 46610000 | L111: 46628000 | M111: =+VLOOKUP(D111,AGRIVET!$B$3:$G$348,5,FALSE()) -> #N/A | N111: NOAH | O111: 3490600
A112: 4 | B112: 46 | C112: 467 | D112: 46718000 | E112: NMP | F112: 0 | G112: 825000000 | H112: 180000 | I112: 180000 | K112: 46610000 | L112: 46629000 | M112: =+VLOOKUP(D112,AGRIVET!$B$3:$G$348,5,FALSE()) -> #N/A | N112: RYA | O112: 7971037.2
A113: 4 | B113: 46 | C113: 467 | D113: 46721000 | E113: ID MOTORS | F113: 0 | G113: 350000000 | H113: 300000000 | I113: 300000000 | K113: 46610000 | L113: 46632000 | M113: =+VLOOKUP(D113,AGRIVET!$B$3:$G$348,5,FALSE()) -> #N/A | N113: SIM | O113: 10644774
A114: 4 | B114: 46 | C114: 467 | D114: 46732000 | E114: AMCHO | F114: 0 | H114: 400000000 | I114: 400000000 | K114: 46610000 | L114: 46633000 | M114: =+VLOOKUP(D114,AGRIVET!$B$3:$G$348,5,FALSE()) -> #N/A | N114: LMOI | O114: 19569276
A115: 4 | B115: 46 | C115: 467 | D115: 46733000 | E115: FLY TECHNOLOGIE | F115: 0 | G115: 1200000000 | H115: 0 | I115: 0 | K115: 46610000 | L115: 46660000 | M115: =+VLOOKUP(D115,AGRIVET!$B$3:$G$348,5,FALSE()) -> #N/A | N115: AGRIVETAM | O115: 5460093.9
A116: 4 | B116: 46 | C116: 467 | D116: 46734000 | E116: AGRIVOLA | F116: 0 | G116: 10070399 | H116: 10070399 | I116: 10070399 | K116: 46610000 | L116: 46631000 | M116: =+VLOOKUP(D116,AGRIVET!$B$3:$G$348,5,FALSE()) -> #N/A | N116: RCM | O116: 4579886
A117: 4 | B117: 46 | C117: 467 | D117: 46736000 | E117: NOAH | F117: 0 | G117: 3750000 | H117: 0 | I117: 0 | K117: 46610000 | L117: 46639000 | M117: =+VLOOKUP(D117,AGRIVET!$B$3:$G$348,5,FALSE()) -> #N/A | N117: United Malagasy | O117: 358849.76
A118: 4 | B118: 46 | C118: 467 | D118: 46711000 | E118: AGRIVET PRET | F118: 0 | G118: -1.6126137e+08 | H118: -1.4305469e+08 | I118: -1.4305469e+08 | K118: 46610000 | L118: 46625000 | M118: =+VLOOKUP(D118,AGRIVET!$B$3:$G$348,5,FALSE()) -> #N/A | N118: MCM | O118: 46486823
A119: 4 | B119: 46 | C119: 467 | D119: 46780000 | E119: LMOI PRET | F119: 0 | G119: 950307 | H119: 0 | I119: 0 | K119: 46610000 | L119: 46642000 | M119: =+VLOOKUP(D119,AGRIVET!$B$3:$G$348,5,FALSE()) -> #N/A | N119: AGRIMA | O119: 1600
A120: 4 | B120: 47 | C120: 471 | D120: 47100000 | E120: Compte d'attente | F120: -8428097 | G120: -1167523.3 | H120: 538310 | I120: 538310 | K120: 46610000 | L120: 46640000 | M120: =+VLOOKUP(D120,AGRIVET!$B$3:$G$348,5,FALSE()) -> 0 | N120: AGRIMOTORS | O120: 49388619
A121: 4 | B121: 48 | C121: 486 | D121: 48600000 | E121: Charges constatées d'avance | F121: 9072589.7 | G121: 15286778 | H121: 150000 | I121: 150000 | K121: 46610000 | L121: 46623000 | M121: =+VLOOKUP(D121,AGRIVET!$B$3:$G$348,5,FALSE()) -> 1.3259269e+08 | N121: ID RENTAL | O121: 20625566
A122: 4 | B122: 48 | C122: 487 | D122: 48700000 | E122: PRODUITS CONSTATES D'AVANCE | F122: -2.1389265e+09 | G122: -2.1389265e+09 | H122: 0 | I122: 0 | K122: 46610000 | L122: 46619000 | M122: =+VLOOKUP(D122,AGRIVET!$B$3:$G$348,5,FALSE()) -> #N/A | N122: FLY TECHNOLOGIES | O122: 1.0525247e+08
A123: 4 | B123: 49 | C123: 491 | D123: 49100000 | E123: Pertes de valeur/cptes clients et autres dbiteurs | F123: -4.1571918e+08 | G123: -5.5257875e+08 | H123: -5.5819784e+08 | I123: -5.5819784e+08 | K123: 46610000 | L123: 46626000 | M123: =+VLOOKUP(D123,AGRIVET!$B$3:$G$348,5,FALSE()) -> -1.0068832e+09 | N123: MPL (Madagascar Poids Lourds) | O123: 38766248
A124: 5 | B124: 51 | C124: 511 | D124: 51110000 | E124: Chèques et traites à encaisser | F124: 3.112749e+08 | G124: 4.9010065e+08 | H124: 3.5654833e+08 | I124: 3.5654833e+08 | K124: 46610000 | L124: 46616000 | M124: =+VLOOKUP(D124,AGRIVET!$B$3:$G$348,5,FALSE()) -> 2.922528e+09 | N124: FERRIS | O124: 30667378
A125: 5 | B125: 51 | C125: 512 | D125: 51211000 | E125: BMOI Ariary | F125: -5.3982283e+08 | G125: -1.2162138e+08 | H125: -2.224502e+08 | I125: -2.224502e+08 | K125: 46610000 | L125: 46618000 | M125: =+VLOOKUP(D125,AGRIVET!$B$3:$G$348,5,FALSE()) -> -8.7477337e+08 | N125: FIRST INVESTISSEMENT | O125: 1244000
A126: 5 | B126: 51 | C126: 512 | D126: 51212000 | E126: Banque BMOI Euro | F126: 53730781 | G126: 35011975 | H126: 47601012 | I126: 47601012 | K126: 46610000 | L126: 46638000 | M126: =+VLOOKUP(D126,AGRIVET!$B$3:$G$348,5,FALSE()) -> 19277276 | N126: TANTALUM RARE | O126: -10587000
... A195: 7 | B195: 78 | C195: 785 | D195: 78500000 | E195: Reprise sur provisions | F195: 0 | G195: -26143488 | H195: -2478807.8 | I195: -2478807.8 | K195: 60610000 | L195: 60600000 | M195: =+VLOOKUP(D195,AGRIVET!$B$3:$G$348,5,FALSE()) -> #N/A | N195: Petit outillage usine & mainte | O195: 19988960
D196: 12000000 | E196: Résultat - bénéfice | F196: -1.3058798e+09 | K196: 60680000 | L196: 60600000 | M196: =+VLOOKUP(D196,AGRIVET!$B$3:$G$348,5,FALSE()) -> 0 | N196: Achats matières et fournitures | O196: 485550.03
D197: 16412000 | E197: Emprunt BNI | F197: -4.5821637e+08 | K197: 60701000 | L197: 60700000 | M197: =+VLOOKUP(D197,AGRIVET!$B$3:$G$348,5,FALSE()) -> #N/A | N197: Achats locaux de marchandises | O197: 1.4487693e+08
D198: 16413000 | E198: Emprunt BFV | F198: -4.5094354e+08 | K198: 60702000 | L198: 60700000 | M198: =+VLOOKUP(D198,AGRIVET!$B$3:$G$348,5,FALSE()) -> #N/A | N198: Achats import de m/ses | O198: 2.4954938e+09
D199: 16415000 | E199: Emprunt BOA | F199: -1457000000 | K199: 60801000 | L199: 60800000 | M199: =+VLOOKUP(D199,AGRIVET!$B$3:$G$348,5,FALSE()) -> #N/A | N199: Fret | O199: 75265505
D200: 21570000 | E200: Installation système d'alarme | F200: 32515873 | K200: 60802000 | L200: 60800000 | M200: =+VLOOKUP(D200,AGRIVET!$B$3:$G$348,5,FALSE()) -> #N/A | N200: Assurance | O200: 12304892
D201: 21580000 | E201: AAI CONSTRUCTION | F201: 10573640 | K201: 60803000 | L201: 60800000 | M201: =+VLOOKUP(D201,AGRIVET!$B$3:$G$348,5,FALSE()) -> #N/A | N201: Honoraires transitaire | O201: 7589174.7
D202: 21590000 | E202: INSTALLATION BOUCHE INCENDIE | F202: 19978607 | K202: 60804000 | L202: 60800000 | M202: =+VLOOKUP(D202,AGRIVET!$B$3:$G$348,5,FALSE()) -> #N/A | N202: Divers frais de transit | O202: 1.820798e+08
D203: 21810000 | E203: Matériels & outillages | F203: 6.5898946e+08 | K203: 60805000 | L203: 60800000 | M203: =+VLOOKUP(D203,AGRIVET!$B$3:$G$348,5,FALSE()) -> 1.0167907e+09 | N203: Surestaries | O203: 8106875.9
D204: 21832000 | E204: Autres Mobiliers | F204: 79128089 | K204: 60807000 | L204: 60800000 | M204: =+VLOOKUP(D204,AGRIVET!$B$3:$G$348,5,FALSE()) -> #N/A | N204: Transport sur Achat | O204: 1.604458e+08
D205: 21860000 | E205: Matériel informatiques | F205: 3.7940082e+08 | K205: 60808000 | L205: 60800000 | M205: =+VLOOKUP(D205,AGRIVET!$B$3:$G$348,5,FALSE()) -> 2810305 | N205: Expertise TC (CEMM) | O205: 2175421.7
D206: 21880000 | E206: Materiel&mobilier de logement | F206: 62979925 | K206: 60809000 | L206: 60800000 | M206: =+VLOOKUP(D206,AGRIVET!$B$3:$G$348,5,FALSE()) -> #N/A | N206: Droits de douane | O206: 3.4979303e+08
D207: 23000000 | E207: Investissements | F207: 1.3140599e+09 | K207: 60809100 | L207: 60800000 | M207: =+VLOOKUP(D207,AGRIVET!$B$3:$G$348,5,FALSE()) -> 77514431 | N207: Frais divers Douane | O207: 52048143
... D318: 62704000 | E318: Frais tenu de compte | F318: 1323689.6 | K318: 78500000 | L318: 78500000 | M318: =+VLOOKUP(D318,AGRIVET!$B$3:$G$348,5,FALSE()) -> 18079224 | N318: Reprise d'exploitation - AC | O318: -26143488
D319: 62705000 | E319: Commissions de domiciliation | F319: 5558745.9
D320: 62706000 | E320: CI transfert change | F320: 31989057
D321: 62707000 | E321: Commission de mouvement | F321: 7546112.5
D322: 62708000 | E322: Commissions abonnement Net | F322: 712166.63
D323: 62709000 | E323: Commissions virement | F323: 2232654
D324: 62710000 | E324: Commission impayés | F324: 90280
D325: 62713000 | E325: Frais chèque de banque | F325: 28333.333
D326: 62714000 | E326: Comm sur incident de fonction | F326: 124416
D327: 63507000 | E327: TVA non récupérable | F327: 7077868.7
D328: 63514000 | E328: Taxe sur véhicules de sociétés | F328: 35000
D329: 63540000 | E329: Dts d'enregistremt & de timbre | F329: 2000
D330: 64102000 | E330: Indemnite diverses | F330: 1.2114326e+08
... D357: 78150000 | E357: Reprises prov. risques&charges | F357: -2.00324e+08

Sheet AGRIKOBA
A2: Num.compte | C2: Libellés | D2: 2021 | E2: 2020 | F2: 2019 | G2: Gestion
A3: 1010000 | B3: 10100000 | C3: CAPITAL | D3: -1200000000 | E3: -100000000 | F3: -100000000 | G3: 10100000 | H3: CAPITAL
A4: 1190000 | B4: 11900000 | C4: RAN DEBITEUR | D4: 1.6552003e+09 | E4: 1.6552003e+09 | F4: 5.7469412e+08 | G4: 11900000 | H4: RAN DEBITEUR
A5: 1200000 | B5: 12000000 | C5: RESULTAT NET BENEFICE | D5: 0 | F5: 0 | G5: 12000000 | H5: RESULTAT NET BENEFICE
B6: 12900000 | C6: RESULTAT NET PERTE | D6: 1.4736448e+09 | G6: 12900000 | H6: RESULTAT NET PERTE
A7: 1630000 | B7: 16300000 | C7: EMPRUNT BGFI | D7: 0 | F7: -2.6502224e+09 | G7: 16300000 | H7: EMPRUNT BGFI
A8: 1631000 | B8: 16310000 | C8: Emprunts BNI 746 MGA | D8: 0 | F8: -4.5505451e+08 | G8: 16310000 | H8: Emprunts BNI 746 MGA
A9: 1640000 | B9: 16400000 | C9: EMPRUNTS BNI | D9: -1.5957046e+09 | E9: -2.3202105e+09 | F9: 0 | G9: 16400000 | H9: EMPRUNTS BNI
A10: 1641000 | B10: 16410000 | C10: Emprunts BNI 746 MGA | D10: -3.2193458e+08 | E10: -4.1338519e+08 | F10: 0 | G10: 16410000 | H10: Emprunts BNI 746 MGA
A11: 2110000 | B11: 21100000 | C11: TERRAINS | D11: 55348271 | E11: 66666667 | F11: 0 | G11: 21100000 | H11: TERRAINS
A12: 2120000 | B12: 21200000 | C12: AGENCEMENT AMENAGEMENT TERRAIN | D12: 144235358 | E12: 110417775 | F12: 90218000 | G12: 21200000 | H12: AGENCEMENT AMENAGEMENT TERRAIN
A13: 2130000 | B13: 21300000 | C13: CONSTRUCTIONS | D13: 2.7686945e+09 | E13: 2.7686945e+09 | F13: 1.2789215e+09 | G13: 21300000 | H13: CONSTRUCTIONS
A14: 2150000 | B14: 21500000 | C14: AGENCEMENT AMENAGEMENT INSTAL | D14: 1.2591835e+09 | E14: 1.2591835e+09 | F14: 1.2647545e+09 | G14: 21500000 | H14: AGENCEMENT AMENAGEMENT INSTAL
A15: 2155000 | B15: 21550000 | C15: MACHINES INDUSTRIELS | D15: 4.5303871e+09 | E15: 4.5303871e+09 | F15: 4.3400617e+09 | G15: 21550000 | H15: MACHINES INDUSTRIELS
A16: 2181000 | B16: 21810000 | C16: MATÉRIELS & OUTILLAGES | D16: 1.5843821e+08 | E16: 1.556157e+08 | F16: 1.5516622e+08 | G16: 21810000 | H16: MATÉRIELS & OUTILLAGES
A17: 2182000 | B17: 21820000 | C17: MMB | D17: 19117907 | E17: 14310573 | F17: 8909239.9 | G17: 21820000 | H17: MMB
B18: 21830000 | C18: MATERIEL DE TRANSPORT | D18: 9141666.7 | G18: 21830000 | H18: MATERIEL DE TRANSPORT
A19: 2184000 | B19: 21840000 | C19: MATÉRIEL INFORMATIQUES | D19: 41118647 | E19: 40168647 | F19: 35759247 | G19: 21840000 | H19: MATÉRIEL INFORMATIQUES
B20: 21850000 | C20: MATERIEL &MOBILIER DE LOGEMENT | D20: 4304797.1 | G20: 21850000 | H20: MATERIEL &MOBILIER DE LOGEMENT
A21: 2300000 | B21: 23000000 | C21: IMMO EN COURS | D21: 70057746 | E21: 0 | F21: 1.6314104e+09 | G21: 23000000 | H21: IMMO EN COURS
A22: 2750000 | B22: 27500000 | C22: DEPOT & CAUTIONNEMENTS VERSES | D22: 0 | E22: 16380000 | F22: 1000000 | G22: 27500000 | H22: DEPOT & CAUTIONNEMENTS VERSES
A23: 2812000 | B23: 28120000 | C23: AMORT AGENC AMENAG TERRAIN | D23: -13385195 | E23: -6807507 | F23: -2751444.7 | G23: 28120000 | H23: AMORT AGENC AMENAG TERRAIN
A24: 2813000 | B24: 28130000 | C24: AMTS CONSTRUCTIONS | D24: -2.885326e+08 | E24: -1.5009787e+08 | F24: -67115811 | G24: 28130000 | H24: AMTS CONSTRUCTIONS
A25: 2815000 | B25: 28150000 | C25: AMTS AGEN.AMEN.INSTAL. | D25: -3.8243224e+08 | E25: -2.5651389e+08 | F25: -1.3059555e+08 | G25: 28150000 | H25: AMTS AGEN.AMEN.INSTAL.
A26: 2815500 | B26: 28155000 | C26: AMORT MACHINES INDUSTRIELS | D26: -1.6770622e+09 | E26: -1.2240235e+09 | F26: -7.7860667e+08 | G26: 28155000 | H26: AMORT MACHINES INDUSTRIELS
A27: 2818100 | B27: 28181000 | C27: AMTS MATERIELS & OUTILLAGE | D27: -49734127 | E27: -33955047 | F27: -18396598 | G27: 28181000 | H27: AMTS MATERIELS & OUTILLAGE
A28: 2818200 | B28: 28182000 | C28: AMTS MMB | D28: -3753112.8 | E28: -2185819.5 | F28: -1098080.7 | G28: 28182000 | H28: AMTS MMB
B29: 28183000 | C29: AMTS MATERIEL DE TRANSPORT | D29: -1352204.9 | G29: 28183000 | H29: AMTS MATERIEL DE TRANSPORT
A30: 2818400 | B30: 28184000 | C30: AMTS MATERIEL INFORMATIQUE | D30: -28962544 | E30: -18859028 | F30: -9491036.6 | G30: 28184000 | H30: AMTS MATERIEL INFORMATIQUE
A31: 3100000 | B31: 31000000 | C31: STOCKS DE MAT.1ERES&FOURNITURE | D31: 3.7838989e+08 | E31: 1.5995822e+09 | F31: =136327860+17157114 -> 153484974 | G31: 31000000 | H31: STOCKS DE MAT.1ERES&FOURNITURE
A32: 3110000 | B32: 31100000 | C32: STOCKS DES EMBALLAGES | D32: 24830517 | E32: 24830517 | G32: 31100000 | H32: STOCKS DES EMBALLAGES
A33: 3550000 | B33: 35500000 | C33: STOCKS PRODUITS FINIS | D33: 1.0349128e+09 | E33: 79263118 | F33: 402920473 | G33: 35500000 | H33: STOCKS PRODUITS FINIS
A34: 4011000 | B34: 40110000 | C34: FOURNISSEURS LOCAUX | D34: -1.8351709e+09 | E34: -3.6914243e+09 | F34: -2.6321989e+09 | G34: 40110000 | H34: FOURNISSEURS LOCAUX
A35: 4012000 | B35: 40120000 | C35: FOURNISSEURS ETRANGERS | D35: 3021304.2 | E35: 0 | F35: -714572190 | G35: 40120000 | H35: FOURNISSEURS ETRANGERS
A36: 4034000 | B36: 40340000 | C36: F/SSEURS EFFETS À PAYER BNI | D36: -1.0174928e+08 | E36: -63121776 | F36: -23326387 | G36: 40340000 | H36: F/SSEURS EFFETS À PAYER BNI
A37: 4040000 | B37: 40400000 | C37: F/SSEURS D'IMMOBILISATIONS | D37: 0 | E37: 0 | F37: -6.656958e+08 | G37: 40400000 | H37: F/SSEURS D'IMMOBILISATIONS
A38: 4081000 | B38: 40810000 | C38: F/SSEURS LOC FACT À RECEVOIR | D38: -1.3244481e+08 | E38: -64753104 | F38: -1.0857839e+08 | G38: 40810000 | H38: F/SSEURS LOC FACT À RECEVOIR
B39: 40820000 | C39: F/SSEURS ETR FACT À RECEVOIR | D39: 0 | G39: 40820000 | H39: F/SSEURS ETR FACT À RECEVOIR
A40: 4091000 | B40: 40910000 | C40: FRNS LOCAUX DEBITEURS:AVANCE | D40: 134109583 | E40: 83376330 | F40: 43790926 | G40: 40910000 | H40: FRNS LOCAUX DEBITEURS:AVANCE
A41: 4092000 | B41: 40920000 | C41: FRNS ETRANGER DEBITEUR:AVANCE | D41: 4593682.3 | E41: 39380553 | F41: 0 | G41: 40920000 | H41: FRNS ETRANGER DEBITEUR:AVANCE
A42: 4111000 | B42: 41110000 | C42: CLIENTS LOCAUX | D42: 4.8195615e+08 | E42: 4.8330954e+08 | F42: 2.0600873e+09 | G42: 41110000 | H42: CLIENTS LOCAUX
A43: 4112000 | B43: 41120000 | C43: CLIENTS ETRANGERS | D43: 0 | E43: 216000 | F43: 0 | G43: 41120000 | H43: CLIENTS ETRANGERS
A44: 4130000 | B44: 41300000 | C44: CLIENTS EFFETS À RECEVOIR | D44: 0 | E44: 0 | F44: 0 | G44: 41300000 | H44: CLIENTS EFFETS À RECEVOIR
A45: 4190000 | B45: 41900000 | C45: Clients: avances et acomptes | D45: -71400 | E45: -29280000 | F45: 0 | G45: 41900000 | H45: Clients: avances et acomptes
A46: 4198000 | B46: 41980000 | C46: Avoir à établir | D46: 0 | E46: -216000 | F46: 0 | G46: 41980000 | H46: Avoir à établir
A47: 4210000 | B47: 42100000 | C47: RÉMUNÉRATION DUES AU PERSONNEL | D47: -27272518 | E47: 0 | F47: 258000 | G47: 42100000 | H47: RÉMUNÉRATION DUES AU PERSONNEL
A48: 4211000 | B48: 42110000 | C48: Salaires Temporaires | D48: 27884444 | E48: 0 | F48: 1933800 | G48: 42110000 | H48: Salaires Temporaires
A49: 4250000 | B49: 42500000 | C49: AVANCES & ACOMPTESAU PERSONNEL | D49: 0 | E49: 0 | F49: 0 | G49: 42500000 | H49: AVANCES & ACOMPTESAU PERSONNEL
A50: 4251000 | B50: 42510000 | C50: Avances quinzaines | D50: 0 | F50: 0 | G50: 42510000 | H50: Avances quinzaines
A51: 4252000 | B51: 42520000 | C51: Avances speciales | D51: 3338000 | E51: 7055000 | F51: 0 | G51: 42520000 | H51: Avances speciales
A52: 4253000 | B52: 42530000 | C52: Avances prêt scolaire | D52: 0 | F52: 0 | G52: 42530000 | H52: Avances prêt scolaire
B53: 42540000 | C53: Tsinjo Fameno | D53: 1388722.3 | G53: 42540000 | H53: Tsinjo Fameno
A54: 4280000 | B54: 42800000 | C54: PERSONNEL CONGES PAYES | D54: -29350196 | E54: -16283331 | F54: -12339249 | G54: 42800000 | H54: PERSONNEL CONGES PAYES
A55: 4310000 | B55: 43100000 | C55: CNAPS | D55: -11747312 | E55: -11830651 | F55: -12388105 | G55: 43100000 | H55: CNAPS
A56: 4311000 | B56: 43110000 | C56: CNAPS ALLOCAT° FAMILIALES | D56: -84000 | E56: -168000 | F56: 42000 | G56: 43110000 | H56: CNAPS ALLOCAT° FAMILIALES
A57: 4320000 | B57: 43200000 | C57: OSTIE | D57: -5034562.1 | E57: -5070278.9 | F57: -5309188 | G57: 43200000 | H57: OSTIE
A58: 4330000 | B58: 43300000 | C58: FMFP | D58: -839093.68 | E58: -845046.48 | F58: -884864.66 | G58: 43300000 | H58: FMFP
B59: 43400000 | C59: ASCOMA | D59: 0 | G59: 43400000 | H59: ASCOMA
A60: 4386000 | B60: 43860000 | C60: ORGANISME-AUTRE CHARGE A PAYER | D60: -6607873.3 | E60: -4777943.3 | F60: -3727958 | G60: 43860000 | H60: ORGANISME-AUTRE CHARGE A PAYER
A61: 4400000 | B61: 44000000 | C61: ETAT A PAYER | D61: -21035903 | E61: 0 | F61: 0 | G61: 44000000 | H61: ETAT A PAYER
A62: 4410000 | B62: 44100000 | C62: ETAT: IRSA À PAYER | D62: -4461920 | E62: -7187410.4 | F62: -4098583.1 | G62: 44100000 | H62: ETAT: IRSA À PAYER
A63: 4430000 | B63: 44300000 | C63: ETAT: ACOMPTES IR | D63: 0 | E63: 14510227 | F63: 940941.5 | G63: 44300000 | H63: ETAT: ACOMPTES IR
A64: 4440000 | B64: 44400000 | C64: IR INTERMITENT ETRANGER | D64: 0 | E64: -302232.15 | F64: 0 | G64: 44400000 | H64: IR INTERMITENT ETRANGER
A65: 4441000 | B65: 44410000 | C65: CREDIT D'IR | D65: 0 | E65: 220000 | F65: -29260455 | G65: 44410000 | H65: CREDIT D'IR
A66: 4442000 | B66: 44420000 | C66: IR INTERMITENT LOCAUX | D66: -1654486.8 | E66: 0 | F66: -86748.75 | G66: 44420000 | H66: IR INTERMITENT LOCAUX
A67: 4443000 | B67: 44430000 | C67: IR A PAYER | D67: 0 | E67: 0 | F67: 0 | G67: 44430000 | H67: IR A PAYER
A68: 4454000 | B68: 44540000 | C68: TVA À DÉCAISSER | D68: 0.07 | E68: 0 | F68: 0 | G68: 44540000 | H68: TVA À DÉCAISSER
A69: 4455000 | B69: 44550000 | C69: CREDIT DE TAXE | D69: 1.2232057e+08 | E69: 2.2733386e+08 | F69: 1.5512835e+08 | G69: 44550000 | H69: CREDIT DE TAXE
A70: 4456100 | B70: 44561000 | C70: TVA dédu sur revente taxable | D70: 0 | E70: 0 | F70: 0 | G70: 44561000 | H70: TVA dédu sur revente taxable
A71: 4456200 | B71: 44562000 | C71: TVA pour les Biens | D71: 13095281 | E71: 4455117.4 | F71: 8644720.3 | G71: 44562000 | H71: TVA pour les Biens
... A77: 4457600 | B77: 44576000 | C77: TVA sur refacturation | D77: 0 | E77: 0 | F77: 0 | G77: 44576000 | H77: TVA sur refacturation
B78: 44577000 | C78: TVA en attente remboursement | D78: 49800000 | G78: 44577000 | H78: TVA en attente remboursement
A79: 4458000 | B79: 44580000 | C79: TVA à regulariser | D79: 1873360.3 | E79: 0 | F79: 0 | G79: 44580000 | H79: TVA à regulariser
A80: 4458300 | B80: 44583000 | C80: TVA DED/ FACTURE NON PARVENUE | D80: 0 | E80: 1224488.2 | F80: 7661753 | G80: 44583000 | H80: TVA DED/ FACTURE NON PARVENUE
A81: 4551000 | B81: 45510000 | C81: AGRIVAL | D81: -1494000000 | E81: -2594000000 | F81: -2074000000 | G81: 45510000 | H81: AGRIVAL
A82: 4551100 | B82: 45511000 | C82: C/C ISMAEL DANIL HOUSSEN | D82: -1.830852e+09 | E82: -1.8183742e+09 | F82: -1.1462742e+09 | G82: 45511000 | H82: C/C ISMAEL DANIL HOUSSEN
A83: 4551400 | B83: 45514000 | C83: C/C ISMAEL Shahim | D83: -39000000 | E83: -39000000 | F83: -39000000 | G83: 45514000 | H83: C/C ISMAEL Shahim
A84: 4551500 | B84: 45515000 | C84: C/C AGRICO LTD | D84: -25000000 | E84: -25000000 | F84: -25000000 | G84: 45515000 | H84: C/C AGRICO LTD
A85: 4660000 | B85: 46600000 | C85: Debiteurs & crediteurs divers | D85: 0 | E85: 1350000 | F85: 844800 | G85: 46600000 | H85: Debiteurs & crediteurs divers
A86: 4661000 | B86: 46610000 | C86: DEBITEURS&CREDITEURS DIV/REFAC | D86: -2.8086418e+08 | F86: -3.155199e+08 | G86: 46610000 | H86: DEBITEURS&CREDITEURS DIV/REFAC
A87: 46610000 | B87: 46610000 | C87: AGRIFARM | E87: -138720 | F87: 0 | G87: 46610000 | H87: AGRIFARM
A88: 46610000 | B88: 46610000 | C88: AGRIVAL | E88: -50464199 | F88: 0 | G88: 46610000 | H88: AGRIVAL
A89: 46610000 | B89: 46610000 | C89: AMCHO | E89: 37181444 | F89: 0 | G89: 46610000 | H89: AMCHO
A90: 46610000 | B90: 46610000 | C90: SMTP | E90: -1.3323634e+08 | F90: 0 | G90: 46610000 | H90: SMTP
A91: 46610000 | B91: 46610000 | C91: UNITED MALAGASY | E91: 4649527.6 | F91: 0 | G91: 46610000 | H91: UNITED MALAGASY
B92: 46620000 | C92: PROVISION ND / REFACTURATION | D92: -71947477 | G92: 46620000 | H92: PROVISION ND / REFACTURATION
B93: 46700000 | C93: CRÉANCES INTRA GROUPE/ PRET | D93: -2.74661e+09 | G93: 46700000 | H93: CRÉANCES INTRA GROUPE/ PRET
A94: 46700000 | B94: 46700000 | C94: AGRIVAL | E94: -4.1461002e+08 | F94: 0 | G94: 46700000 | H94: AGRIVAL
A95: 46700000 | B95: 46700000 | C95: AGRIVET | E95: -750000000 | F95: -750000000 | G95: 46700000 | H95: AGRIVET
A96: 4710000 | B96: 47100000 | C96: COMPTE D'ATTENTE | D96: 0 | E96: 0 | F96: 0 | G96: 47100000 | H96: COMPTE D'ATTENTE
A97: 4720000 | B97: 47200000 | C97: Bon Provisoire | D97: 0 | E97: 0 | F97: 0 | G97: 47200000 | H97: Bon Provisoire
B98: 48600000 | C98: CHARGES CONSTATÉES D'AVANCE | D98: 23345734 | G98: 48600000 | H98: CHARGES CONSTATÉES D'AVANCE
A99: 4870000 | B99: 48700000 | C99: PRODUITS CONSTATÉS D'AVANCE | D99: -22703894 | E99: -28897407 | F99: 0 | G99: 48700000 | H99: PRODUITS CONSTATÉS D'AVANCE
A100: 5111000 | B100: 51110000 | C100: CHÈQUE À ENCAISSER | D100: 0 | E100: 0 | F100: 0 | G100: 51110000 | H100: CHÈQUE À ENCAISSER
A101: 5112241 | B101: 51122410 | C101: TRAITE RECUE ENC BNI | D101: 0 | E101: 0 | F101: 0 | G101: 51122410 | H101: TRAITE RECUE ENC BNI
B102: 51130000 | C102: Echange chèque- traite | D102: 0 | G102: 51130000 | H102: Echange chèque- traite
A103: 5114000 | B103: 51140000 | C103: VIREMENT REÇU | D103: -446743.2 | E103: -212506416 | F103: -21990560 | G103: 51140000 | H103: VIREMENT REÇU
B104: 51202000 | C104: AIRTEL MONEY | D104: 283660 | G104: 51202000 | H104: AIRTEL MONEY
B105: 51231000 | C105: BOA MGA | D105: 0 | G105: 51231000 | H105: BOA MGA
A106: 5124100 | B106: 51241000 | C106: BNI MGA | D106: 1.7628238e+08 | E106: 2.5765333e+08 | G106: 51241000 | H106: BNI MGA
...

Sheet LMOI
E2: -1.0490417e-05
B3: Libellés | C3: 2021 | D3: 2020 | E3: 2019 | F3: Gestion
A4: 10100000 | B4: Capital | C4: -2500000000 | D4: -2500000000 | E4: -10000000 | F4: 10100000
A5: 10500000 | B5: Ecart d'évalutations | C5: -4.8681626e+09 | D5: -4.8681626e+09 | E5: 0 | F5: 10500000
A6: 11900000 | B6: RAN débiteur | C6: 44761038 | D6: 26908969 | E6: 26908969 | F6: 11900000
A7: 12800000 | B7: Resultat net en instance d'affectat | C7: 0 | D7: -22734534 | E7: 17852069 | F7: 12800000
A8: 12900000 | B8: Resultat net de exercice perte | C8: 0 | D8: 17852069 | E8: 0 | F8: 12900000
A9: 16100000 | B9: Emprunts BMOI | C9: -7.7871447e+09 | D9: -8.1756144e+09 | E9: -17895000000 | F9: 16100000
A10: 16110000 | B10: EMPRUNTS RABOBANK | C10: -1.1175588e+10 | D10: -1.79418e+10 | E10: -2.3208642e+10 | F10: 16110000
A11: 16200000 | B11: Emprunts BNI | C11: -5.7608547e+09 | D11: -8.1153054e+09 | E11: -9895000000 | F11: 16200000
A12: 16411000 | B12: DETTE COURT TERME BMOI | C12: -388469700 | D12: -2.1674402e+09 | E12: 0 | F12: 16411000
A13: 16413000 | B13: DETTE COURT TERME BNI | C13: -1.9429275e+09 | D13: -1.756342e+09 | E13: 0 | F13: 16413000
A14: 16414000 | B14: DETTE A COURT TERME BNI 2 | C14: -4.115232e+08 | D14: -3.7251592e+08 | E14: 0 | F14: 16413000
A15: 16420000 | B15: A RENOMMER | C15: 0 | D15: -5.9806e+09 | E15: 0 | F15: 16420000
... A67: 28120000 | B67: Amts Agens Amenag Terrain | C67: -5.8940399e+08 | D67: -2.7163079e+08 | E67: -67302147 | F67: 28120000
A68: 28121000 | C68: 0 | E68: -33493017 | F68: 28120000
A69: 28131000 | B69: AMMOT ABRI VOITURE | C69: -1329490.8 | D69: -1329490.8 | E69: 0 | F69: 28131000
A70: 28132000 | B70: AMMORT SILO | C70: 0 | D70: 0 | E70: 0 | F70: 28131000
A71: 281321000 | B71: AMMORT SOCLE SILO | C71: 0 | D71: -3.1303259e+08 | E71: 0 | F71: 28131000
A72: 28132300 | B72: AMMORT SILO 400T | C72: -28006521 | D72: -28006521 | E72: 0 | F72: 28131000
A73: 28132400 | B73: AMMORT SOUS SOL | C73: -70816839 | D73: -70816839 | E73: 0 | F73: 28131000
A74: 28133000 | B74: AMMORT TOUR ET SILO | C74: 0 | D74: 0 | E74: 0 | F74: 28131000
A75: 281331 | B75: AMMORT TOUR 1-2 RDC | C75: 0 | D75: -27982948 | E75: 0 | F75: 28131000
A76: 28133200 | B76: AMMORT TOUR 1-2 1ER ETAGE | C76: -27982948 | D76: -27982948 | E76: 0 | F76: 28131000
A77: 28133300 | B77: AMMORT TOUR 1-2 2EME ETAGE | C77: -27982948 | D77: -27982948 | E77: 0 | F77: 28131000
A78: 28133400 | B78: AMMORT TOUR 1-2 3EME ETAGE | C78: -27982948 | D78: -27982948 | E78: 0 | F78: 28131000
A79: 28133500 | B79: AMMORT TOUR 1-2 4EME ETAGE | C79: -27982948 | D79: -27982948 | E79: 0 | F79: 28131000
A80: 28133600 | B80: AMMORT TOUR 1-2 5EME ETAGE | C80: -27982948 | D80: -27982948 | E80: 0 | F80: 28131000
... A107: 35503000 | B107: STOCK SON | C107: 1.600163e+09 | D107: 1896469666 | E107: 0 | F107: 31000000
A108: 38000000 | B108: Stocks flottants | C108: 0 | E108: 2.3276736e+10 | F108: 38000000
A109: 39200000 | B109: PERTE DE STOCK MP | C109: 0 | D109: -5.3265475e+08 | E109: 0 | F109: 39200000
A110: 39500000 | B110: PERTE DE STOCK PF | C110: -66200000 | D110: -66200000 | E110: 0 | F110: 39500000
A111: 40110000 | B111: Fournisseur locaux | C111: -3.5059014e+09 | D111: -3.0687213e+09 | E111: -1.2251704e+09 | F111: 40110000
A112: 40120000 | B112: Fournisseur étranger | C112: -5.3375427e+10 | D112: -3.094073e+10 | E112: -3.4974505e+10 | F112: 40120000
A113: 40300000 | B113: F/sseurs effets à payer BMOI | C113: 0 | D113: 66129851 | E113: -1.5066803e+09 | F113: 40300000
A114: 40310000 | B114: F/sseurs effets à payer BNI | C114: 209236.39 | D114: -3.3100691e+08 | E114: -86343636 | F114: 40310000
A115: 40400000 | B115: F/sseurs d'immobilisations | C115: -9.4749057e+09 | D115: -1.0157799e+10 | E115: -5.7863478e+09 | F115: 40400000
A116: 40800000 | B116: F/sseurs fact à recevoir | C116: -2840834.2 | D116: -2832082.2 | E116: -99747596 | F116: 40800000
A117: 40810000 | B117: FRNS FACT NON PARVENUES | C117: 0 | D117: 0 | E117: -4218536.5 | F117: 40810000
A118: 40910000 | B118: Frns débiteurs: avances et acomptes | C118: 5.9587328e+08 | D118: 2.0113481e+10 | E118: 6.3668004e+08 | F118: 40910000
A119: 41100000 | B119: Collectifs clients | C119: 6.40184e+09 | D119: 3.3369015e+09 | E119: 1.6442263e+08 | F119: 41100000
A120: 41110000 | B120: clients non identifiés | C120: 395942160 | D120: 5.1941949e+08 | E120: 0 | F120: 41110000
... A146: 44570000 | B146: TVA collectées | C146: 0 | D146: -1.7166138e-05 | E146: 0 | F146: 44570000
A147: 44580000 | B147: TVA à regulariser | C147: 0 | E147: 9.4658798e+08 | F147: 44580000
A148: 45510000 | B148: MOHABOUBALY Férid | C148: -1585486200 | D148: -1585486200 | E148: -2207986200 | F148: 45510000
A149: 45520000 | B149: MOHABOUBALY Arifmamod | C149: -3.6321911e+08 | D149: -3.6321911e+08 | E149: -9.8570911e+08 | F149: 45520000
A150: 45530000 | B150: ISMAEL DANIL HOUSSEN | C150: -32148044 | D150: -32148044 | E150: -5.3014804e+08 | F150: 45530000
A151: 45540000 | B151: ISMAEL SHAHIM | C151: -18670944 | D151: -18670944 | E151: -3.9217094e+08 | F151: 45540000
A152: 45550000 | B152: ISMAEL YANISH | C152: -1.6758877e+08 | D152: -1.6758877e+08 | E152: -5.4108877e+08 | F152: 45550000
A153: 46600000 | B153: Debiteurs & crediteurs divers | C153: 67857556 | D153: 63824896 | E153: 63824896 | F153: 46600000
A154: 46700002 | B154: TARTINE | C154: -1320655718 | D154: -1320655718 | E154: -1320655718 | F154: 46700002
A155: 46700003 | B155: FIRST ENERGY | C155: 250000000 | D155: -1275000000 | E155: -1275000000 | F155: 46700002
A156: 46700004 | B156: AGRIVAL | C156: -120000000 | D156: -120000000 | E156: -120000000 | F156: 46700004
A157: 46710070 | B157: SMTP | C157: -4454871.9 | D157: -4454871.9 | E157: -4454871.9 | F157: 46710070
A158: 48600000 | B158: Charges constatées d'avance | C158: 3.4419878e+08 | D158: 1.8270197e+08 | E158: 1.4304208e+08 | F158: 48600000
A159: 49100000 | B159: Pertes de valeur/cptes clients | C159: -42500004 | D159: -42500004 | E159: 0 | F159: 49100000
... A169: 60201000 | B169: Emballages | C169: 3981204200 | D169: 2267735500 | E169: 3.2260417e+08 | F169: 60201000
A170: 60202000 | B170: Fournitures de bureau | C170: 0 | E170: 1769839.8 | F170: 60201000
A171: 60203000 | B171: Consommables informatiques | C171: 4459874 | D171: 12685642 | E171: 35000 | F171: 60203000
A172: 60204000 | B172: Produits d'hygiene & article ménage | C172: 4511108.3 | D172: 12196925 | E172: 0 | F172: 60204000
A173: 60205000 | B173: Petit outillage usine & maintenance | C173: 8689000 | D173: 63216161 | E173: 29060256 | F173: 60205000
A174: 60205200 | B174: Combustible | C174: 0 | D174: 238000 | E174: 0 | F174: 60205200
A175: 60206000 | B175: Pièces de rechange | C175: 43324140 | D175: 2535036.3 | E175: 0 | F175: 60206000
A176: 60223000 | B176: Fournitures d'atelier et d'usine | C176: 2.9925084e+08 | D176: 2.206056e+08 | E176: 0 | F176: 60206000
A177: 60301000 | B177: VARIATION STOCKS MATIERE PREMIERE | C177: -2.6790606e+10 | D177: 1.9373546e+10 | E177: -4.2074167e+10 | F177: 60301000
A178: 60302000 | B178: Variations AUTRES APPRO | C178: -1.1810781e+09 | D178: -3.2748503e+08 | E178: -28664200 | F178: 60302000
A179: 60400000 | B179: Prestations de services | C179: 0 | D179: 9359000 | E179: 866333.33 | F179: 60400000
A180: 60601000 | B180: Eau & électricité | C180: 0 | D180: 1.7177457e+09 | E180: 3.0380791e+08 | F180: 60601000
A181: 60602000 | B181: Carburants pour vehicules | C181: 734000 | D181: 44955038 | E181: 32031748 | F181: 60602000
A182: 60605000 | B182: Petit outillage | C182: 11399053 | D182: 38000 | E182: 34009604 | F182: 60605000
... A184: 60608000 | B184: Autres charges | C184: 0 | D184: 174110 | E184: 233240 | F184: 60608000
A185: 60609000 | B185: Achats matières et fournitures | C185: 0 | E185: 60834821 | F185: 60609000
A186: 60612000 | B186: CARBURANT | C186: 1.6237745e+08 | D186: 6457393.6 | E186: 0 | F186: 60609000
A187: 60630000 | B187: FOURNITURE D'ENTRETIEN ET PETIT EQU | C187: 19215153 | D187: 14579681 | E187: 0 | F187: 60630000
A188: 60631000 | B188: EQUIPEMENT AUTO | C188: 8253553.7 | D188: 244500 | E188: 0 | F188: 60630000
A189: 60636000 | B189: Vêtements de travail | C189: 3857892 | D189: 3515000 | E189: 0 | F189: 60630000
A190: 60640000 | B190: FOURNITURES DE BUREAU | C190: 9150394.2 | D190: 7168094.5 | E190: 0 | F190: 60640000
A191: 60801000 | B191: Fret | C191: 44071140 | D191: 3.2074164e+08 | E191: 1917790 | F191: 60801000
A192: 60803000 | B192: Honoraires transitaire | C192: 34853357 | D192: 101656389 | E192: 5.1966017e+08 | F192: 60803000
A193: 60804000 | B193: Divers frais de transit | C193: 6.4936742e+09 | D193: 2.9093685e+08 | E193: 4.6477867e+08 | F193: 60804000
A194: 60806000 | B194: Surestaries | C194: 0 | D194: 4.6380512e+08 | E194: 51254109 | F194: 60806000
A195: 60808000 | B195: Transport sur Achat | C195: 41133296 | D195: 2.1982585e+09 | E195: 6.8596075e+08 | F195: 60808000
A196: 60811000 | B196: Droits de douane | C196: 124206372 | D196: 57349637 | E196: 1.1602377e+08 | F196: 60811000
A197: 60811100 | B197: Frais divers Douane | C197: 398832105 | D197: 4.1835996e+08 | E197: 37342773 | F197: 60811100
... A218: 62260000 | B218: Frais envoie dossier | C218: 0 | D218: 4459334 | E218: 0 | F218: 62204000
A219: 62208000 | B219: Autres honoraires | C219: 0 | E219: 53662766 | F219: 62208000
A220: 62301000 | B220: Insertions publicitaires média | C220: 6290469 | D220: 5588067 | E220: 80000 | F220: 62301000
A221: 62302000 | B221: Sponsoring | C221: 33333333 | D221: 40000000 | E221: 0 | F221: 62302000
A222: 62303000 | B222: Support publicitaires | C222: 15546950 | D222: 1857710 | E222: 6412000 | F222: 62303000
A223: 62401000 | B223: Transport produits finis | C223: 0 | D223: 22900040 | E223: 207416667 | F223: 62401000
A224: 62402000 | B224: Transports /vente | C224: 1.5757722e+09 | D224: 2.4939705e+08 | E224: 0 | F224: 62402000
A225: 62403000 | B225: Transport sur achat | C225: 6.7553182e+08 | D225: 644462056 | E225: 0 | F225: 62403000
A226: 62501000 | B226: Billets d'avion | C226: 2.0545976e+08 | D226: 140954898 | E226: 145798516 | F226: 62501000
A227: 62504000 | B227: Réceptions et hebergement | C227: 40402735 | D227: 29372697 | E227: 0 | F227: 62504000
A228: 62505000 | B228: Mission et déplacement | C228: 27938018 | D228: 5954271.7 | E228: 90453596 | F228: 62505000
A229: 62506000 | B229: Frais de deplacement en ville | C229: 102000 | D229: 774200 | E229: 94400 | F229: 62506000
A230: 62601000 | B230: Telephone fixe | C230: 0 | E230: 1442322 | F230: 62601000
A231: 62602000 | B231: Telephone mobile | C231: 21072584 | D231: 17400562 | E231: 11619851 | F231: 62602000
A232: 62603000 | B232: Internet | C232: 8013332 | D232: 8089000 | E232: 0 | F232: 62603000
A233: 62604000 | B233: Envoi colis | C233: 0 | D233: 26480 | E233: 335480 | F233: 62604000
...

Sheet TARTINE
F2: EF CONSO
C3: Libellés | D3: 2021 | E3: 2020 | F3: 2019 | G3: Gestion
A4: 101000 | B4: 10100000 | C4: CAPITAL SOCIAL | D4: -10000000 | E4: -10000000 | F4: -10000000 | G4: 10100000
A5: 110000 | B5: 11000000 | C5: REPPORT | D5: -1.6673122e+08 | E5: -1.6673122e+08 | F5: -1.6673122e+08 | G5: 11000000
A6: 120000 | B6: 12000000 | C6: RESULTAT EN INSTANCE | D6: -5.5200068e+08 | E6: -1.8951649e+08 | F6: 0 | G6: 12000000
B7: 12800000 | C7: RESULTAT EN INSTANCE D AFFECTATION | D7: 0 | F7: 1.1298661e+08 | G7: 12800000
A8: 164000 | B8: 16400000 | C8: EMPRUNT A LMT | D8: 92.52 | E8: 92.52 | F8: 0 | G8: 16100000
A9: 203000 | B9: 20300000 | C9: FRAIS DE PREMIER ETABLISSEMENT | D9: 395000 | E9: 395000 | F9: 395000 | G9: 20300000
B10: 21300000 | C10: CONSTRUCTION | D10: 4.134719e+08 | G10: 21500000
A11: 215000 | B11: 21500000 | C11: AGENCEMENT,AMENAGEMENT BATIMENT | D11: 33185707 | E11: 33185707 | F11: 33185707 | G11: 21500000
A12: 215400 | B12: 21540000 | C12: MATERIET ET OUTILLAGE INDUSTRIEL | D12: 4.6715389e+09 | E12: 4.4693722e+09 | F12: 3.9804631e+09 | G12: 21540000
A13: 218200 | B13: 21820000 | C13: MATERIEL DE TRANSPORT | D13: 6.8631579e+08 | E13: 6.3631579e+08 | F13: 3.2772076e+08 | G13: 21830000
A14: 218300 | B14: 21830000 | C14: MATERIELT ET MOBILIER DE BUREAU | D14: 3.2970518e+08 | E14: 3.2970518e+08 | F14: 6.3344079e+08 | G14: 21820000
A15: 218310 | B15: 21831000 | C15: MATERIEL INFORMATIQUE &DIVERS MACHI | D15: 2.7503161e+08 | E15: 2.6173275e+08 | F15: 257013902 | G15: 21840000
A16: 232000 | B16: 23200000 | C16: IMMOBILISATION EN COURS | D16: 0 | E16: 2.5597773e+08 | F16: 2.5597773e+08 | G16: 23200000
A17: 275000 | B17: 27500000 | C17: DEPOT ET CAUTIONNEMENT VERSE | D17: 7776400 | E17: 7776400 | F17: 7764400 | G17: 27500000
A18: 280300 | B18: 28030000 | C18: AMORTISSEMENT FRAIS D'ETABLISSEMENT | D18: -395000 | E18: -395000 | F18: -395000 | G18: 28030000
B19: 28130000 | C19: AMORTISSEMENT CONSTRUCTIONS | D19: -33967322 | G19: 28150000
A20: 281500 | B20: 28150000 | C20: AMORTISSEMENT AGENCEMENT AMENAGM | D20: -25367332 | E20: -22048761 | F20: -18730191 | G20: 28150000
A21: 281540 | B21: 28154000 | C21: AMORTISSEMENT MAT ET OUTILLAGE | D21: -3.4536574e+09 | E21: -2.9932424e+09 | F21: -2.9932424e+09 | G21: 28154000
A22: 281550 | B22: 28155000 | C22: AMORTISSEMENT GROUPE, MATERIELS | D22: -4.1078548e+08 | E22: -4.1078548e+08 | F22: 0 | G22: 28154000
A23: 281820 | B23: 28182000 | C23: AMORTISSEMENT MATERIEL DE TRANSPORT | D23: -5.7857341e+08 | E23: -4.7974115e+08 | F23: -3.8053146e+08 | G23: 28183000
A24: 281830 | B24: 28183000 | C24: AMORTISSEMENT MOBILIER DE BUREAU | D24: -3.2654307e+08 | E24: -3.2430448e+08 | F24: -3.2207525e+08 | G24: 28182000
A25: 281831 | B25: 28183100 | C25: AMORTISSEMENT MAT INFORMATIQUE | D25: -2.580737e+08 | E25: -2.4785202e+08 | F25: -222111311 | G25: 28184000
A26: 310000 | B26: 31000000 | C26: STOCK | D26: 3769834243 | E26: 2913947581 | F26: 2.6087187e+09 | G26: 31000000
A27: 350000 | B27: 35000000 | C27: STOCK PRODUIT FINI | D27: 54663892 | E27: -1292000 | F27: 63711112 | G27: 35500000
A28: 401000 | B28: 40100000 | C28: FOURNISSEUR D'EXPLOITATION | D28: -1.3561763e+09 | E28: -4.8513681e+08 | F28: 0 | G28: 40110000
A29: 401100 | B29: 40110000 | C29: FOURNISSEUR ETRANGER | D29: 45300075 | E29: 86420751 | F29: -4.0179266e+08 | G29: 40110000
A30: 404000 | B30: 40400000 | C30: FOURNISSEUR D'IMMOBILISATION | D30: -9049257.6 | E30: -7849257.6 | F30: -7849257.6 | G30: 40400000
A31: 411000 | B31: 41100000 | C31: CLIENT | D31: 4.1121022e+08 | E31: 4.2339562e+08 | F31: 4.175079e+08 | G31: 41100000
... A70: 606211 | B70: 60621100 | C70: HUILE, CARBURANT, GRAISSE POUR BOUL | D70: 6.7169799e+08 | E70: 3.9791267e+08 | F70: 0 | G70: 60600000
B71: 60630000 | C71: GAS OIL POUR GROUPE ELECTROGENE | D71: 10625000 | G71: 60600000
A72: 606400 | B72: 60640000 | C72: FOURNITURES ADMINISTRATIVES | D72: 12582915 | E72: 5564142 | F72: 5126524.3 | G72: 60600000
B73: 60812000 | C73: Gasy Net | D73: 0 | F73: 360794 | G73: 60800000
B74: 61000000 | C74: FRAIS DIVERS | D74: 6660426.3 | G74: 60600000
B75: 61100000 | C75: sous traitances | D75: 0 | F75: 23169247 | G75: 61100000
A76: 611400 | B76: 61140000 | C76: VISITE | D76: 0 | E76: 1884396 | F76: 0 | G76: 61100000
A77: 611620 | B77: 61162000 | C77: DSMI | D77: 0 | E77: 3765640.3 | F77: 0 | G77: 61100000
A78: 613000 | B78: 61300000 | C78: LOCATION D' IMMEUBLE | D78: 1200000 | E78: 1200000 | F78: 1800000 | G78: 61300000
B79: 61300100 | C79: LOCATION BOUTEILLE A GAZ | D79: 1328416.7 | G79: 61300000
B80: 61302000 | C80: LOCATø GROUPE DEPANAGE | D80: 8436000 | G80: 61300000
A81: 615000 | B81: 61500000 | C81: ENTRETIEN REPARATION MAINTENANCE | D81: 8099876.7 | E81: 12354333 | F81: 13765262 | G81: 61500000
A82: 615200 | B82: 61520000 | C82: ENTTRETIEN, REPARATION BOULANGERIE | D82: 0 | E82: 9384000 | F82: 0 | G82: 61500000
A83: 615500 | B83: 61550000 | C83: ENTRETIEN POSTE TRANSFO JIRAMA | D83: 5503540 | E83: 564480 | F83: 0 | G83: 61500000
B84: 61600000 | C84: PRIME D'ASSURANCE | D84: 23961638 | G84: 61500000
B85: 61604000 | C85: Autres polices d'assurances | D85: 0 | F85: 7596944 | G85: 61600000
B86: 61710000 | C86: ASSISTANCE REMORQUAGE | D86: 560833.33 | G86: 61500000
A87: 621000 | B87: 62100000 | C87: PERSONNEL EXTERIEUR A L'ENTREPRISE | D87: 55080000 | E87: 33580000 | F87: 22080000 | G87: 62100000
A88: 622000 | B88: 62200000 | C88: VEHICULE GPS | D88: 2520000 | E88: 2520000 | F88: 0 | G88: 62200000
B89: 62208000 | C89: Autres honoraires | D89: 0 | F89: 3465986 | G89: 62200000
A90: 622200 | B90: 62220000 | C90: HONORAIRE TRANSITAIRE | D90: 0 | E90: 434193.39 | F90: 0 | G90: 62200000
A91: 622210 | B91: 62221000 | C91: PRESTATION GASY NET | D91: 0 | E91: 711541 | F91: 0 | G91: 62200000
A92: 622222 | B92: 62222200 | C92: HONORAIRE EXPERT COMPTABLE | D92: 7600000 | E92: 6000000 | F92: 6000000 | G92: 62200000
B93: 62224000 | C93: DEVELOPPEMENT LOGICIEL DE GESTION | D93: 1270000 | G93: 62200000
A94: 622242 | B94: 62224200 | C94: DOMAINE TARTINE.MG | D94: 420000 | E94: 233333.33 | F94: 0 | G94: 62200000
B95: 62301000 | C95: Insertions publicitaires média | D95: 0 | F95: 1750000 | G95: 62300000
B96: 62401000 | C96: Transport | D96: 0 | F96: 2762000 | G96: 62401000
A97: 625000 | B97: 62500000 | C97: DEPLACEMENT, MISSION ET RECEPTION | D97: 10793281 | E97: 12170443 | F97: 1.2856261e+08 | G97: 62501000
A98: 625010 | B98: 62501000 | C98: HEBERGEMENT, HOTELERIE | D98: 0 | E98: 2723083.3 | F98: 0 | G98: 62501000
A99: 626000 | B99: 62600000 | C99: FRAIS POSTAUX ET TELECOMMUNICATION | D99: 0 | E99: 27133 | F99: 0 | G99: 62601000
A100: 626010 | B100: 62601000 | C100: TELEPHONE FIXE | D100: 887068.67 | E100: 530890 | F100: 2811915.7 | G100: 62601000
A101: 626020 | B101: 62602000 | C101: TELEPHONE MOBILE | D101: 12484980 | E101: 9653276.3 | F101: 7001129.9 | G101: 62601000
A102: 626040 | B102: 62604000 | C102: INTERNET BLUELINE | D102: 9828000 | E102: 9072000 | F102: 8960000 | G102: 62601000
B103: 62606000 | C103: GEOLOCALISATION VEHICULE | D103: 0 | F103: 2520000 | G103: 62601000
A104: 627000 | B104: 62700000 | C104: SERVICE BANCAIRE ET ASSIMILE | D104: 0 | E104: 10000 | G104: 62701000
B105: 62708000 | C105: Frais abonnement WEB | D105: 0 | F105: 353332.2 | G105: 62701000
A106: 627200 | B106: 62720000 | C106: FRAIS DE TENUE DE COMPTE | D106: 0 | E106: 8879184.4 | F106: 0 | G106: 62701000
A107: 627400 | B107: 62740000 | C107: DIVERS FRAIS ET COMMISSIONS | D107: 566260.4 | E107: 529213.33 | F107: 9080196.9 | G107: 62701000
A108: 627500 | B108: 62750000 | C108: FRAIS & COMø DE TRANSFERT ETRANGER | D108: 376932.76 | E108: 4184109.1 | F108: 0 | G108: 62701000
A109: 627600 | B109: 62760000 | C109: COMMISSION DE DOMICILIATION | D109: 116667 | E109: 142500 | F109: 120000 | G109: 62701000
A110: 627900 | B110: 62790000 | C110: ABONNEMENT CARTE UNIVERSELLE | D110: 200000 | E110: 249000 | F110: 0 | G110: 62701000
B111: 62800000 | C111: COMMISSION TRANSIT & TRANSPORT | D111: 7022809.8 | G111: 62800000
A112: 628010 | B112: 62801000 | C112: COTISATION VERSEE | D112: 6150000 | E112: 5000000 | F112: 5000000 | G112: 62800000
A113: 631000 | B113: 63100000 | C113: DROIT DE DOUANE | D113: 547279.58 | E113: 14246414 | F113: 0 | G113: 63500000
A114: 641000 | B114: 64100000 | C114: SALAIRE ET APPOINTEMENT | D114: 4.1941816e+08 | E114: 3.4764093e+08 | F114: 3.0380572e+08 | G114: 64101000
B115: 64504000 | C115: FMFP Patronale | D115: 0 | F115: 1400278.1 | G115: 64501000
A116: 645100 | B116: 64510000 | C116: CHARGES PATRONALES CNaPS | D116: 42213017 | E116: 31780770 | F116: 24569034 | G116: 64501000
A117: 646000 | B117: 64600000 | C117: CHARGE PERSONNEL MEDICAMENTS | D117: 9039700 | E117: 3318200 | F117: 0 | G117: 64700000
A118: 648000 | B118: 64800000 | C118: CANTINE | D118: 46534000 | E118: 32254000 | F118: 26192000 | G118: 64801000
A119: 648100 | B119: 64810000 | C119: AUTRES CHARGES DU PERSONNEL | D119: 8682450.4 | E119: 23768707 | F119: 3471057.6 | G119: 64801000
A120: 655000 | B120: 65500000 | C120: DON et OEUVRE SOCIALE | D120: 0 | E120: 5000000 | F120: 1900000 | G120: 65602000
B121: 65600000 | C121: AMENDE ET PENALITE | D121: 868517.54 | G121: 65602000
A122: 658000 | B122: 65800000 | C122: AUTRES CHARGES DE GESTION | D122: 105300 | E122: 401900 | F122: 1048024.4 | G122: 65700000
B123: 66102000 | C123: Intérêt bancaires/ Agios | D123: 0 | F123: 1412976.5 | G123: 66100000
A124: 681000 | B124: 68100000 | C124: DOTATø AUX AMORTISSM & PROVø | D124: 6.2085383e+08 | E124: 5.4128368e+08 | F124: 5.3877866e+08 | G124: 68112000
B125: 69500000 | C125: IMPOT SUR LE REVENU | D125: 77387462 | G125: 69500000
B126: 69800000 | C126: Autres impôts sur le résultat | D126: 0 | F126: 76498923 | G126: 69500000
A127: 701000 | B127: 70100000 | C127: VENTE DU PAIN | D127: -8.5540182e+09 | E127: -6.5031343e+09 | F127: -6.1486412e+09 | G127: 70110000
A128: 713000 | B128: 71300000 | C128: VARIATION STOCK PRODUIT FINI | D128: 7755220 | E128: 1292000 | F128: -63711112 | G128: 71400000
A129: 758000 | B129: 75800000 | C129: AUTRES PRODUITS DE GESTION | D129: -9233.17 | E129: -4800 | F129: -39199.92 | G129: 75800000
A130: 762000 | B130: 76200000 | C130: INTERETS CREDITEURS | D130: -10813470 | E130: -1529750.9 | F130: 0 | G130: 76500000
B131: 76500000 | C131: Intérets crediteurs | D131: 0 | F131: -2557610.8 | G131: 76500000

Sheet IDF
C1: 2021 | D1: 2020
A2: 10100000 | B2: Capital | C2: -4520000000 | D2: -4520000000 | E2: -4520000000 | F2: 10100000 | H2: -4520000000
A3: 10610000 | B3: Reserves légales | C3: -452000000 | D3: -452000000 | E3: -452000000 | F3: 10610000 | H3: -452000000
A4: 11000000 | B4: RAN crediteur | C4: -5.3453872e+09 | D4: -5.3453872e+09 | E4: -5.3453872e+09 | F4: 11000000 | H4: -5.3453872e+09
A5: 12000000 | B5: Resultat net de l'exercice benefice | C5: 0 | D5: 0 | E5: 0 | F5: 12000000 | H5: 0
A6: 12800000 | B6: Resultat net en instance d'affectat | C6: -3.7114218e+09 | D6: -2.6345924e+09 | E6: -1.2928444e+09 | F6: 12800000 | H6: -1.2928444e+09
A7: 16200000 | B7: Emprunts LMT BNI | C7: -2.0159906e+08 | D7: -9.6428724e+08 | E7: -1.9781291e+09 | F7: 16100000 | H7: -1.9781291e+09
A8: 16210000 | B8: Emprunt CTS BNI | C8: 0 | D8: -500000000 | E8: 0 | F8: 16100000 | H8: 0
A9: 16220000 | B9: Emprunt part -1an BGFI | C9: -7.2024501e+08 | D9: -6.5107759e+08 | E9: 0 | F9: 16150000 | H9: 0
A10: 16230000 | B10: Emprunt part -1an BNI | C10: -9.9179637e+08 | D10: -6.9727864e+08 | E10: 0 | F10: 16100000 | H10: 0
A11: 16450000 | B11: EMPRUNT BGFI | C11: -3.8836305e+08 | D11: -1.1086081e+09 | E11: -2.1570666e+09 | F11: 16150000 | H11: -2.1570666e+09
A12: 16500000 | B12: Depots et cautionnements re | C12: -1.5811715e+08 | D12: -1.5621e+08 | E12: -2.2623315e+08 | F12: 16500000 | H12: -2.2623315e+08
A13: 16510000 | B13: Caution la CITY | C13: -7.4047613e+08 | D13: -6.2032379e+08 | E13: -4.4018188e+08 | F13: 16500000 | H13: -4.4018188e+08
... A54: 41910000 | B54: Clients créditeurs: acomptes | C54: -1.2180264e+09 | D54: -67001176 | E54: -38719439 | F54: 41910000 | H54: -38719439
A55: 41980000 | C55: 0 | E55: -39797548 | F55: 41980000 | H55: -39797548
A56: 42100000 | B56: Rémunérations dues au personnel | C56: 7026192.6 | D56: -1976146.9 | E56: 0 | F56: 42110000 | H56: 0
A57: 42110000 | B57: Salaires Temporaires | C57: 0 | D57: 0 | E57: 0 | F57: 42110000 | H57: 0
A58: 42520000 | B58: Avances spéciales | C58: -21667.66 | D58: 1325000 | E58: 0 | F58: 42520000 | H58: 0
A59: 42800000 | B59: Congés payés provision | C59: -73922784 | D59: -42239582 | E59: -45822526 | F59: 42800000 | H59: -45822526
A60: 43100000 | B60: CNaPS | C60: -12983942 | D60: -17967253 | E60: -14381402 | F60: 43100000 | H60: -14381402
A61: 43110000 | B61: Allocation familiale CNAPS | C61: -804000 | D61: -396000 | E61: =-240000 -> -240000 | F61: 43110000 | H61: -240000
A62: 43200000 | B62: OSTIE | C62: -7795343.8 | D62: -7652251.4 | E62: =-6115457.94+H63 -> -6163457.9 | F62: 43200000 | H62: -6115457.9
A63: 43220000 | B63: FUNECHE | C63: -17000 | D63: -40000 | F63: 43100000 | H63: -48000
A64: 43300000 | B64: FMFP | C64: -254669.08 | D64: -1283375.2 | E64: -1027243 | F64: 43300000 | H64: -1027243
A65: 43860000 | B65: Organismes autres charges à payer | C65: 0 | D65: -4531293 | E65: -13662186 | F65: 43860000 | H65: -13662186
A66: 44000000 | B66: Etat à payer | C66: 0 | D66: 0 | E66: 0 | F66: 44400000 | H66: 0
A67: 44100000 | B67: Etat: IRSA à payer | C67: -18328370 | D67: -18295478 | E67: -12151263 | F67: 44100000 | H67: -12151263
A68: 44200000 | B68: Etat : IFPB | C68: -898979230 | D68: -452291346 | E68: -335608089 | F68: 44200000 | H68: -335608089
A69: 44300000 | B69: Etat: acomptes IR | C69: 3.3738727e+08 | D69: 3.4314863e+08 | E69: 4.2736981e+08 | F69: 44300000 | H69: 4.2736981e+08
A70: 44400000 | B70: Crédit IR | C70: 1.1982909e+08 | D70: 70987822 | E70: 2545460.2 | F70: 44410000 | H70: 2545460.2
A71: 44410000 | B71: IR Intermittent locaux | C71: -2186426.3 | D71: -2168421.1 | E71: -394354.33 | F71: 44411000 | H71: -394354.33
A72: 44420000 | B72: TVA Intermittente étranger | C72: 2078209.2 | D72: 1531605.2 | E72: -8715235.3 | F72: 44412000 | H72: -8715235.3
A73: 44430000 | B73: Impôts sur les résultats (IR) | C73: 0 | D73: -2.9430691e+08 | E73: -3.5892745e+08 | F73: 44400000 | H73: -3.5892745e+08
A74: 44540000 | B74: TVA à décaisser | C74: -1.0492892e+08 | D74: 0 | E74: -1.5175573e+08 | F74: 44540000 | H74: -1.5175573e+08
A75: 44550000 | B75: Credit de taxe | C75: 0 | D75: 13647300 | E75: 0 | F75: 44550000 | H75: 0
... A102: 46720800 | B102: AGRIFARM | C102: 0 | D102: -187680 | E102: -211500 | F102: 46610000 | H102: -211500
A103: 46721000 | B103: SIRR | C103: 0 | D103: 0 | E103: 0 | F103: #N/A | H103: 0
A104: 46722000 | B104: SIM | C104: 0 | D104: 395000000 | E104: 695000000 | F104: 46731000 | H104: 695000000
A105: 46723000 | B105: AMCHO | C105: 0 | D105: 0 | E105: 500000000 | F105: 46732000 | H105: 500000000
A106: 46724000 | B106: FLY TECHNOLOGIE | C106: 0 | D106: -48344709 | E106: 42131026 | F106: 46733000 | H106: 42131026
A107: 46725000 | B107: IRS IMMO | C107: 0 | D107: 2046999.5 | E107: 0 | F107: 46743000 | H107: 0
A108: 47100000 | B108: Compte d'attente | C108: 0 | D108: 0 | E108: 0 | F108: 47100000 | H108: 0
A109: 48600000 | B109: Charges constatées d'avance | C109: 97269372 | D109: 45747357 | E109: 30574953 | F109: 48600000 | H109: 30574953
A110: 48700000 | B110: PRODUIT CONSTATE D'AVANCE | C110: 0 | D110: 0 | E110: -34136516 | F110: 48700000 | H110: -34136516
A111: 49100000 | B111: Pertes de valeur/cptes clients | C111: -8.1814077e+08 | D111: -1.0911638e+09 | E111: -9.5747333e+08 | F111: 49100000 | H111: -9.5747333e+08
A112: 51110000 | B112: Chèque à encaisser | C112: 17764115 | D112: 92478190 | E112: 3391500 | F112: 51110000 | H112: 3391500
A113: 51120000 | B113: Traite reçue | C113: 2.3008493e+08 | D113: 9.9014552e+08 | E113: 3200000 | F113: 51110000 | H113: 3200000
A114: 51140000 | B114: Virement- Chq- Versment reçus | C114: -82688040 | D114: -2979124.4 | E114: 0 | F114: 51110000 | H114: 0
A115: 51211000 | B115: BMOI Ariary | C115: 14955512 | D115: 10519563 | E115: 86804361 | F115: 51211000 | H115: 86804361
... A132: 60609000 | B132: Achats matières et fournitures | C132: 2.1924263e+08 | D132: 165466540 | E132: 5.6214769e+08 | F132: 60600000 | H132: 5.6214769e+08
A133: 60801000 | B133: Fret | C133: 0 | E133: 0 | F133: 60800000 | H133: 0
A134: 60802000 | B134: Assurance | C134: 0 | E134: 0 | F134: 60800000 | H134: 0
A135: 60803000 | B135: Honoraires transitaire | C135: 0 | E135: 90000 | F135: 60800000 | H135: 90000
A136: 60804000 | B136: Divers frais de transit | C136: 0 | E136: 775696.88 | F136: 60800000 | H136: 775696.88
A137: 60808000 | B137: Transport terrestre | C137: 0 | E137: 85000 | F137: 60800000 | H137: 85000
A138: 60811000 | B138: Droits de douane | C138: 0 | E138: 1180363 | F138: 60800000 | H138: 1180363
A139: 60812000 | B139: Gasy Net | C139: 0 | E139: 101485 | F139: 60800000 | H139: 101485
A140: 60900000 | B140: RRR obtenus | C140: -5171051.2 | D140: -283475.71 | E140: 0 | F140: 60800000 | H140: 0
A141: 60970000 | B141: RRR O/ achats | C141: 0 | D141: -4730061.1 | E141: 0 | F141: 60900000 | H141: 0
A142: 61100000 | B142: Sous traitance Groupe | C142: 2.2562608e+08 | D142: 95135085 | E142: 1.1474338e+08 | F142: 61100000 | H142: 1.1474338e+08
A143: 61101000 | B143: Enlèvement déchet la city Sotherly | C143: 54664230 | D143: 40644450 | E143: 41934750 | F143: 61100000 | H143: 41934750
A144: 61301000 | B144: Locations immobilières | C144: 1.3183712e+09 | D144: 6.5243645e+08 | E144: 0 | F144: 61300000 | H144: 0
A145: 61302000 | B145: Locations mobilières | C145: 46426548 | D145: 33964538 | E145: 11241564 | F145: 61300000 | H145: 11241564
A146: 61400000 | B146: Charges locatives | C146: 11416691 | D146: 15712347 | E146: 0 | F146: 61300000 | H146: 0
A147: 61500000 | B147: Autres entretiens et réparations po | C147: 1605856 | D147: 85510298 | E147: 1397000 | F147: 61500000 | H147: 1397000
A148: 61501000 | B148: ERM Immobilieres | C148: 401760.67 | D148: 8881130.3 | E148: 7857562.5 | F148: 61500000 | H148: 7857562.5
A149: 61501110 | B149: ERM DIGITAL | C149: 0 | D149: 105879.57 | E149: 477391.95 | F149: 61500000 | H149: 477391.95
A150: 61501120 | B150: ERM ANDRANOMENA | C150: 4450570 | D150: 1470000 | E150: 181500 | F150: 61500000 | H150: 181500
A151: 61501200 | B151: ERM ANTSAHAVOLA | C151: 0 | D151: 6961951.8 | E151: 12484779 | F151: 61500000 | H151: 12484779
A152: 61501400 | B152: ERM ABAO | C152: 573984 | D152: 8947471 | E152: 5426144.3 | F152: 61500000 | H152: 5426144.3
A153: 61501600 | B153: ERM AVOANJO | C153: 0 | E153: 392700 | F153: 61500000 | H153: 392700
A154: 61501700 | B154: ERM LA CITY | C154: 2.436897e+08 | D154: 1.1509689e+08 | E154: 1.6743449e+08 | F154: 61500000 | H154: 1.6743449e+08
A155: 61503000 | B155: ERM vehicules | C155: 8689660.4 | D155: -1063467.3 | E155: 7096770.6 | F155: 61500000 | H155: 7096770.6
A156: 61504000 | B156: ENTRETIEN APPARTEMENTS LA CITY | C156: 0 | D156: 18000000 | E156: 0 | F156: 61500000 | H156: 0
A157: 61601000 | B157: Assurances flottes auto | C157: 6120.73 | E157: 16200 | F157: 61600000 | H157: 16200
A158: 61602000 | B158: Assurances multirisques | C158: 1.5167881e+08 | D158: 80800356 | E158: 81191034 | F158: 61600000 | H158: 81191034
A159: 61604000 | B159: Autres polices d'assurances | C159: 970955.82 | D159: 81781926 | E159: 85111015 | F159: 61600000 | H159: 85111015
A160: 61801000 | B160: Journaux | C160: 635030 | D160: 16500 | E160: 74000 | F160: 61800000 | H160: 74000
A161: 61802000 | B161: Autres divers & documentation | C161: 202925 | D161: 687036 | E161: 208912 | F161: 61800000 | H161: 208912
A162: 62101000 | B162: Personnel extérieur de l'entreprise | C162: 25330980 | D162: 62138795 | E162: 1.0474548e+08 | F162: 62100000 | H162: 1.0474548e+08
A163: 62102000 | B163: Agent de sécurité | C163: 89300833 | D163: 1.7937417e+08 | E163: 1.597786e+08 | F163: 62100000 | H163: 1.597786e+08
A164: 62103000 | B164: Prestation ALPHA MADA | C164: 50709086 | D164: 44112348 | E164: 16625932 | F164: 62100000 | H164: 16625932
A165: 62105000 | B165: Prestation deratisation-desinsectio | C165: 6887800 | D165: 3030200 | E165: 4296750 | F165: 62100000 | H165: 4296750
A166: 62106000 | B166: Prestation NICE GARDEN | C166: 15575414 | D166: 15140000 | E166: 17700000 | F166: 62100000 | H166: 17700000
A167: 62109000 | B167: Prestation URBAN PROPRETE | C167: 0 | E167: 54960000 | F167: 62100000 | H167: 54960000
A168: 62201000 | B168: Honoraires Huissiers | C168: 99182563 | D168: 12723068 | E168: 6156000 | F168: 62200000 | H168: 6156000
A169: 62202000 | B169: Honoraires avocat divers | C169: 0 | D169: 17981000 | E169: 114275000 | F169: 62200000 | H169: 114275000
A170: 62203000 | B170: Honoraire commissaire aux comptes | C170: 245544 | D170: 37060100 | E170: 0 | F170: 62200000 | H170: 0
A171: 62204000 | B171: Honoraires United Malagasy | C171: 0 | D171: 18840765 | E171: 65333333 | F171: 62200000 | H171: 65333333
A172: 62208000 | B172: Autres honoraires | C172: 1.0165193e+08 | D172: 85950236 | E172: 1.7719759e+08 | F172: 62200000 | H172: 1.7719759e+08
A173: 62301000 | B173: Insertions publicitaires média | C173: 30898927 | D173: 1938454.1 | E173: 6891486 | F173: 62300000 | H173: 6891486
A174: 62302000 | B174: Sponsoring & billets | C174: 2547517 | E174: 1500000 | F174: 62300000 | H174: 1500000
A175: 62303000 | B175: Support publicitaires | C175: 6487401.7 | D175: 42203343 | E175: 36871455 | F175: 62300000 | H175: 36871455
A176: 62304000 | B176: Foires & expositions | C176: 42112294 | D176: 4310000 | E176: 35000 | F176: 62300000 | H176: 35000
A177: 62401000 | B177: Transport sur achats | C177: 2184000 | D177: 47000 | E177: 4706000 | F177: 62401000 | H177: 4706000
A178: 62501000 | B178: Billets d'avion | C178: 18230444 | D178: 17057355 | E178: 24965627 | F178: 62501000 | H178: 24965627
A179: 62503000 | B179: Per Diem tournées | C179: 673479 | D179: 79005 | E179: 0 | F179: 62501000 | H179: 0
A180: 62504000 | B180: Réceptions | C180: 2798806 | E180: 2775179 | F180: 62501000 | H180: 2775179
A181: 62505000 | B181: Mission: Hergement , hotel | C181: 2420746 | D181: -80050 | E181: 3769251.7 | F181: 62501000 | H181: 3769251.7
A182: 62506000 | B182: Frais de deplacement en ville | C182: 2887080 | D182: 1816900 | E182: 7380577.4 | F182: 62501000 | H182: 7380577.4
...

Sheet RYA
D1: 2021 | E1: 2020 | F1: 2019
A2: N°COMPTE | C2: LIBELLE
A3: 101000 | B3: 10100000 | C3: Capital | D3: -1350000000 | E3: -1100000000 | F3: -10000000 | G3: 10100000
A4: 119000 | B4: 11900000 | C4: RAN (Solde débiteur) | D4: 1.8101098e+08 | E4: 1.8101098e+08 | F4: 1.1150155e+08 | G4: 11900000
A5: 120000 | B5: 12000000 | C5: Résultat - bénéfice | D5: -3.4222507e+08 | E5: 0 | F5: 0 | G5: 12000000
A6: 129000 | B6: 12900000 | C6: Résultat - perte | D6: 0 | E6: 0 | F6: 0 | G6: 12900000
B7: 16413000 | C7: Emprunt BFV_Part plus d'un an | D7: -3.6228585e+09 | G7: 16413000
B8: 16413100 | C8: Emprunt BFV-Part moins d'un an | D8: -6.2936178e+08 | G8: 16413000
A9: 165000 | B9: 16500000 | C9: Depots et cautionnements reçus | D9: -64226195 | E9: -44340784 | F9: 0 | G9: 16500000
A10: 211000 | B10: 21100000 | C10: Terrains | D10: 1.0381894e+09 | E10: 9.1318939e+08 | F10: 7.9407939e+08 | G10: 21100000
A11: 212000 | B11: 21200000 | C11: Agenc. et aménag. de terrains | D11: 1.7683271e+08 | E11: 1.7683271e+08 | F11: 1.8290495e+08 | G11: 21200000
A12: 213000 | B12: 21300000 | C12: Batiments - Constructions | D12: 5.2059049e+09 | E12: 4.4697993e+08 | F12: 4.4697993e+08 | G12: 21300000
A13: 215000 | B13: 21500000 | C13: Agencement aménagement install | D13: 1.1546931e+08 | E13: 63528991 | F13: 46270341 | G13: 21500000
A14: 218100 | B14: 21810000 | C14: Matériels & outillages | D14: 8498717.8 | E14: 3613750 | F14: 3613750 | G14: 21540000
A15: 218800 | B15: 21880000 | C15: Materiel&mobilier de logement | D15: 77100928 | E15: 3976733.3 | F15: 0 | G15: 21820000
B16: 23120000 | C16: Immo en cours Analamahitsy | D16: 2699631.9 | G16: 23120000
B17: 23160000 | C17: Immo en cours Alarobia | D17: 1.3951661e+08 | G17: 23160000
B18: 23170000 | C18: Immo en cours Tamatave | D18: 4.4166799e+08 | G18: 23170000
B19: 23190000 | C19: Immo en cours Ford Dauphin | D19: 1661495 | G19: 23190000
A20: 230000 | B20: 23000000 | C20: Immo en cours | D20: 6.3276286e+09 | E20: 6.0768375e+09 | F20: 0 | G20: 23200000
A21: 231000 | B21: 23100000 | C21: Immo. corporelles en cours | D21: 1.7163699e+09 | E21: 1664191.2 | F21: 0 | G21: 23200000
A22: 231100 | B22: 23110000 | C22: Immo en cours RéhabilitatioMantasoa | D22: 1.5315954e+08 | E22: 32494477 | F22: 0 | G22: 23200000
A23: 231300 | B23: 23130000 | C23: Immo en cours Mahitsy | D23: 19506500 | E23: 19506500 | F23: 0 | G23: 23200000
B24: 23210000 | C24: Immo en cours-villa MSI Ivandry | D24: 11021337 | G24: 23200000
A25: 281110 | B25: 28111000 | C25: Amort agencement terrain | D25: -53105016 | E25: -35421745 | F25: -29394578 | G25: 28120000
A26: 281300 | B26: 28130000 | C26: Amorts Batiments&Constructions | D26: -4.4607462e+08 | E26: -89395987 | F26: -44697993 | G26: 28130000
A27: 281500 | B27: 28150000 | C27: Amort Agenc Amenag installation | D27: -20937300 | E27: -12730221 | F27: -8021687.4 | G27: 28150000
A28: 281810 | B28: 28181000 | C28: Amort. Matériels & outillages | D28: -1823135.7 | E28: -1139335.1 | F28: -777960.07 | G28: 28154000
A29: 281880 | B29: 28188000 | C29: Amort Materiel&mobilier de logement | D29: -3457918 | E29: -20337.96 | F29: 0 | G29: 28182000
A30: 401100 | B30: 40110000 | C30: Fournisseurs Locaux | D30: -3.4096483e+08 | E30: -3.8834177e+08 | F30: -5.8746546e+08 | G30: 40110000
B31: 40120000 | C31: Fournisseurs ‚trangers | D31: -89116538 | G31: 40120000
B32: 40310000 | C32: F/sseurs effets … payer BMOI | D32: -1242170.7 | G32: 40310000
A33: 404000 | B33: 40400000 | C33: Fournisseurs d'immobilisations | D33: -454000000 | E33: -554000000 | F33: 0 | G33: 40400000
A34: 408000 | B34: 40800000 | C34: F/sseurs fact à recevoir | D34: -5.0870851e+09 | E34: -5019014000 | F34: -7322459.6 | G34: 40810000
A35: 409000 | B35: 40900000 | C35: Avances et acomptes fournisseurs | D35: 10981327 | E35: 0 | F35: 0 | G35: 40910000
A36: 409100 | B36: 40910000 | C36: Frns locaux: avance et acompte | D36: 1.0294216e+09 | E36: 4.4897299e+08 | F36: 64654778 | G36: 40910000
B37: 40920000 | C37: Frns ‚trangers: avances&acpt | D37: 1.3474389e+08 | G37: 40920000
A38: 411000 | B38: 41100000 | C38: Clients | D38: 3.9561555e+08 | E38: 37147316 | F38: 0 | G38: 41100000
A39: 418000 | B39: 41800000 | C39: Produit non encore facturé | D39: 65934380 | E39: 63146435 | F39: 0 | G39: 41810000
A40: 419100 | B40: 41910000 | C40: Clients créditeurs : acomptes | D40: -125000000 | E40: -2000000 | F40: 0 | G40: 41910000
A41: 421100 | B41: 42110000 | C41: Rémunérations dues personnel | D41: -611400.49 | E41: -611400.49 | F41: -815200.49 | G41: 42110000
B42: 42540000 | C42: Tsinjo Fameno | D42: -294999 | G42: 42540000
B43: 42800000 | C43: Cong‚s pay‚s provision | D43: -9713890 | G43: 42800000
A44: 431000 | B44: 43100000 | C44: CNaPS | D44: -2130316.3 | E44: -925181.04 | F44: -701740.06 | G44: 43100000
A45: 432300 | B45: 43230000 | C45: FUNHECE | D45: -780730.1 | E45: -396506.16 | F45: -300745.74 | G45: 43100000
B46: 43200000 | C46: OSTIE | D46: -132262.6 | G46: 43200000
A47: 433000 | B47: 43300000 | C47: FMFP | D47: -152165.45 | E47: -66084.36 | F47: -50124.29 | G47: 43300000
B48: 43820000 | C48: Charges soc. s/Cong‚s … payer | D48: -1748500 | G48: 43300000
A49: 441000 | B49: 44100000 | C49: Etat: IRSA à payer | D49: -62000 | E49: -32000 | F49: -16000 | G49: 44100000
A50: 443000 | B50: 44300000 | C50: Etat : acomptes IR | D50: 43058134 | E50: 599999.99 | F50: 320000 | G50: 44300000
A51: 444000 | B51: 44400000 | C51: Etat à payer: IR | D51: 0 | E51: 0 | F51: -560000 | G51: 44410000
A52: 444100 | B52: 44410000 | C52: Etat : IR Intermittent | D52: -2673704.3 | E52: -684864.94 | F52: 0 | G52: 44411000
A53: 445400 | B53: 44540000 | C53: TVA à décaisser | D53: 0 | E53: 0 | F53: 0 | G53: 44540000
A54: 445500 | B54: 44550000 | C54: Credit de taxe | D54: 6.9738454e+08 | E54: 2026736.3 | F54: 35933589 | G54: 44550000
A55: 445620 | B55: 44562000 | C55: TVA sur Immobilisation | D55: 182163.34 | E55: 1093660 | F55: 0 | G55: 44561000
A56: 445640 | B56: 44564000 | C56: TVA pour les Services | D56: -965295.76 | E56: 508168.64 | F56: 10800 | G56: 44561000
A57: 445650 | B57: 44565000 | C57: TVA pour les Biens | D57: 0 | E57: 199616.62 | F57: 0 | G57: 44561000
A58: 445700 | B58: 44570000 | C58: TVA collectées | D58: 0 | E58: 0 | F58: 0 | G58: 44571000
A59: 445720 | B59: 44572000 | C59: TVA relatifs aux op locales | D59: -56469133 | E59: -23576288 | F59: 0 | G59: 44571000
A60: 445760 | B60: 44576000 | C60: TVA sur refacturation | D60: 0 | E60: 52454.52 | F60: 0 | G60: 44571000
... A63: 455110 | B63: 45511000 | C63: C/C des Associés | D63: 0 | E63: -3.0145576e+08 | F63: -1.1089658e+09 | G63: 45500000
B64: 45520000 | C64: C/C DANIL ISMAEL | D64: -2.0549538e+09 | G64: 45520000
B65: 45530000 | C65: C/C SHERALY MINAZE | D65: -82500000 | G65: 45530000
B66: 45540000 | C66: C/C ISMAEL SHAIMA | D66: -227500000 | G66: 45540000
B67: 45550000 | C67: C/C ISMAEL SHAHIM | D67: -327500000 | G67: 45550000
B68: 45560000 | C68: C/C ISMAEL YANISH | D68: -76232553 | G68: 45550000
A69: 466000 | B69: 46600000 | C69: Debiteurs & crediteurs divers | D69: 12408190 | E69: 9175000 | F69: 56813800 | G69: 46600000
A70: 466100 | B70: 46610000 | C70: AGRIFARM REFACTURATION | D70: -3.0760922e+08 | E70: -32640 | F70: 0 | G70: 46610000
A71: 466100 | B71: 46610000 | C71: FLY TECH REFACTURATION | E71: -1.6741994e+08 | F71: 0 | G71: 46619000
A72: 466100 | B72: 46610000 | C72: IDF REFACTURATION | E72: -1.4641216e+08 | F72: 0 | G72: 46621000
A73: 466100 | B73: 46610000 | C73: SMTP REFACTURATION | E73: -7971037.2 | F73: 0 | G73: 46634000
A74: 467100 | B74: 46710000 | C74: AGRIVET | D74: 0 | F74: -50000000 | G74: 46711000
A75: 467000 | B75: 46700000 | C75: AGRIFARM PRET | D75: -79000000 | E75: -250000000 | F75: 0 | G75: 46720000
A76: 467000 | B76: 46700000 | C76: RCM PRET | E76: 50000000 | F76: 0 | G76: 46726000
B77: 46800000 | C77: AGRIMOTORS REFACTURATION | D77: -54906450 | G77: 46800000
B78: 46800000 | C78: IDM REFACTURATION | G78: 46800000
B79: 46800000 | C79: FLY TECH REFACTURATION | G79: 46800000
B80: 46800000 | C80: MCM REFACTURATION | G80: 46800000
B81: 46800000 | C81: IDF REFACTURATION | G81: 46800000
B82: 46800000 | C82: INVISO REFACTURATION | G82: 46800000
A83: 471000 | B83: 47100000 | C83: Compte d'attente | D83: 883000 | E83: 0 | F83: 0 | G83: 47100000
B84: 48700000 | C84: Produits constat‚s d'avance | D84: -1125000000 | G84: 48700000
A85: 511100 | B85: 51110000 | C85: Chèques à encaisser | D85: 16451712 | E85: 0 | F85: 0 | G85: 51110000
A86: 511400 | B86: 51140000 | C86: Virement- Chq- Versement reçus | D86: 10299770 | E86: 0 | F86: 0 | G86: 51110000
B87: 51127000 | C87: ChŠques emis | D87: -1.2689878e+08 | G87: 51110000
A88: 512110 | B88: 51211000 | C88: Banque BMOI Ariary | D88: 40788521 | E88: 45214747 | F88: 35282021 | G88: 51211000
B89: 51221000 | C89: Banque BFV Ariary | D89: 92313214 | G89: 51221000
B90: 51800000 | C90: Int‚rˆts courus | D90: -1298528.9 | G90: 51800000
A91: 530000 | B91: 53000000 | C91: Caisse La city | D91: 2764397.4 | E91: 3434346 | F91: 0 | G91: 53100000
A92: 531000 | B92: 53100000 | C92: Caisse Ambohibao | D92: -21.2 | E92: 38203.8 | F92: 931.8 | G92: 53100000
B93: 53500000 | C93: CAISSE DEPENSE | D93: 1891619.5 | G93: 53500000
A94: 580000 | B94: 58000000 | C94: Virements internes | D94: 0 | E94: 0 | F94: 0 | G94: 58000000
B95: 60204000 | C95: Petit outillage immobilier | D95: 9027749.6 | G95: 60204000
A96: 606010 | B96: 60601000 | C96: Eau & électricité | D96: 41837306 | E96: 7557244.1 | F96: 441079.2 | G96: 60600000
A97: 606020 | B97: 60602000 | C97: Carburants pour vehicules | D97: 20817 | E97: 306000 | F97: 51000 | G97: 60600000
A98: 606050 | B98: 60605000 | C98: Petit outillage | D98: 36047017 | E98: 3967629.9 | F98: 405000 | G98: 60600000
A99: 606080 | B99: 60608000 | C99: Fournitures de bureau | D99: 1412310.3 | E99: 27500 | F99: 0 | G99: 60600000
A100: 606090 | B100: 60609000 | C100: Autres charges | D100: 520550 | E100: 178804 | F100: 0 | G100: 60600000
B101: 60604000 | C101: Carburant chaudiŠre | D101: 510654 | G101: 60604000
B102: 60606000 | C102: Produits d'hygiene et m‚nages | D102: 205116 | G102: 60606000
...

Sheet SCI NOAH
D2: 2021 | E2: 2020 | F2: EF CONSO 2019 | G2: Compte de gestion | I2: 2019
B3: 10100000 | C3: CAPITAL | D3: -17000000 | E3: -2000000 | F3: -2000000 | G3: 10100000 | I3: -2000000
B4: 11900000 | C4: RAN DEBITEUR | D4: 17263181 | E4: 17263181 | F4: 6906485.2 | G4: 11900000 | I4: 6906485.2
B5: 12900000 | C5: RESULTAT NET DE L'EXERCICE PERTE | D5: 28789451 | G5: 12900000 | M5: 0
B6: 21100000 | C6: TERRAIN | D6: 145000000 | E6: 145000000 | F6: 0 | G6: 21100000 | I6: 0
B7: 23100000 | C7: IMMO EN COURS BYPASS | D7: 7.1506008e+08 | E7: 6.5780068e+08 | F7: 5.8558467e+08 | G7: 23200000 | I7: 5.8558467e+08
B8: 23200000 | C8: POZZOLAN II-III | D8: 88685000 | E8: 88685000 | F8: 88685000 | G8: 23200000 | I8: 88685000
B9: 23300000 | C9: POZZOLAN IV-V | D9: 145536950 | E9: 145536950 | F9: 145536950 | G9: 23200000 | I9: 145536950
B10: 40100000 | C10: COLLECTIFS FOURNISSEURS | D10: -4254000 | E10: 0 | F10: -2275230 | G10: 40110000 | I10: -2275230
B11: 40340000 | C11: F/SSEURS EFFETS À PAYER BNI | D11: -14285025 | G11: 40340000
B12: 40400000 | C12: F/SSEURS D'IMMOBILISATIONS | D12: -117658750 | E12: -1.9537247e+08 | F12: -2.0179378e+08 | G12: 40400000 | I12: -2.0179378e+08
B13: 40800000 | C13: F/SSEURS FACT À RECEVOIR | D13: -280896 | G13: 40800000 | M13: 28813251 | N13: 23800
B14: 40900000 | C14: FOURNS:ACPTE RECU | D14: 15104000 | G14: 40900000
B15: 42100000 | C15: RÉMUNÉRATIONS DUES AU PERSONNEL | D15: 1044239.8 | F15: -1072849.4 | G15: 42110000 | I15: -1072849.4
B16: 43100000 | C16: CNAPS | D16: -709243.08 | E16: -1403457.4 | F16: -719482.68 | G16: 43100000 | I16: -719482.68
B17: 43110000 | C17: CNAPS ALLOCAT° FAMILIALES | D17: -48000 | G17: 43110000
B18: 43200000 | C18: OSTIE | D18: -303961.32 | E18: -601481.76 | F18: -308349.72 | G18: 43200000 | I18: -308349.72
B19: 43300000 | C19: FMFP | D19: -50660.22 | E19: -100246.96 | F19: -51391.62 | G19: 43300000 | I19: -51391.62
B20: 43860000 | C20: ORGANISMES-AUTRES CHARGES A PAYER | D20: -20000 | G20: 43860000
B21: 44100000 | C21: ETAT: IRSA À PAYER | D21: -121000 | E21: -299080 | F21: -153500 | G21: 44100000 | I21: -153500
B22: 44300000 | C22: ETAT: ACOMPTES IR | D22: 320000 | E22: 320000 | F22: 320000 | G22: 44300000 | I22: 320000
B23: 44410000 | C23: IR IMPOTS SUR LES RESULTATS | D23: -16000 | E23: -320000 | F23: -320000 | G23: 44400000 | I23: 0
B24: 44550000 | C24: CREDIT DE TAXE | D24: 23174027 | E24: 20426267 | F24: 134913.33 | G24: 44550000 | I24: 134913.33
B25: 44562000 | C25: TVA pour les Biens | D25: 0 | E25: 0 | F25: 18000 | G25: 44561000 | I25: 18000
B26: 44564000 | C26: TVA pour les Services | D26: 0 | E26: 2700000 | F26: 3066.66 | G26: 44561000 | I26: 3066.66
B27: 44565000 | C27: TVA pour l'Immobilisation | D27: 1890000 | F27: 14004505 | G27: 44561000 | I27: 14004505
B28: 45511000 | C28: C/C ISMAEL DANIL HOUSSEN | D28: -964805600 | E28: -787905600 | F28: -642905600 | G28: 45500001 | I28: -642905600
B29: 45512000 | C29: C/C ISMAEL SHAHIM | D29: -56800000 | E29: -56800000 | F29: 0 | G29: 45500002 | I29: 0
B30: 45513000 | C30: C/C ISMAEL YANISH | D30: -53300000 | E30: -53300000 | F30: 0 | G30: 45500003 | I30: 0
B31: 46610000 | C31: DEBIT ET CRED DIVERS REFACTURATION | D31: 130000 | G31: 46610000
B32: 46710070 | C32: SMTP | D32: -3750000 | E32: -7240600 | F32: -3750000 | G32: 46715000 | I32: -3750000
B33: 46720072 | C33: AGRIVET | D33: -1000000 | E33: -1000000 | F33: -1000000 | G33: 46711000 | I33: -1000000
B34: 51241000 | C34: BNI Ariary | D34: 13400825 | E34: -743894.81 | F34: 4792092.9 | G34: 51241000 | I34: 4792092.9
B35: 53100000 | C35: CAISSE AMBOHIBAO | D35: 0 | E35: 565300 | F35: 7800 | G35: 53100000 | I35: 7800
B36: 53200000 | C36: Caisse dépense | D36: 300100 | G36: 53200000
B37: 58000000 | C37: VIREMENTS INTERNES | D37: -20 | G37: 58000000
B38: 60602000 | C38: CARBURANTS POUR VEHICULES | D38: 0 | E38: 35000 | F38: 0 | G38: 60600000 | I38: 0
B39: 60605000 | C39: Petit outillage | D39: 77000 | E39: 155500 | F39: 670650 | G39: 60600000 | I39: 670650
B40: 60608000 | C40: FOURNITURE DE BUREAU | D40: 0 | E40: 27500 | F40: 0 | G40: 60600000 | I40: 0
B41: 60609000 | C41: Autres charges | D41: -32000 | G41: 60609000
B42: 61302000 | C42: LOCATIONS MOBILIERS | D42: 2609000 | G42: 61302000
B43: 61501000 | C43: ERM IMMOBILIERES | D43: 255600 | G43: 61501000
B44: 61503000 | C44: ERM VEHICULES | D44: -98000 | G44: 61503000
B45: 61604000 | C45: Autres polices d'assurances | D45: 280896 | G45: 61604000
B46: 61802000 | C46: Documentations | D46: 176000 | E46: 92000 | F46: 0 | G46: 61800000 | I46: 0
B47: 62100000 | C47: Prestations de services | D47: 898000 | F47: 80000 | G47: 62100000 | I47: 80000
B48: 62201000 | C48: AUTRES HONORAIRES | D48: 0 | E48: 18750000 | F48: 0 | G48: 62200000 | I48: 0
B49: 62501000 | C49: MISSIONS & DEPLACEMENTS | D49: 0 | E49: 3483933.3 | F49: 0 | G49: 62501000 | I49: 0
B50: 62505000 | C50: Hergement , hotel | D50: 157020 | G50: 62505000
B51: 62506000 | C51: FRAIS DE DEPLACEMENT EN VILLE | D51: 118000 | E51: 0 | F51: 300000 | G51: 62501000 | I51: 300000
B52: 62507000 | C52: collation du personnel | D52: 187900 | E52: 19000 | F52: 0 | G52: 62501000 | I52: 0
B53: 62703000 | C53: Frais bancaires | D53: 126400 | E53: 280666.71 | F53: 174000.01 | G53: 62701000 | I53: 174000.01
B54: 62709000 | C54: CI modification | D54: 247800 | G54: 62709000
B55: 63502000 | C55: TAXES FONCIÈRES | D55: 0 | F55: 11500 | G55: 63502000 | I55: 11500
B56: 63504000 | C56: AUTRES TAXES | D56: 301500 | E56: 93500 | F56: 300000 | G56: 63504000 | I56: 300000
B57: 64101000 | C57: SALAIRES & APPOINTEMENTS | D57: 24941088 | E57: 31242113 | F57: 4884105.3 | G57: 64101000 | I57: 4884105.3
B58: 64102000 | C58: INDEMNITE DIVERSES | D58: 1366000 | E58: 1110000 | F58: 156333.33 | G58: 64101000 | I58: 156333.33
B59: 64103000 | C59: PRIMES DIVERSES | D59: 0 | E59: 2438674.2 | F59: 0 | G59: 64101000 | I59: 0
B60: 64105000 | C60: CONGÉS PAYES | D60: 1096620 | F60: 98722.86 | G60: 64101000 | I60: 98722.86
B61: 64501000 | C61: COT PATRONALE CNAPS | D61: 3562482 | E61: 4522801.9 | F61: 668091.06 | G61: 64501000 | I61: 668091.06
B62: 64502000 | C62: COT PATRONALE OSTIE | D62: 1370185.4 | E62: 1739539.2 | F62: 256958.1 | G62: 64501000 | I62: 256958.1
B63: 64504000 | C63: FMFP Patronale | D63: 274037.08 | E63: 347907.84 | F63: 51391.62 | G63: 64501000 | I63: 51391.62
B64: 65700000 | C64: Autres charges de gestion courante | D64: 0 | E64: 0.41 | F64: 244150 | G64: 65700000 | I64: 244150
B65: 65800000 | C65: Charges non déductibles | D65: 167999.99 | F65: 1787900 | G65: 65700000 | I65: 1787900
B66: 66102000 | C66: Interet bancaires/ agios | D66: 645772.1 | E66: 512463.47 | F66: 1833043.1 | G66: 66100000 | I66: 1833043.1
B67: 69800000 | C67: Autres impôts sur les résultats | D67: 16000 | E67: 320000 | F67: 320000 | G67: 69800000 | I67: 0
B68: 75800000 | C68: Autres produits de gestion courante | D68: 0 | E68: -89049.98 | F68: 0 | G68: 75800000 | I68: 0
B69: 75810000 | C69: TICKETS CANTINE | D69: -40000 | G69: 75810000
B70: 77200000 | C70: Production immobilisée | D70: 0 | E70: -36292100 | F70: -1480150 | G70: 72100000 | I70: -1480150

Sheet SIM
A1: Compte | B1: Libellé | C1: 2021 | D1: 2020 | E1: EF CONSO 2019 | F1: Gestion | H1: 2019
A2: 10100000 | B2: Capital | C2: -2000000 | D2: -2000000 | E2: -2000000 | F2: 10100000 | H2: -2000000
A3: 10610000 | B3: Reserves légales | C3: -200000 | D3: -200000 | E3: -200000 | F3: 10610000 | H3: -200000
A4: 11000000 | B4: RAN crediteur | C4: -6.3567628e+08 | D4: -6.3567628e+08 | E4: -2.3620647e+08 | F4: 11000000 | H4: -2.3620647e+08
A5: 12000000 | B5: Resultat net de l'exercice benefice | C5: 0 | D5: 0 | E5: 0 | F5: 12000000 | H5: 0
A6: 16440000 | B6: EMPRUNT BFV | C6: -1.4228853e+09 | D6: -1.4228853e+09 | E6: -1.7526203e+09 | F6: 16120000 | H6: -1.7526203e+09
A7: 16500000 | B7: Depots et cautionnements re | C7: -44488766 | D7: -44488766 | E7: -43090321 | F7: 16500000 | H7: -43090321
A8: 21100000 | B8: Terrains | C8: 1206360000 | D8: 1206360000 | E8: 1206360000 | F8: 21100000 | H8: 1206360000
A9: 21310000 | B9: Batiments et constructions | C9: 4.8409064e+09 | D9: 4.8409064e+09 | E9: 4.8409064e+09 | F9: 21300000 | H9: 4.8409064e+09
A10: 21500000 | B10: AAI batiments | C10: 6.351237e+08 | D10: 6.351237e+08 | E10: 5.4302178e+08 | F10: 21500000 | H10: 5.4302178e+08
A11: 21810000 | B11: Matériels & outillages | C11: 1.2789837e+08 | D11: 1.2789837e+08 | E11: 1.2789837e+08 | F11: 21540000 | H11: 1.2789837e+08
A12: 21820000 | B12: MMB | C12: 1793333.3 | D12: 1793333.3 | E12: 0 | F12: 21820000 | H12: 0
A13: 21830000 | B13: Materiel de transport | C13: 70310075 | D13: 70310075 | E13: 70310075 | F13: 21830000 | H13: 70310075
... A56: 46610000 | B56: FLY TECHNOLOGIES | C56: 0 | D56: 0 | E56: 0 | F56: 46619000 | H56: 0
A57: 46700000 | B57: Créances intra groupe | C57: 0 | D57: 0 | E57: 0 | F57: #N/A | H57: 0
A58: 46710000 | B58: ABDOUL KADODIA | C58: 0 | D58: 0 | E58: -17407814 | F58: 46600000 | H58: -17407814
A59: 46710010 | B59: IDF | C59: -395000000 | D59: -395000000 | E59: -695000000 | F59: 46719000 | H59: -695000000
A60: 46710102 | B60: NMP | C60: 0 | D60: 0 | E60: -296476.64 | F60: 46718000 | H60: -296476.64
A61: 46720070 | B61: SMTP | C61: -2673736.5 | D61: -2673736.5 | E61: -2334421.9 | F61: 46715000 | H61: -2334421.9
A62: 46720800 | B62: AGRIFARM | C62: -20400 | D62: -20400 | E62: -27000 | F62: 46610000 | H62: -27000
A63: 46720900 | B63: IRS IMMO | C63: 39541000 | D63: 39541000 | E63: 0 | F63: 46743000 | H63: 0
A64: 47100000 | B64: Compte d'attente | C64: 0 | D64: 0 | E64: 0 | F64: 47100000 | H64: 0
A65: 48600000 | B65: Charges constatées d'avance | C65: 4857654.1 | D65: 4857654.1 | E65: 7216460 | F65: 48600000 | H65: 7216460
A66: 48700000 | B66: PRODUIT CONSTATE D'AVANCE | C66: -26400000 | D66: -26400000 | E66: -17760000 | F66: 48700000 | H66: -17760000
A67: 49100000 | B67: Pertes de valeur/cptes clients | C67: -2500000 | D67: -2500000 | E67: -2500000 | F67: 49100000 | H67: -2500000
A68: 51110000 | B68: Chèque à encaisser | C68: 0 | D68: 0 | E68: 0 | F68: 51110000 | H68: 0
A69: 51140000 | B69: Virement- Chq- Versment reçus | C69: -450700 | D69: -450700 | E69: 0 | F69: 51110000 | H69: 0
... A74: 58000000 | B74: Virements internes | C74: 0 | D74: 0 | E74: 0 | F74: 58000000 | H74: 0
A75: 60400000 | B75: Achats études et prestation de sce | C75: 0 | D75: 0 | E75: 0 | F75: #N/A | H75: 0
A76: 60601000 | B76: Eau & électricité | C76: 11811640 | D76: 11811640 | E76: 12550897 | F76: 60600000 | H76: 12550897
A77: 60602000 | B77: Carburants pour vehicules | C77: 3304000 | D77: 3304000 | E77: 77000 | F77: 60600000 | H77: 77000
A78: 60603000 | B78: Carburant Gpe Electrogène | C78: 0 | D78: 0 | E78: 6020300 | F78: 60600000 | H78: 6020300
A79: 60604000 | B79: Produits d'hygiene et ménages | C79: 2179643.9 | D79: 2179643.9 | E79: 637141 | F79: 60600000 | H79: 637141
A80: 60605000 | B80: Petit outillage | C80: 11388983 | D80: 11388983 | E80: 2663135.2 | F80: 60600000 | H80: 2663135.2
A81: 60607000 | B81: Fournitures informatiques | C81: 87000 | D81: 87000 | E81: 617133.33 | F81: 60600000 | H81: 617133.33
A82: 60608000 | B82: Fournitures de bureau | C82: 526270 | D82: 526270 | E82: 355890 | F82: 60600000 | H82: 355890
A83: 60609000 | B83: Achats autres matières et fournitur | C83: 135000 | D83: 135000 | E83: 136250 | F83: 60600000 | H83: 136250
A84: 60900000 | B84: RRR obtenus | E84: -122000 | F84: 60900000 | H84: -122000
A85: 60801000 | B85: Fret | C85: 8285265 | D85: 8285265 | E85: 0 | F85: 60800000 | H85: 0
A86: 60802000 | B86: Assurance | C86: 114459 | D86: 114459 | E86: 0 | F86: 60800000 | H86: 0
A87: 60803000 | B87: Honoraires transitaire | C87: 80000 | D87: 80000 | E87: 0 | F87: 60800000 | H87: 0
A88: 60804000 | B88: Divers frais de transit | C88: 2408093.1 | D88: 2408093.1 | E88: 0 | F88: 60800000 | H88: 0
A89: 60811000 | B89: Droits de douane | C89: 9646870 | D89: 9646870 | E89: 0 | F89: 60800000 | H89: 0
A90: 60811100 | B90: Divers frais Douane | C90: 829405 | D90: 829405 | E90: 0 | F90: 60800000 | H90: 0
A91: 60812000 | B91: Gasy Net | C91: 324444 | D91: 324444 | E91: 0 | F91: 60800000 | H91: 0
A92: 61302000 | B92: Locations mobilières | C92: 240000 | D92: 240000 | E92: 1320000 | F92: 61300000 | H92: 1320000
A93: 61500000 | B93: Autres entretiens et réparations po | C93: 0 | D93: 0 | E93: 123000 | F93: 61500000 | H93: 123000
A94: 61501000 | B94: ERM Immobilieres | C94: 17146904 | D94: 17146904 | E94: 32735300 | F94: 61500000 | H94: 32735300
A95: 61501700 | B95: ERM LA CITY | C95: 0 | D95: 0 | E95: 9420850 | F95: 61500000 | H95: 9420850
A96: 61502000 | B96: ERM bureautique & informatique | C96: 60000 | D96: 60000 | E96: 0 | F96: 61500000 | H96: 0
... A107: 62303000 | B107: Support publicitaires | C107: 3373000 | D107: 3373000 | E107: 3461000 | F107: 62300000 | H107: 3461000
A108: 62304000 | B108: Foires & expositions | E108: 2007000 | F108: 62300000 | H108: 2007000
A109: 62401000 | B109: Transport sur achats | C109: 50000 | D109: 50000 | E109: 1000000 | F109: 62401000 | H109: 1000000
A110: 62504000 | B110: Réceptions | C110: 0 | D110: 0 | E110: 0 | F110: 62501000 | H110: 0
A111: 62506000 | B111: Frais de deplacement en ville | C111: 121000 | D111: 121000 | E111: 206018 | F111: 62501000 | H111: 206018
A112: 62507000 | B112: Collation du personnel | C112: 293000 | D112: 293000 | E112: 178896 | F112: 62501000 | H112: 178896
A113: 62602000 | B113: Telephone mobile | C113: 855475.56 | D113: 855475.56 | E113: 829460.25 | F113: 62601000 | H113: 829460.25
A114: 62603000 | B114: Internet | C114: 320000 | D114: 320000 | E114: 390000 | F114: 62601000 | H114: 390000
A115: 62604000 | B115: Envoi colis | C115: 828200 | D115: 828200 | E115: 407300 | F115: 62601000 | H115: 407300
A116: 62606000 | B116: Abonnement Télésurveillance | C116: 1200000 | D116: 1200000 | E116: 0 | F116: 62601000 | H116: 0
A117: 62703000 | B117: Commissions diverses banques | C117: 678022.38 | D117: 678022.38 | E117: 290154.2 | F117: 62701000 | H117: 290154.2
A118: 62704000 | B118: Frais de tenu de compte | C118: 40000 | D118: 40000 | E118: 60000 | F118: 62701000 | H118: 60000
A119: 62706000 | B119: CI transfert change | C119: 539550.07 | D119: 539550.07 | E119: 0 | F119: 62701000 | H119: 0
A120: 62707000 | B120: Commission de mouvement | C120: 572339.78 | D120: 572339.78 | E120: 796291.53 | F120: 62701000 | H120: 796291.53
... A123: 63501000 | B123: Certification-Légalisation | C123: 17000 | D123: 17000 | E123: 51700 | F123: 63501000 | H123: 51700
A124: 63502000 | B124: Taxes foncières | E124: 59736 | F124: 63502000 | H124: 59736
A125: 63504000 | B125: Autres taxes | C125: 6000 | D125: 6000 | E125: 12000 | F125: 63504000 | H125: 12000
A126: 63506000 | B126: Droit d'enregistrement | C126: 2000 | D126: 2000 | E126: 10000 | F126: 63506000 | H126: 10000
A127: 64101000 | B127: Salaires & appointements | C127: 36251898 | D127: 36251898 | E127: 32389075 | F127: 64101000 | H127: 32389075
A128: 64101300 | B128: Salaires Temporaires | C128: 90000 | D128: 90000 | E128: 0 | F128: 64101000 | H128: 0
A129: 64102000 | B129: Indemnite diverses | C129: 220000 | D129: 220000 | E129: 240000 | F129: 64101000 | H129: 240000
A130: 64103000 | B130: Primes diverses | C130: 3433873.7 | D130: 3433873.7 | E130: 2538383.7 | F130: 64101000 | H130: 2538383.7
A131: 64104000 | B131: Heures supp | C131: 71451.2 | D131: 71451.2 | E131: 0 | F131: 64101000 | H131: 0
A132: 64105000 | B132: Congés payes | E132: 600000.3 | F132: 64101000 | H132: 600000.3
A133: 64180000 | B133: Prov congés payés | C133: 2178427.5 | D133: 2178427.5 | E133: 2442971.7 | F133: 64101000 | H133: 2442971.7
A134: 64501000 | B134: CNaPS | C134: 4788051.8 | D134: 4788051.8 | E134: 4089960.5 | F134: 64501000 | H134: 4089960.5
A135: 64502000 | B135: FUNECHE | C135: 1841558.4 | D135: 1841558.4 | E135: 1600837.2 | F135: 64501000 | H135: 1600837.2
A136: 64503000 | B136: COT PATR FMFP | C136: 368311.68 | D136: 368311.68 | E136: 286837.03 | F136: 64501000 | H136: 286837.03
A137: 64504000 | B137: Charge patronal OSTIE | C137: 0 | D137: 0 | E137: 0 | F137: 64501000 | H137: 0
A138: 64580000 | B138: Organisme charges à payés | C138: 307404.01 | D138: 307404.01 | E138: 92625.2 | F138: 64501000 | H138: 92625.2
A139: 64801000 | B139: Habillement du personnel | C139: 162500 | D139: 162500 | E139: 996.02 | F139: 64801000 | H139: 0
A140: 65100000 | B140: Rédevences brevet-licences | C140: 4231344.3 | D140: 4231344.3 | E140: 0 | F140: 65100000 | H140: 0
A141: 65602000 | B141: Dons & liberalités | C141: 50000 | D141: 50000 | E141: 0 | F141: 65602000 | H141: 0
A142: 65700000 | B142: Charges except° de gestion courante | C142: 1132142.4 | D142: 1132142.4 | E142: 0 | F142: 65700000 | H142: 996.02
A143: 66101000 | B143: Interet sur escompte | C143: 9864552.8 | D143: 9864552.8 | E143: 0 | F143: 66100000 | H143: 0
A144: 66102000 | B144: Interet bancaires/ agios | C144: 546551.87 | D144: 546551.87 | E144: 0 | F144: 66100000 | H144: 0
... A147: 68112000 | B147: Dot.amort immob corporelles | C147: 3.1455254e+08 | D147: 3.1455254e+08 | E147: 3.2545859e+08 | F147: 68112000 | H147: 3.2545859e+08
A148: 68500000 | B148: Dotations actifs courants | E148: 2500000 | F148: 68500000 | H148: 2500000
A149: 69500000 | B149: Impôts sur les bénéfices | E149: 99867452 | F149: 69800000 | H149: 99867452
A150: 69800000 | B150: Autres impôts sur le résultat | C150: 0 | D150: 0 | E150: 0 | F150: 69800000 | H150: 0
A151: 70600000 | B151: Locations Baobab city | C151: -1.0293544e+09 | D151: -1.0293544e+09 | E151: -1.0732108e+09 | F151: 70600000 | H151: -1.0732108e+09
A152: 70810000 | B152: Refacturation charges communes | C152: -76264285 | D152: -76264285 | E152: 0 | F152: 70800000 | H152: 0
A153: 75800000 | B153: Autres produits de gestion courante | C153: -20859848 | D153: -20859848 | E153: -2070654.2 | F153: 75800000 | H153: -2070654.2
A154: 75820000 | B154: Refacturation charges communes | C154: -15503916 | D154: -15503916 | E154: -88745733 | F154: 75800000 | H154: -88745733

Sheet First Energy
C1: 2021 | D1: 2020 | E1: 2019 | I1: EF CONSO 2019
A2: COMPTE | B2: LIBELLES | C2: =+SUBTOTAL(9,C3:C283) -> 4.5231936e-07 | D2: =+SUBTOTAL(9,D3:D283) -> 0 | E2: =+SUBTOTAL(9,E3:E283) -> 0 | I2: =+SUBTOTAL(9,I3:I283) -> -1.2382279e-06
A3: 10100000 | B3: Capital | C3: -2000000 | D3: -2000000 | E3: -2000000 | F3: 10100000 | G3: =+LEFT(F3) -> 1 | H3: =+LEFT(F3,3) -> 101 | I3: -2000000
A4: 10610000 | B4: Reserves légales | C4: -200000 | D4: -200000 | E4: -200000 | F4: 10610000 | G4: =+LEFT(F4) -> 1 | H4: =+LEFT(F4,3) -> 106 | I4: -200000
A5: 11000000 | B5: RAN crediteur | C5: -7.9534521e+09 | D5: -8.4378739e+09 | E5: -7.6359783e+09 | F5: 11000000 | G5: =+LEFT(F5) -> 1 | H5: =+LEFT(F5,3) -> 110 | I5: -5.7639056e+09
A6: 12000000 | B6: Resultat net de l'exercice benefice | C6: 0 | D6: -0.0043087006 | E6: 0.0050001144 | F6: 12000000 | G6: =+LEFT(F6) -> 1 | H6: =+LEFT(F6,3) -> 120 | I6: -1.8720727e+09
A7: 16200000 | B7: Emprunts LMT BNI | C7: -3.3540253e+08 | D7: -5.7255806e+08 | E7: -7.8511713e+08 | F7: 16200000 | G7: =+LEFT(F7) -> 1 | H7: =+LEFT(F7,3) -> 162 | I7: -8.0135683e+08
A8: 16440000 | B8: Emprunt BFV | C8: -4.7688851e+08 | D8: -6.9937012e+08 | E8: -8.6703987e+08 | F8: 16440000 | G8: =+LEFT(F8) -> 1 | H8: =+LEFT(F8,3) -> 164 | I8: -8.6495865e+08
A9: 16885000 | B9: Intérêts courus sur emprunts | C9: 0 | D9: 0 | E9: 0 | F9: 16885000 | G9: =+LEFT(F9) -> 1 | H9: =+LEFT(F9,3) -> 168
A10: 20400000 | B10: Logiciels informatiques & assimilés | C10: 4832320.4 | D10: 4832320.4 | E10: 4832320.4 | F10: 20400000 | G10: =+LEFT(F10) -> 2 | H10: =+LEFT(F10,3) -> 204 | I10: 4832320.4
A11: 21100000 | B11: Terrains | C11: 87050320 | D11: 87050320 | E11: 87050320 | F11: 21100000 | G11: =+LEFT(F11) -> 2 | H11: =+LEFT(F11,3) -> 211 | I11: 87050320
A12: 21200000 | B12: Agencement amenagement terrain | C12: 5757579 | D12: 5757579 | E12: 5757579 | F12: 21200000 | G12: =+LEFT(F12) -> 2 | H12: =+LEFT(F12,3) -> 212 | I12: 5757579
A13: 21300000 | B13: Batiments et constructions | C13: 8.2233486e+08 | D13: 8.2233486e+08 | E13: 0 | F13: 21300000 | G13: =+LEFT(F13) -> 2 | H13: =+LEFT(F13,3) -> 213 | I13: 3.0137553e+09
A14: 21310000 | B14: Agencement amenagement Construction | C14: 1.638953e+08 | D14: 4.7490055e+08 | E14: 3.6369656e+08 | F14: 21310000 | G14: =+LEFT(F14) -> 2 | H14: =+LEFT(F14,3) -> 213 | I14: 3.6369656e+08
A15: 21500000 | B15: Installations techniques | C15: 1.3898304e+09 | D15: 8121930 | E15: 0 | F15: 21500000 | G15: =+LEFT(F15) -> 2 | H15: =+LEFT(F15,3) -> 215
A16: 21510000 | B16: Parks groupes éléctrogènes | C16: 5.0914946e+09 | D16: 4.8261378e+09 | E16: 4.7989619e+09 | F16: 21510000 | G16: =+LEFT(F16) -> 2 | H16: =+LEFT(F16,3) -> 215 | I16: 4.8264321e+09
A17: 21520000 | B17: Accessoires Groupes | C17: 8.38705e+08 | D17: 6.6855374e+08 | E17: 6.5085469e+08 | F17: 21520000 | G17: =+LEFT(F17) -> 2 | H17: =+LEFT(F17,3) -> 215 | I17: 6.5085469e+08
A18: 21530000 | B18: Central solaire | C18: 5.6639361e+09 | D18: 1.0611947e+10 | E18: 5.8367272e+09 | F18: 21530000 | G18: =+LEFT(F18) -> 2 | H18: =+LEFT(F18,3) -> 215 | I18: 2.8229718e+09
A19: 21800000 | B19: Autres immo corp(materiel+o) | C19: 30223951 | D19: 30223951 | E19: 0 | F19: 21800000 | G19: =+LEFT(F19) -> 2 | H19: =+LEFT(F19,3) -> 218
A20: 21810000 | B20: Matériels & outillages | C20: 3.7694557e+08 | D20: 3.6679841e+08 | E20: 3.6679841e+08 | F20: 21810000 | G20: =+LEFT(F20) -> 2 | H20: =+LEFT(F20,3) -> 218 | I20: 3.6679841e+08
A21: 21820000 | B21: MMB | C21: 8826515.9 | D21: 8826515.9 | E21: 8826515.9 | F21: 21820000 | G21: =+LEFT(F21) -> 2 | H21: =+LEFT(F21,3) -> 218 | I21: 8826515.9
A22: 21830000 | B22: Materiel de transport | C22: 945406539 | D22: 9.4540654e+08 | E22: 9.4540654e+08 | F22: 21830000 | G22: =+LEFT(F22) -> 2 | H22: =+LEFT(F22,3) -> 218 | I22: 1.2287399e+09
A23: 21840000 | B23: Matériel informatiques | C23: 40576863 | D23: 35645649 | E23: 33263244 | F23: 21840000 | G23: =+LEFT(F23) -> 2 | H23: =+LEFT(F23,3) -> 218 | I23: 33263244
A24: 21850000 | B24: Materiel & mobilier de logement | C24: 19538125 | D24: 18977500 | E24: 1070000 | F24: 21850000 | G24: =+LEFT(F24) -> 2 | H24: =+LEFT(F24,3) -> 218 | I24: 1070000
A25: 21860000 | B25: GROS PIECES AUTOS | C25: 0 | D25: 5035552 | E25: 0 | F25: 21860000 | G25: =+LEFT(F25) -> 2 | H25: =+LEFT(F25,3) -> 218
A26: 23000000 | B26: immo en cours MAEVANTANANA | C26: -1000000 | D26: 0 | E26: 4.5623798e+09 | F26: 23000000 | G26: =+LEFT(F26) -> 2 | H26: =+LEFT(F26,3) -> 230 | I26: 5.2169793e+09
A27: 23130000 | B27: Autres Immo en cours | C27: 8.3579672e+08 | D27: 880600 | E27: 0 | F27: 23130000 | G27: =+LEFT(F27) -> 2 | H27: =+LEFT(F27,3) -> 231
A28: 23140000 | B28: Immo en cours Central | C28: 4974366.7 | F28: 23140000
A29: 23160000 | B29: Immo en cours Mampikony | C29: 1.7727896e+09 | D29: 6.2255883e+08 | E29: 2.2524552e+08 | F29: 23160000 | G29: =+LEFT(F29) -> 2 | H29: =+LEFT(F29,3) -> 231
A30: 23170000 | B30: Immo en cours Port Bergé | C30: 1.7774364e+09 | D30: 2.7779062e+08 | E30: 86320926 | F30: 23170000 | G30: =+LEFT(F30) -> 2 | H30: =+LEFT(F30,3) -> 231
A31: 23180000 | B31: Immo en cours Anivorano Nord | C31: 9.680433e+08 | D31: 6527457 | E31: 6527457 | F31: 23180000 | G31: =+LEFT(F31) -> 2 | H31: =+LEFT(F31,3) -> 231
A32: 23190000 | B32: Immo en cours Antsohihy | C32: 10000 | D32: 0 | E32: 3.3650558e+08 | F32: 23190000 | G32: =+LEFT(F32) -> 2 | H32: =+LEFT(F32,3) -> 231
A33: 27500000 | B33: Depot & cautionnements verses | C33: 8350000 | D33: 208631800 | E33: 194231800 | F33: 27500000 | G33: =+LEFT(F33) -> 2 | H33: =+LEFT(F33,3) -> 275 | I33: 194231800
A34: 28040000 | B34: Amts logiciel informatique | C34: -4832320.3 | D34: -3881964 | E34: -2902076.8 | F34: 28040000 | G34: =+LEFT(F34) -> 2 | H34: =+LEFT(F34,3) -> 280 | I34: -2902076.8
A35: 28111000 | B35: Amort agencement terrain | C35: 0 | D35: 0 | E35: 0 | F35: 28111000 | G35: =+LEFT(F35) -> 2 | H35: =+LEFT(F35,3) -> 281
A36: 28120000 | B36: Amts Aménagement terrain | C36: -2590910.5 | D36: -2015152.6 | E36: -1431398.1 | F36: 28120000 | G36: =+LEFT(F36) -> 2 | H36: =+LEFT(F36,3) -> 281 | I36: -1431398.1
A37: 28130000 | B37: Amts batiments et constructions | C37: -47969533 | D37: -95342543 | E37: -43887195 | F37: 28130000 | G37: =+LEFT(F37) -> 2 | H37: =+LEFT(F37,3) -> 281 | I37: -43887195
A38: 28131000 | B38: AGENCEMENT AMENAGEMENTS CONSTRUCTIO | C38: -23055977 | F38: 28131000
A39: 28150000 | B39: Amts Amenagement batiments | C39: -3.0245826e+08 | D39: 0 | E39: 0 | F39: 28150000 | G39: =+LEFT(F39) -> 2 | H39: =+LEFT(F39,3) -> 281 | I39: -3.2649016e+08
A40: 28151000 | B40: Amorts Packs groupes éléctrogènes | C40: -2.6344879e+09 | D40: -2.0422001e+09 | E40: -1.554141e+09 | F40: 28151000 | G40: =+LEFT(F40) -> 2 | H40: =+LEFT(F40,3) -> 281 | I40: -1.5130634e+09
A41: 28152000 | B41: Amorts Accessoires Groupes | C41: -3.5959117e+08 | D41: -2.9131787e+08 | E41: -2.2442789e+08 | F41: 28152000 | G41: =+LEFT(F41) -> 2 | H41: =+LEFT(F41,3) -> 281 | I41: -2.7592134e+08
A42: 28153000 | B42: Amts Central Solaire | C42: -2.1114638e+09 | D42: -1.8797135e+09 | E42: -9.6322715e+08 | F42: 28153000 | G42: =+LEFT(F42) -> 2 | H42: =+LEFT(F42,3) -> 281 | I42: -6.3673698e+08
A43: 28156000 | B43: AMORT INSTALL TECHNIQUE | C43: 0 | D43: -504217.68 | E43: 0 | F43: 28156000 | G43: =+LEFT(F43) -> 2 | H43: =+LEFT(F43,3) -> 281
A44: 28180000 | B44: Autres immo corporelles | C44: -3729331.5 | D44: -706936.44 | E44: 0 | F44: 28180000 | G44: =+LEFT(F44) -> 2 | H44: =+LEFT(F44,3) -> 281
A45: 28181000 | B45: Amts matériels & outillage | C45: -1.9416703e+08 | D45: -1.5680844e+08 | E45: -1.1961915e+08 | F45: 28181000 | G45: =+LEFT(F45) -> 2 | H45: =+LEFT(F45,3) -> 281 | I45: -1.1961915e+08
A46: 28182000 | B46: Amts MMB | C46: -3681091.9 | D46: -2798440.3 | E46: -1903529.6 | F46: 28182000 | G46: =+LEFT(F46) -> 2 | H46: =+LEFT(F46,3) -> 281 | I46: -1903529.6
A47: 28183000 | B47: AMT matériel de transport | C47: -8.8335945e+08 | D47: -8.290286e+08 | E47: -6.8084105e+08 | F47: 28183000 | G47: =+LEFT(F47) -> 2 | H47: =+LEFT(F47,3) -> 281 | I47: -8.8645447e+08
A48: 28184000 | B48: Amts materiel informatique | C48: -31938089 | D48: -25372133 | E48: -17151273 | F48: 28184000 | G48: =+LEFT(F48) -> 2 | H48: =+LEFT(F48,3) -> 281 | I48: -17151273
A49: 28185000 | B49: Amts mat & mob de logt | C49: -3724808 | D49: -1785011.1 | E49: -125130.56 | F49: 28185000 | G49: =+LEFT(F49) -> 2 | H49: =+LEFT(F49,3) -> 281 | I49: -125130.56
A50: 28186000 | B50: AMORT GROS PIECES AUTOS | C50: 0 | D50: -255973.89 | E50: 0 | F50: 28186000 | G50: =+LEFT(F50) -> 2 | H50: =+LEFT(F50,3) -> 281
A51: 37100000 | B51: Stock de marchandises | C51: 9.2666699e+08 | D51: 1.2367034e+09 | E51: 1.148297e+09 | F51: 37100000 | G51: =+LEFT(F51) -> 3 | H51: =+LEFT(F51,3) -> 371 | I51: 5.8752481e+08
A52: 38000000 | B52: Stocks flottant | C52: 0 | D52: 0 | E52: 0 | F52: 38000000 | G52: =+LEFT(F52) -> 3 | H52: =+LEFT(F52,3) -> 380
A53: 40100000 | B53: FNRS | C53: -1.9225049e+08 | D53: -1.5507642e+08 | E53: 0 | F53: 40100000 | G53: =+LEFT(F53) -> 4 | H53: =+LEFT(F53,3) -> 401
A54: 40110000 | B54: Frournisseur Locaux | C54: -6.5857393e+08 | D54: -1.3812746e+09 | E54: -98778539 | F54: 40110000 | G54: =+LEFT(F54) -> 4 | H54: =+LEFT(F54,3) -> 401 | I54: -89675450 | J54: =+#REF!-I54 -> #REF!
A55: 40120000 | B55: Fournisseur étrangers | C55: -3.0950399e+09 | D55: -1.7551857e+09 | E55: -2.3463941e+09 | F55: 40120000 | G55: =+LEFT(F55) -> 4 | H55: =+LEFT(F55,3) -> 401 | I55: -2.3463941e+09
A56: 40320000 | B56: F/sseurs effets à payer BFV | C56: 0 | D56: 0 | E56: 0 | F56: 40320000 | G56: =+LEFT(F56) -> 4 | H56: =+LEFT(F56,3) -> 403
A57: 40330000 | B57: F/sseurs effets à payer BOA | C57: 0 | D57: 0 | E57: -7250767 | F57: 40330000 | G57: =+LEFT(F57) -> 4 | H57: =+LEFT(F57,3) -> 403 | I57: -7250767
A58: 40340000 | B58: F/sseurs effets à payer BNI | C58: -1.0160923e+09 | D58: -21771350 | E58: -340848772 | F58: 40340000 | G58: =+LEFT(F58) -> 4 | H58: =+LEFT(F58,3) -> 403 | I58: -340848772
A59: 40400000 | B59: F/sseurs d'immobilisations | C59: -8.1292902e+08 | D59: -3.7932306e+09 | E59: -3.4962904e+09 | F59: 40400000 | G59: =+LEFT(F59) -> 4 | H59: =+LEFT(F59,3) -> 404 | I59: -3.4962904e+09
A60: 40800000 | B60: F/sseurs fact à recevoir | C60: -96660096 | D60: -7692475.1 | E60: -1.877532e+08 | F60: 40800000 | G60: =+LEFT(F60) -> 4 | H60: =+LEFT(F60,3) -> 408 | I60: -1.4913813e+08
A61: 40900000 | B61: Frns: avance et acomptes | C61: 27341487 | D61: 17916871 | E61: 3262450 | F61: 40900000 | G61: =+LEFT(F61) -> 4 | H61: =+LEFT(F61,3) -> 409 | I61: 3262450
A62: 41100000 | B62: Collectifs clients | C62: 4.0053353e+09 | D62: 4.9686012e+09 | E62: 1.0850528e+10 | F62: 41100000 | G62: =+LEFT(F62) -> 4 | H62: =+LEFT(F62,3) -> 411 | I62: 3.7848973e+09
A63: 41110000 | C63: 0 | D63: 0 | E63: 0 | F63: 41110000 | G63: =+LEFT(F63) -> 4 | H63: =+LEFT(F63,3) -> 411
A64: 41210000 | B64: Clts: effets remis encaissement | C64: 0 | D64: 0 | E64: 0 | F64: 41210000 | G64: =+LEFT(F64) -> 4 | H64: =+LEFT(F64,3) -> 412
A65: 41300000 | B65: Clients effets à recevoir | C65: 9720000 | D65: 0 | E65: 0 | F65: 41300000 | G65: =+LEFT(F65) -> 4 | H65: =+LEFT(F65,3) -> 413
A66: 41351000 | B66: Client effet à recevoir BNI | C66: -0.01 | D66: -0.0099999979 | E66: 0 | F66: 41351000 | G66: =+LEFT(F66) -> 4 | H66: =+LEFT(F66,3) -> 413
A67: 41600000 | B67: Clts douteux ou litigieux | C67: 3.9841846e+08 | D67: 6.7518942e+08 | E67: -3.306818e+09 | F67: 41600000 | G67: =+LEFT(F67) -> 4 | H67: =+LEFT(F67,3) -> 416 | I67: 5.6729244e+09
A68: 41810000 | C68: 1.0163323e+09 | D68: -4.0614869e+08 | E68: 0 | F68: 41810000 | G68: =+LEFT(F68) -> 4 | H68: =+LEFT(F68,3) -> 418
A69: 41910000 | B69: Clients créditeurs: acomptes | C69: -2.4135591e+08 | D69: -100000000 | E69: -100000000 | F69: 41910000 | G69: =+LEFT(F69) -> 4 | H69: =+LEFT(F69,3) -> 419 | I69: -100000000
A70: 42100000 | B70: Rémunérations dues au personnel | C70: 882669.27 | D70: -6.39 | E70: -1933777 | F70: 42100000 | G70: =+LEFT(F70) -> 4 | H70: =+LEFT(F70,3) -> 421 | I70: -1933777
A71: 42110000 | B71: Salaires Temporaires | C71: 1341000 | D71: 801000 | E71: 43125 | F71: 42110000 | G71: =+LEFT(F71) -> 4 | H71: =+LEFT(F71,3) -> 421 | I71: 43125
A72: 42500000 | B72: Avances & acomptes au personnel | C72: -128733.33 | F72: 42500000
A73: 42510000 | B73: Avances quinzaines | C73: -100000 | D73: -100000 | E73: -100000 | F73: 42510000 | G73: =+LEFT(F73) -> 4 | H73: =+LEFT(F73,3) -> 425 | I73: -100000
A74: 42520000 | B74: Avances spéciales | C74: -332867.01 | D74: 102800 | E74: 102800 | F74: 42520000 | G74: =+LEFT(F74) -> 4 | H74: =+LEFT(F74,3) -> 425 | I74: 102800
A75: 42700000 | B75: Pret au personnel | C75: -114333 | F75: 42700000
A76: 42820000 | B76: Personnel-congés payés | C76: -47560636 | D76: -47560636 | E76: -27284530 | F76: 42820000 | G76: =+LEFT(F76) -> 4 | H76: =+LEFT(F76,3) -> 428 | I76: -27284530
A77: 43100000 | B77: CNaPS | C77: -18966407 | D77: -1.0485268e+08 | E77: -23085762 | F77: 43100000 | G77: =+LEFT(F77) -> 4 | H77: =+LEFT(F77,3) -> 431 | I77: -23085762
A78: 43110000 | B78: Allocation familiale CNAPS | C78: -826000 | D78: -790000 | E78: -280000 | F78: 43110000 | G78: =+LEFT(F78) -> 4 | H78: =+LEFT(F78,3) -> 431 | I78: -280000
A79: 43200000 | B79: OSTIE | C79: -7897939.1 | D79: -44996004 | E79: -9893897.8 | F79: 43200000 | G79: =+LEFT(F79) -> 4 | H79: =+LEFT(F79,3) -> 432 | I79: -9893897.8
A80: 43230000 | B80: FUNHECE | C80: -1732772.4 | F80: 43230000
A81: 43300000 | B81: FMFP | C81: -900019.54 | D81: -7499334 | E81: -2661708.2 | F81: 43300000 | G81: =+LEFT(F81) -> 4 | H81: =+LEFT(F81,3) -> 433 | I81: -2661708.2
A82: 43400000 | B82: ASCOMA | C82: -1130000 | F82: 43400000
A83: 43860000 | B83: Organismes autres charges à payer | C83: -8641897.6 | D83: -8641897.6 | E83: -8641897.6 | F83: 43860000 | G83: =+LEFT(F83) -> 4 | H83: =+LEFT(F83,3) -> 438 | I83: -8641897.6
A84: 44100000 | B84: Etat: IRSA à payer | C84: -12876468 | D84: -9573522 | E84: -12756405 | F84: 44100000 | G84: =+LEFT(F84) -> 4 | H84: =+LEFT(F84,3) -> 441 | I84: -12756405
A85: 44300000 | B85: Etat: acomptes IR | C85: 3.575645e+08 | D85: 3.0336679e+08 | E85: 3.4240791e+08 | F85: 44300000 | G85: =+LEFT(F85) -> 4 | H85: =+LEFT(F85,3) -> 443
A86: 44310000 | B86: IR Intermittent Locaux | C86: -7778758.3 | D86: -7646258.4 | E86: -725630.95 | F86: 44310000 | G86: =+LEFT(F86) -> 4 | H86: =+LEFT(F86,3) -> 443 | I86: -725630.95
A87: 44320000 | B87: IR Intermittent étranger | C87: -10917785 | D87: -10917785 | E87: -5830271.8 | F87: 44320000 | G87: =+LEFT(F87) -> 4 | H87: =+LEFT(F87,3) -> 443 | I87: -5830271.8
A88: 44400000 | B88: IMPOT SUR LE RESULTAT (IR) | C88: -4.8267962e+08 | D88: -2.7258114e+08 | E88: -5.3327656e+08 | F88: 44400000 | G88: =+LEFT(F88) -> 4 | H88: =+LEFT(F88,3) -> 444 | I88: -1.5116771e+08
A89: 44540000 | B89: TVA à décaisser | C89: -87500100 | D89: 0 | E89: 0 | F89: 44540000 | G89: =+LEFT(F89) -> 4 | H89: =+LEFT(F89,3) -> 445
A90: 44550000 | B90: Credit de taxe | C90: -1.7474388e+08 | D90: -41283090 | E90: 1.6531996e+08 | F90: 44550000 | G90: =+LEFT(F90) -> 4 | H90: =+LEFT(F90,3) -> 445 | I90: 1.6509992e+08
A91: 44560000 | B91: TVA déductibles | C91: 21773.88 | D91: 0 | E91: 0 | F91: 44560000 | G91: =+LEFT(F91) -> 4 | H91: =+LEFT(F91,3) -> 445
A92: 44561000 | B92: TVA déductible sur revente | C92: 7894276 | D92: 7894276 | E92: 0 | F92: 44561000 | G92: =+LEFT(F92) -> 4 | H92: =+LEFT(F92,3) -> 445
A93: 44562000 | B93: TVA pour les Biens | C93: 1.3472284e+08 | D93: 1.3946864e+08 | E93: 10837942 | F93: 44562000 | G93: =+LEFT(F93) -> 4 | H93: =+LEFT(F93,3) -> 445 | I93: 40343127
A94: 44563000 | B94: TVA Intermittente deductible | C94: 27576421 | D94: 27576421 | E94: 17401396 | F94: 44563000 | G94: =+LEFT(F94) -> 4 | H94: =+LEFT(F94,3) -> 445 | I94: 17401396
A95: 44564000 | B95: TVA pour les Services | C95: 682089.05 | D95: 27606817 | E95: -2414921 | F95: 44564000 | G95: =+LEFT(F95) -> 4 | H95: =+LEFT(F95,3) -> 445 | I95: 4517762.7
A96: 44565000 | B96: TVA pour l'Immobilisation | C96: 1.1084145e+08 | D96: 1.1064969e+08 | E96: -1.003376e+08 | F96: 44565000 | G96: =+LEFT(F96) -> 4 | H96: =+LEFT(F96,3) -> 445 | I96: 81746845
A97: 44566000 | B97: TVA SUR DD | C97: 21082746 | D97: 21082746 | E97: 0 | F97: 44566000 | G97: =+LEFT(F97) -> 4 | H97: =+LEFT(F97,3) -> 445
A98: 44567000 | B98: TVA SUR PGN | C98: 127208 | D98: 127208 | E98: 0 | F98: 44567000 | G98: =+LEFT(F98) -> 4 | H98: =+LEFT(F98,3) -> 445
A99: 44570000 | B99: TVA collectées | C99: -1.1943381e+09 | D99: -8.7640385e+08 | E99: 65720982 | F99: 44570000 | G99: =+LEFT(F99) -> 4 | H99: =+LEFT(F99,3) -> 445 | I99: -15590644
A100: 44571000 | B100: TVA Intermittente collectée | C100: -17949255 | D100: -17949255 | E100: -7774230 | F100: 44571000 | G100: =+LEFT(F100) -> 4 | H100: =+LEFT(F100,3) -> 445 | I100: -2.4548118e+08
...

Sheet ID Motors
A1: x | D1: 2021 | E1: 2020 | F1: 2019 2e dépôt | J1: EF CONSO 2019
D2: =SUM(D3:D314) -> -1.0673254e-06 | E2: =SUM(E3:E314) -> 5.1470155e-06 | F2: =SUM(F3:F314) -> 2.654273e-06 | J2: =+SUBTOTAL(9,J3:J283) -> 1.6540325e-06
A3: 10100000 | B3: 10100000 | C3: CAPITAL | D3: -2000000 | E3: -2000000 | F3: -2000000 | G3: 10100000 | H3: 1 | I3: 101 | J3: -2000000 | K3: =+F3-J3 -> 0
A4: 10610000 | B4: 10610000 | C4: RESERVES LÉGALES | D4: -200000 | E4: -200000 | F4: -200000 | G4: 10610000 | H4: 1 | I4: 106 | J4: -200000 | K4: =+F4-J4 -> 0
A5: 11000000 | B5: 11000000 | C5: RAN CREDITEUR | D5: -2.9784895e+09 | E5: -2.9784895e+09 | F5: -2.9784895e+09 | G5: 11000000 | H5: 1 | I5: 110 | J5: -2.9784895e+09 | K5: =+F5-J5 -> 0
A6: 12000000 | B6: 12000000 | C6: RESULTAT NET DE L'EXERCICE BENEFICE | D6: 9.5792226e+08 | E6: 9.5792226e+08 | F6: -1.8358938e+09 | G6: 12000000 | H6: 1 | I6: 120 | J6: -1.8358938e+09 | K6: =+F6-J6 -> 0
A7: 12900000 | B7: 12900000 | C7: RESULTAT NET DE L'EXERCICE PERTE | D7: 4.6472769e+09 | E7: 0 | F7: 0 | G7: 12900000 | H7: 1 | I7: 129 | J7: 0 | K7: =+F7-J7 -> 0
A8: 16100000 | B8: 16100000 | C8: EMPRUNTS BMOI | D8: -67679548 | E8: -2.5774589e+08 | F8: -3.4591237e+08 | G8: 16100000 | H8: 1 | I8: 161 | J8: -3.4591237e+08 | K8: =+F8-J8 -> 0
A9: 16300000 | B9: 16300000 | C9: EMPRUNT BMOI 2 | D9: -3.5378085e+08 | E9: -5.6192151e+08 | F9: -6.5847217e+08 | G9: 16300000 | H9: 1 | I9: 161 | J9: -6.5847217e+08 | K9: =+F9-J9 -> 0
A10: 16410000 | B10: 16410000 | C10: BNI LEASING | D10: -2.2186586e+09 | E10: -3.0642265e+09 | F10: -2.3726868e+09 | G10: 16410000 | H10: 1 | I10: 164 | J10: 0 | K10: =+F10-J10 -> -2.3726868e+09
A11: 16414000 | B11: 16414000 | C11: A RENOMMER | D11: 0 | E11: 0 | F11: 0 | G11: 16414000 | H11: #N/A | I11: #N/A | J11: 0 | K11: =+F11-J11 -> 0
A12: 20400000 | B12: 20400000 | C12: LOGICIELS INFORMATIQUES & ASSIMILÉS | D12: 4832320.4 | E12: 4832320.4 | F12: 4832320.4 | G12: 20400000 | H12: 2 | I12: 204 | J12: 4832320.4 | K12: =+F12-J12 -> 0
A13: 21500000 | B13: 21500000 | C13: AGENCEMENT AMENAGEMENT INSTALLATION | D13: 2.2803413e+08 | E13: 2.1743153e+08 | F13: 2.1743153e+08 | G13: 21500000 | H13: 2 | I13: 215 | J13: 2.1743153e+08 | K13: =+F13-J13 -> 0
A14: 21520000 | B14: 21520000 | C14: INSTALLATION CAMERA | D14: 4631041.9 | E14: 4631041.9 | F14: 4631041.9 | G14: 21520000 | H14: 2 | I14: 215 | J14: 4631041.9 | K14: =+F14-J14 -> 0
... A283: 78500000 | B283: 78500000 | C283: REPRISE PROVISION | D283: 0 | E283: -10287024 | F283: 0 | G283: 78500000 | H283: 7 | I283: 785 | J283: 0 | K283: =+F283-J283 -> 0
B284: 16200000 | C284: EMPRUNTS BFV | D284: -2000000000 | G284: 16200000
B285: 16400000 | C285: EMPRUNT BOA | D285: -3.5399178e+09 | G285: 16400000
B286: 21300000 | C286: CONSTRUCTIONS | D286: 0 | G286: 21300000
B287: 28130000 | C287: AMTS CONSTRUCTIONS | D287: 0 | G287: 28130000
B288: 40960000 | C288: EMBALLAGES A RENDRE | D288: 2980800 | G288: 40960000
B289: 42110000 | C289: Salaires temporaires | D289: 450000 | G289: 42110000
B290: 43500000 | C290: ASCOMA | D290: -400000 | G290: 43500000
B291: 45500001 | C291: ASSOCIE MCM | D291: -40000000 | G291: 45500001
B292: 46720081 | C292: AGRICORP | D292: -22471598 | G292: 46720081
B293: 46720082 | C293: AGRIMOTORS | D293: -33482844 | G293: 46720082
B294: 46720083 | C294: SALAMA | D294: 5124531.8 | G294: 46720083
B295: 46720084 | C295: RYA | D295: -3664420.7 | G295: 46720084
... B314: 76880000 | C314: DIVERS XTS FINANCIERS | D314: -154894.95 | G314: 76880000

Sheet ID RENTAL
A1: N° COMPTE | C1: INTITULES | D1: 2021 | E1: 2020 | F1: EF CONSO 2019 | I1: 2019
A2: 1010000 | B2: 10100000 | C2: CAPITAL | D2: -2000000 | E2: -2000000 | F2: -2000000 | G2: 10100000 | I2: -2000000
A3: 1200000 | B3: 12000000 | C3: RESULTAT NET DE L'EXERCICE BENEFICE | D3: 5.3531069e+08 | E3: -4.9959917e+08 | F3: 0 | G3: 12000000 | I3: 0
A4: 1620000 | B4: 16200000 | C4: EMPRUNTS BFV | D4: -1.8796214e+09 | E4: -2.4606543e+09 | F4: 0 | G4: 16200000 | I4: 0
A5: 2183000 | B5: 21830000 | C5: MATERIEL DE TRANSPORT | D5: 1.2702289e+10 | E5: 5.3014817e+09 | F5: 1.5659586e+09 | G5: 21830000 | I5: 1.5659586e+09
A6: 2184000 | B6: 21840000 | C6: MATÉRIEL INFORMATIQUES | D6: 10396500 | E6: 5316500 | F6: 950000 | G6: 21840000 | I6: 950000
A7: 2750000 | B7: 27500000 | C7: DEPOT & CAUTIONNEMENTS VERSES | D7: 11551700 | E7: 2144000 | F7: 1000000 | G7: 27500000 | I7: 1000000
A8: 2813000 | B8: 28130000 | C8: AMTS CONSTRUCTIONS | D8: 0 | E8: 0 | F8: 0 | G8: 28130000 | I8: 0
A9: 2818300 | B9: 28183000 | C9: AMTS MATERIEL DE TRANSPORT | D9: -3.2377663e+09 | E9: -1.3805926e+09 | F9: -4.2414934e+08 | G9: 28183000 | I9: -4.2414934e+08
A10: 2818400 | B10: 28184000 | C10: AMTS MATERIEL INFORMATIQUE | D10: -2520772.7 | E10: -607837.94 | F10: -93681 | G10: 28184000 | I10: -93681
A11: 4010000 | B11: 40100000 | C11: FOURNISSEURS LOCAUX | D11: -2.4156319e+08 | E11: -3.6365948e+08 | F11: 0 | G11: 40100000 | I11: 0
A12: 4011000 | B12: 40110000 | C12: FOURNISSEURS LOCAUX | D12: 28450264 | E12: 5040921.2 | F12: -1.1430953e+08 | G12: 40110000 | I12: -1.1241737e+08
A13: 4033000 | B13: 40330000 | C13: F/SSEURS EFFETS À PAYER BOA | D13: 0 | E13: 0 | F13: 0 | G13: 40330000 | I13: 0
... A19: 4130000 | B19: 41300000 | C19: CLIENTS EFFETS À RECEVOIR | D19: 117216000 | E19: 0 | F19: 0 | G19: 41300000 | I19: 0
A20: 4180000 | B20: 41800000 | C20: Clients produits non encore facturer | D20: 247500000 | F20: 0 | G20: 41800000 | I20: -3180000
A21: 4210000 | B21: 42100000 | C21: RÉMUNÉRATIONS DUES AU PERSONNEL | D21: 11110408 | E21: -2478070 | F21: 0 | G21: 42100000 | I21: 0
A22: 4250000 | B22: 42500000 | C22: AVANCES & ACOMPTES AU PERSONNEL | D22: -3075000 | E22: 285000 | F22: 0 | G22: 42500000 | I22: 0
A23: 4251000 | B23: 42510000 | C23: AVANCES SPECIALES | D23: 15090500 | E23: 17726333 | F23: 5260000 | G23: 42510000 | I23: 5260000
A24: 4282000 | B24: 42820000 | C24: PERSONNEL CONGES PAYES | D24: -1.7188316e+08 | E24: -47046991 | F24: 0 | G24: 42820000 | I24: 0
A25: 4310000 | B25: 43100000 | C25: CNAPS | D25: -27749296 | E25: -42333017 | F25: -7931976.5 | G25: 43100000 | I25: -7931976.5
A26: 4311000 | B26: 43110000 | C26: CNAPS ALLOCAT° FAMILIALES | D26: 86000 | E26: 74000 | F26: 32000 | G26: 43110000 | I26: 32000
A27: 4312000 | B27: 43120000 | C27: FMFP | D27: -407541.03 | E27: -1621589.8 | F27: -566569.75 | G27: 43120000 | I27: -566569.75
A28: 4320000 | B28: 43200000 | C28: OSTIE | D28: -12250872 | E28: -15935415 | F28: -3399418.5 | G28: 43200000 | I28: -3399418.5
A29: 434à créer | B29: 434à créer0 | C29: FUNHECE | D29: 0 | E29: 0 | F29: 0 | G29: 434à créer0 | I29: 0
A30: 4410000 | B30: 44100000 | C30: ETAT: IRSA À PAYER | D30: -12152142 | E30: -10153247 | F30: -2460983 | G30: 44100000 | I30: -2460983
A31: 4430000 | B31: 44300000 | C31: ETAT: ACOMPTES IR | D31: 0 | E31: 1.2962817e+08 | F31: 320000 | G31: 44300000 | I31: 320000
A32: 4431000 | B32: 44310000 | C32: IR Intermittent Locaux | D32: -252552.16 | E32: -191763.16 | F32: -65000 | G32: 44310000 | I32: -65000
A33: 4441000 | B33: 44410000 | C33: IR IMPOTS SUR LES RESULTATS | D33: 0 | E33: -80842587 | F33: 0 | G33: 44410000 | I33: -1.2537073e+08
A34: 4455000 | B34: 44550000 | C34: CREDIT DE TAXE | D34: 6.4480545e+08 | E34: 1.6622645e+08 | F34: 58505143 | G34: 44550000 | I34: 58505143
A35: 4456000 | B35: 44560000 | C35: TVA DÉDUCTIBLES | D35: 0 | E35: 0 | F35: 0 | G35: 44560000 | I35: 0
A36: 4456200 | B36: 44562000 | C36: TVA pour les Biens | D36: 49648759 | E36: 558705.01 | F36: 2607788.4 | G36: 44562000 | I36: 2607788.4
A37: 4456400 | B37: 44564000 | C37: TVA pour les Services | D37: 1714775.9 | E37: 11894004 | F37: 29330442 | G37: 44564000 | I37: 29330442
A38: 4456500 | B38: 44565000 | C38: TVA pour l'Immobilisation | D38: 2.837772e+08 | E38: 2.0011229e+08 | F38: 2.5557172e+08 | G38: 44565000 | I38: 2.5557172e+08
A39: 4457000 | B39: 44570000 | C39: TVA COLLECTÉES | D39: -4.9759658e+08 | E39: -2.0993169e+08 | F39: -1.4492559e+08 | G39: 44570000 | I39: -1.4492559e+08
A40: 4457200 | B40: 44572000 | C40: TVA COLLECTEES SUR SERVICES | D40: 0 | E40: 0 | F40: -1.5413271e+08 | G40: 44572000 | I40: -1.5413271e+08
A41: 4457400 | B41: 44574000 | C41: TVA relatifs aux cessions d'immobil | D41: -1.711168e+08 | E41: 0 | F41: 0 | G41: 44574000 | I41: 0
... A53: 4860000 | B53: 48600000 | C53: CHARGES CONSTATEES D'AVANCE | D53: 21323083 | E53: 61164302 | F53: 0 | G53: 48600000 | I53: 0
A54: 4870000 | B54: 48700000 | C54: PRODUITS CONSTATES D'AVANCE | D54: -5.3798087e+08 | E54: -4.6806573e+08 | F54: 0 | G54: 48700000 | I54: -108120000 | J54: =+I54/2 -> -54060000
A55: 5111000 | B55: 51110000 | C55: CHÈQUE À ENCAISSER | D55: 9120236 | E55: 0.0099999905 | F55: 0 | G55: 51110000 | I55: 0
A56: 5112000 | B56: 51120000 | C56: TRAITE REÇUE | D56: 814535182 | E56: 824136826 | F56: -3180000 | G56: 51120000 | I56: 0
A57: 5112100 | B57: 51121000 | C57: EFFET REMIS A L'ENCAISSEMENT | D57: 9000000 | E57: 0 | F57: 0 | G57: 51121000 | I57: 0
A58: 5114000 | B58: 51140000 | C58: VIREMENT REÇU | D58: 44124000 | E58: 45124000 | F58: 0 | G58: 51140000 | I58: 0
A59: 5122100 | B59: 51221000 | C59: BFV Ariary | D59: 1.0926657e+08 | E59: 28759889 | F59: 0 | G59: 51221000 | I59: 0
A60: 5123100 | B60: 51231000 | C60: BOA Ariary | D60: 7936615.4 | E60: 73554228 | F60: 108785.56 | G60: 51231000 | I60: 108785.56
A61: 5124100 | B61: 51241000 | C61: BNI MGA | D61: 7049534.8 | E61: -77486313 | F61: 8913880.8 | G61: 51241000 | I61: 8913880.8
A62: 5320000 | B62: 53200000 | C62: Caisse Digue | D62: 5433058 | E62: 467058 | F62: 2951117.8 | G62: 53200000 | I62: 2951117.8
A63: 5330000 | B63: 53300000 | C63: Caisse recette | D63: 0 | E63: 2500000 | F63: 5606000 | G63: 53300000 | I63: 5606000
A64: 5800000 | B64: 58000000 | C64: VIREMENTS INTERNES | D64: 0 | E64: 0 | F64: 0 | G64: 58000000 | I64: 0
A65: 6020600 | B65: 60206000 | C65: Pièces de rechange | D65: 3.5800242e+08 | E65: 37494941 | F65: 32993636 | G65: 60206000 | I65: 32993636
A66: 6060100 | B66: 60601000 | C66: EAU & ÉLECTRICITÉ | D66: 75273 | E66: 75258 | F66: 0 | G66: 60601000 | I66: 0
... A109: 6410300 | B109: 64103000 | C109: PRIMES DIVERSES | D109: 23779362 | E109: 13825004 | F109: 0 | G109: 64103000 | I109: 0
A110: 6410400 | B110: 64104000 | C110: HEURES SUPP | D110: 33583260 | F110: 244060.21 | G110: 64104000 | I110: 244060.21
A111: 6410500 | B111: 64105000 | C111: CONGS PAYES | D111: 4835229.7 | F111: 95594.58 | G111: 64105000 | I111: 95594.58
A112: 6450100 | B112: 64501000 | C112: COT PATRONALE CNAPS | D112: 98598837 | E112: 40976993 | F112: 7365406.8 | G112: 64501000 | I112: 7365406.8
A113: 6450200 | B113: 64502000 | C113: COT PATRONALE OSTIE | D113: 37762324 | E113: 15680912 | F113: 2832848.8 | G113: 64502000 | I113: 2832848.8
A114: 6450400 | B114: 64504000 | C114: COTISATION FMFP | D114: 7584523 | E114: 1621589.8 | F114: 566569.75 | G114: 64504000 | I114: 566569.75
A115: 6470000 | B115: 64700000 | C115: Autres charges sociales | D115: -196330 | E115: 560000 | F115: 0 | G115: 64700000 | I115: 0
A116: 6480000 | B116: 64800000 | C116: Compte à créer | D116: 1600751 | E116: 1000000 | F116: 0 | G116: 64800000 | I116: 0
A117: 6480300 | B117: 64803000 | C117: FRAIS MÉDICAUX | D117: 500364 | E117: 0 | F117: 0 | G117: 64803000 | I117: 0
A118: 6480800 | B118: 64808000 | C118: Autres charges du personnel | D118: 2673370 | E118: 55626677 | F118: 0 | G118: 64808000 | I118: 0
A119: 6560100 | B119: 65601000 | C119: AMENDES FISCALES | D119: 200000 | E119: 195437.95 | F119: 0 | G119: 65601000 | I119: 0
A120: 6560200 | B120: 65602000 | C120: DONS & LIBERALITS | D120: 36301 | F120: 600000 | G120: 65602000 | I120: 600000
A121: 6570000 | B121: 65700000 | C121: Autres charges de gestion courante | D121: 134537.91 | E121: 10552728 | F121: 1733.28 | G121: 65700000 | I121: 1733.28
A122: 6610000 | B122: 66100000 | C122: Compte à créer | D122: 0 | E122: 6465692.2 | F122: 0 | G122: 66100000 | I122: 0
A123: 6610100 | B123: 66101000 | C123: INTERET SUR ESCOMPTE | D123: 17920940 | E123: 567705.93 | F123: 0 | G123: 66101000 | I123: 0
A124: 6610200 | B124: 66102000 | C124: Intérêt / découverts bancaires | D124: 26169882 | E124: 8452588.3 | F124: 912577.68 | G124: 66102000 | I124: 912577.68
A125: 6610300 | B125: 66103000 | C125: Intéret des emprunts PMT | D125: 2.6696426e+08 | E125: 51075144 | F125: 0 | G125: 66103000 | I125: 0
A126: 6614000 | B126: 66140000 | C126: Compte à créer | D126: 0 | E126: 94910.11 | F126: 0 | G126: 66140000 | I126: 0
A127: 6688000 | B127: 66880000 | C127: ECART | D127: 0 | E127: 36.8 | F127: 0 | G127: 66880000 | I127: 0
A128: 6703000 | B128: 67030000 | C128: Compte à créer | D128: 0 | E128: 9000 | F128: 0 | G128: 67030000 | I128: 0
A129: 6811200 | B129: 68112000 | C129: DOT AMO IMMOB CORPORELLES | D129: 2.1057294e+09 | E129: 9.5695737e+08 | F129: 93681 | G129: 68112000 | I129: 4.2424302e+08
A130: 6980000 | B130: 69800000 | C130: IMPOTS SUR LES REVENUS | D130: 37043341 | E130: 14692480 | F130: 0 | G130: 69800000 | I130: 1.2537073e+08
A131: 7061000 | B131: 70610000 | C131: LOCATIONS | D131: -6.6281085e+09 | E131: -2.7663761e+09 | F131: -1.2229631e+09 | G131: 70610000 | I131: -1.5479936e+09
A132: 7083000 | B132: 70830000 | C132: Locations diverses | D132: 0 | E132: -108120000 | F132: 0 | G132: 70830000 | I132: 108120000
A133: 7580000 | B133: 75800000 | C133: Autres produits de gestion courante | D133: -3829089.4 | E133: -1614109.8 | F133: 0 | G133: 75800000 | I133: 0
A134: 7581000 | B134: 75810000 | C134: TICKETS CANTINE | D134: -818200 | F134: -240695 | G134: 75810000 | I134: -240695
B135: 11000000 | C135: REPORT A NOUVEAU | D135: -2.6765535e+08 | G135: 11000000
B136: 16100000 | C136: EMPRUNTS BMOI | D136: -1.4249691e+09 | G136: 16100000
B137: 16300000 | C137: EMPRUNT BMOI 2 | D137: -9.3103798e+08 | G137: 16300000
B138: 16400010 | C138: BNI LEASING_LSB10282_ZNA 4304TBP | D138: -64119080 | G138: 16400010
B139: 16400020 | C139: BNI LEASING_LSB10283_CAMION 7T B | D139: -37307324 | G139: 16400020
B140: 16400030 | C140: BNI LEASING_LSB10284_ CAMION 3.5 | D140: -59482361 | G140: 16400030
B141: 16400040 | C141: BNI LEASING_LSB10285_CAMION 3.5T | D141: -59482361 | G141: 16400040
B142: 16400050 | C142: BNI LEASING_LSB10286_ MINIBUS V2 | D142: -14710071 | G142: 16400050
B143: 16400060 | C143: BNI LEASING_LSB10287_ MINIBUS V2 | D143: -32462553 | G143: 16400060
B144: 16400070 | C144: BNI LEASING_LSB10288_CAMION 4T B | D144: -45044899 | G144: 16400070
B145: 16400080 | C145: BNI LEASING_LSB10289_PICK UP DOU | D145: -18566241 | G145: 16400080
B146: 16400090 | C146: BNI LEASING_LSB10290_DONG FENG V | D146: -32500749 | G146: 16400090
... B204: 76600000 | C204: GAINS DE CHANGE | D204: -249078 | G204: 76600000

Sheet MCM 
B1: N° COMPTE | C1: INTITULES | D1: 2021 | E1: 2020 | F1: EF 2019 Conso | G1: Gestion | I1: 2019
A2: =+LEFT(B:B) -> 4 | B2: 4457100 | C2: Compte à créer | D2: 0 | E2: -31696433 | F2: 0 | G2: 44571000 | I2: 0
A3: =+LEFT(B:B) -> 7 | B3: 7071000 | C3: Compte à créer | D3: 0 | E3: -9.4423971e+08 | F3: 0 | G3: 70710000 | I3: 0
A4: =+LEFT(B:B) -> 1 | B4: 10100000 | C4: CAPITAL | D4: -1500000000 | E4: -1500000000 | F4: -500000000 | G4: 10100000 | I4: -500000000
A5: =+LEFT(B:B) -> 1 | B5: 10680000 | C5: AUTRE RESERVE | D5: -9.507467e+08 | E5: -9.507467e+08 | F5: -9.507467e+08 | G5: 10620000 | I5: -9.507467e+08
A6: =+LEFT(B:B) -> 1 | B6: 11000000 | C6: RAN CREDITEUR | D6: -8.2018774e+08 | E6: -6.750593e+08 | F6: -8.7592455e+08 | G6: 11000000 | I6: -8.7592455e+08
A7: =+LEFT(B:B) -> 1 | B7: 11900000 | C7: RAN DEBITEUR | D7: -0.19 | E7: -0.19 | F7: -0.19 | G7: 11900000 | I7: -0.19
A8: =+LEFT(B:B) -> 1 | B8: 12000000 | C8: RESULTAT NET DE L'EXERCICE BENEFICE | D8: 0 | E8: 0 | F8: 3.0574719e+08 | G8: 12000000 | I8: 3.0574719e+08
A9: =+LEFT(B:B) -> 1 | B9: 16411000 | C9: ASM BNI | D9: -1.3746491e+08 | E9: 0 | F9: -240000000 | G9: 51920000 | I9: -240000000
A10: =+LEFT(B:B) -> 1 | B10: 16412000 | C10: ASM BMOI | D10: 0 | E10: 1.8597368e+08 | F10: 1.8597368e+08 | G10: 51960000 | I10: 1.8597368e+08
A11: =+LEFT(B:B) -> 1 | B11: 16413000 | C11: ASM MCB | D11: 0 | E11: 200000000 | F11: 200000000 | G11: 51950000 | I11: 200000000
A12: =+LEFT(B:B) -> 2 | B12: 20400000 | C12: LOGICIELS INFORMATIQUES & ASSIMILÉS | D12: 3492900 | E12: 3492900 | F12: 2297900 | G12: 20400000 | I12: 2297900
A13: =+LEFT(B:B) -> 2 | B13: 21350000 | C13: INSTALLATION GENERAL | D13: 3129764.7 | E13: 3129764.7 | F13: 2000000 | G13: 21520000 | I13: 2000000
... A26: =+LEFT(B:B) -> 2 | B26: 28182000 | C26: AMTS MMB | D26: -6650071 | E26: -32701720 | F26: -29224197 | G26: 28182000 | I26: -29224197
A27: =+LEFT(B:B) -> 2 | B27: 28183000 | C27: AMTS MATERIEL DE TRANSPORT | D27: -1.8595208e+08 | E27: -1.596103e+08 | F27: =-133360297.44-178333.39 -> -1.3353863e+08 | G27: 28183000 | I27: -1.333603e+08
A28: =+LEFT(B:B) -> 2 | B28: 28184000 | C28: AMTS MATERIEL INFORMATIQUE | D28: -50512474 | E28: -45430769 | F28: -39957199 | G28: 28184000 | I28: -39957199
A29: =+LEFT(B:B) -> 2 | B29: 28185000 | C29: AMTS MAT & MOB DE LOGT | D29: -3817553.2 | E29: -3700000 | F29: -3700000 | G29: 28182000 | I29: -3700000
A30: =+LEFT(B:B) -> 2 | B30: 28187000 | C30: AMORT MAT & MOB DE MAGASIN | D30: -579583.55 | E30: -401250.15 | F30: -222916.75 | G30: 28182000 | I30: -222916.75
A31: =+LEFT(B:B) -> 3 | B31: 37100000 | C31: STOCKS DE MARCHANDISES | D31: 1.6557086e+09 | E31: 2.4639294e+09 | F31: 2463886490 | G31: 37100000 | I31: 2463886490
A32: =+LEFT(B:B) -> 3 | B32: 37200000 | C32: STOCKS DES PIECES ET ACC MOTO | D32: 700000000 | E32: 1.3060246e+09 | F32: 1207407178 | G32: 35000000 | I32: 1207407178
A33: =+LEFT(B:B) -> 4 | B33: 40100000 | C33: FOURNISSEURS LOCAUX | D33: -7.1024017e+08 | E33: -6.7607612e+08 | F33: -407738003 | G33: 40110000 | I33: -407738003
A34: =+LEFT(B:B) -> 4 | B34: 40120000 | C34: FRNS ETRANGERS | D34: -1.722368e+09 | E34: -2.3657227e+09 | F34: -1223182498 | G34: 40120000 | I34: -1223182498
A35: =+LEFT(B:B) -> 4 | B35: 40300000 | C35: F/SSEURS EFFETS À PAYER | D35: -184384943 | G35: 40300000
A36: =+LEFT(B:B) -> 4 | B36: 40310000 | C36: F/SSEURS EFFETS À PAYER BMOI | D36: 5.6664376e+08 | E36: 1.2467416e+08 | F36: 0 | G36: 40310000 | I36: 0
A37: =+LEFT(B:B) -> 4 | B37: 40320000 | C37: F/SSEURS EFFETS À PAYER BFV | D37: 23441114 | G37: 40320000
A38: =+LEFT(B:B) -> 4 | B38: 40340000 | C38: F/SSEURS EFFETS À PAYER BNI | D38: 17596698 | E38: -3.8806111e+08 | F38: 0 | G38: 40310000 | I38: 0
A39: =+LEFT(B:B) -> 4 | B39: 40400000 | C39: F/SSEURS D'IMMOBILISATIONS | D39: -160800000 | E39: -9641150 | F39: 0 | G39: 40400000 | I39: 0
A40: =+LEFT(B:B) -> 4 | B40: 40800000 | C40: F/SSEURS FACT À RECEVOIR | D40: -1.543975e+08 | E40: 0 | F40: 0 | G40: 40810000 | I40: 0
B41: 40910000 | C41: FRNS DEBITEURS: AVANCES ET ACOMPTES | D41: 0 | G41: 40810000
A42: =+LEFT(B:B) -> 4 | B42: 41100000 | C42: COLLECTIFS CLIENTS | D42: 9.036855e+08 | E42: 2.5261753e+09 | F42: 956587769 | G42: 41100000 | I42: 956587769
A43: =+LEFT(B:B) -> 4 | B43: 41110000 | C43: BNI LEASING | D43: -5530000 | E43: -5392500 | F43: 0 | G43: 41100000 | I43: 0
A44: =+LEFT(B:B) -> 4 | B44: 41200000 | C44: CLIENT EFFET A RECEVOIR | D44: 0 | E44: 0 | F44: 0 | G44: 41310000 | I44: 0
A45: =+LEFT(B:B) -> 4 | B45: 41210000 | C45: Clts: effets remis encaissement | D45: 1.5164661e+08 | E45: 1.5164661e+08 | F45: 1.5164661e+08 | G45: 41310000 | I45: 1.5164661e+08
A46: =+LEFT(B:B) -> 4 | B46: 41300000 | C46: CLIENTS EFFETS À RECEVOIR | D46: -0.27000001 | E46: -1.5975595e+08 | F46: -90541625 | G46: 41310000 | I46: -90541625
A47: =+LEFT(B:B) -> 4 | B47: 41311000 | C47: Clients effets à recevoir BMOI | D47: 0.45000005 | E47: 94442032 | F47: 0 | G47: 41310000 | I47: 0
A48: =+LEFT(B:B) -> 4 | B48: 41341000 | C48: Client effet à recevoir BNI | D48: 0.21000001 | E48: -49065250 | F48: 0 | G48: 41310000 | I48: 0
A49: =+LEFT(B:B) -> 4 | B49: 41371000 | C49: TRAITE ESCOMPTE | D49: 3.9319466e+08 | E49: 3.9319466e+08 | F49: 3.9319466e+08 | G49: 41310000 | I49: 3.9319466e+08
A50: =+LEFT(B:B) -> 4 | B50: 41600000 | C50: CLTS DOUTEUX OU LITIGIEUX | D50: 1.9131996e+08 | E50: 1.9131996e+08 | F50: 2.0460393e+08 | G50: 41600000 | I50: 2.0460393e+08
A51: =+LEFT(B:B) -> 4 | B51: 41800000 | C51: Clients- produits non encore factur | D51: 1.7511069e+09 | G51: 41800000
A52: =+LEFT(B:B) -> 4 | B52: 42100000 | C52: RÉMUNÉRATIONS DUES AU PERSONNEL | D52: 0 | E52: -5512867.7 | F52: 5686027.1 | G52: 42110000 | I52: 5686027.1
A53: =+LEFT(B:B) -> 4 | B53: 42110000 | C53: Salaires temporaires | D53: 0 | E53: -4625000 | F53: 575000 | G53: 42110000 | I53: 575000
A54: =+LEFT(B:B) -> 4 | B54: 42120000 | C54: SOLDE DE TOUT COMPTE | D54: 0 | G54: 42120000
A55: =+LEFT(B:B) -> 4 | B55: 42500000 | C55: AVANCES & ACOMPTES AU PERSONNEL | D55: 2702000 | E55: 3684000 | F55: -13273000 | G55: 42510000 | I55: -13273000
A56: =+LEFT(B:B) -> 4 | B56: 42510000 | C56: AVANCES SPECIALES | D56: 0 | E56: -4689333.3 | F56: -5580000 | G56: 42510000 | I56: -5580000
A57: =+LEFT(B:B) -> 4 | B57: 42520000 | C57: AUTRE CESSIONS | D57: 675500 | E57: 675500 | F57: 675500 | G57: 42520000 | I57: 675500
B58: 42700000 | C58: Pret au personnel | D58: 0 | G58: 42520000
A59: =+LEFT(B:B) -> 4 | B59: 42820000 | C59: PERSONNEL CONGES PAYES | D59: -70759326 | E59: 168000 | F59: 168000 | G59: 42800000 | I59: 168000
A60: =+LEFT(B:B) -> 4 | B60: 43100000 | C60: CNAPS | D60: -12363661 | E60: -21551384 | F60: -8159086.1 | G60: 43100000 | I60: -8159086.1
A61: =+LEFT(B:B) -> 4 | B61: 43110000 | C61: CNAPS ALLOCAT° FAMILIALES | D61: 0 | E61: -2061000 | F61: -1143000 | G61: 43110000 | I61: -1143000
A62: =+LEFT(B:B) -> 4 | B62: 43120000 | C62: FMFP | D62: -705145.9 | E62: -3400374.8 | F62: -2142679.2 | G62: 43300000 | I62: -2142679.2
A63: =+LEFT(B:B) -> 4 | B63: 43200000 | C63: OSTIE | D63: -4113921.4 | E63: -2257269.5 | F63: 1513040.2 | G63: 43200000 | I63: 1513040.2
A64: =+LEFT(B:B) -> 4 | B64: 43300000 | C64: OSTIE | D64: 0 | E64: -4027716.1 | F64: -4027716.1 | G64: 43200000 | I64: -4027716.1
A65: =+LEFT(B:B) -> 4 | B65: 43400000 | C65: ASCOMA | D65: -150000 | G65: 43400000
A66: =+LEFT(B:B) -> 4 | B66: 43860000 | C66: AUTRES ORGNAISMES | D66: 7032688.8 | E66: 5992500 | F66: 0 | G66: 43860000 | I66: 0
A67: =+LEFT(B:B) -> 4 | B67: 44100000 | C67: ETAT: IRSA À PAYER | D67: -12479712 | E67: -9761962.1 | F67: -6363021.9 | G67: 44100000 | I67: -6363021.9
A68: =+LEFT(B:B) -> 4 | B68: 44250000 | C68: IR A PAYER 2019 | D68: 18583328 | E68: -18747505 | F68: -45661250 | G68: 44400000 | I68: -45661250
A69: =+LEFT(B:B) -> 4 | B69: 44300000 | C69: ETAT: ACOMPTES IR | D69: 34440901 | E69: 30826430 | F69: 26913745 | G69: 44300000 | I69: 26913745
A70: =+LEFT(B:B) -> 4 | B70: 44310000 | C70: IR Intermittent Locaux | D70: -97402.1 | E70: -57500 | F70: -57500 | G70: 44411000 | I70: -57500
A71: =+LEFT(B:B) -> 4 | B71: 44311000 | C71: ARS | D71: 36904315 | G71: 44311000
A72: =+LEFT(B:B) -> 4 | B72: 44320000 | C72: IR Intermittent étranger | D72: -18906806 | E72: -15758311 | F72: -905542 | G72: 44412000 | I72: -905542
A73: =+LEFT(B:B) -> 4 | B73: 44400000 | C73: IRI Locaux (ne plus utilisé) | D73: 0 | E73: 20789574 | F73: 20789574 | G73: 44411000 | I73: 20789574
A74: =+LEFT(B:B) -> 4 | B74: 44410000 | C74: IMPOT SUR LE REVENU | D74: -21992222 | E74: -41805730 | F74: 0 | G74: 44400000 | I74: 0
A75: =+LEFT(B:B) -> 4 | B75: 44510000 | C75: CREDIT DE TVA | D75: 0 | E75: 11279720 | F75: 0 | G75: 44550000 | I75: 0
A76: =+LEFT(B:B) -> 4 | B76: 44540000 | C76: TVA À DÉCAISSER | D76: 50860867 | E76: 54094823 | F76: 686579 | G76: 44540000 | I76: 686579
A77: =+LEFT(B:B) -> 4 | B77: 44550000 | C77: CREDIT DE TAXE | D77: 0 | G77: 44550000
A78: =+LEFT(B:B) -> 4 | B78: 44560000 | C78: TVA DÉDUCTIBLES | D78: 411804 | E78: 411804 | F78: 411804 | G78: 44561000 | I78: 411804
A79: =+LEFT(B:B) -> 4 | B79: 44561000 | C79: TVA déductible sur revente | D79: -67363166 | E79: -68749166 | F79: 0 | G79: 44561000 | I79: 0
